Workbook

Sheet employees_cleaned
A1: employee_id | B1: gender | C1: age | D1: education | E1: department | F1: job_role | G1: hire_date | H1: manager_id | I1: location | J1: employment_type | K1: attrition_flag | L1: exit_date | M1: salary | N1: bonus | O1: salary_band | P1: avg_engagement_score | Q1: engagement_response_flag | R1: tenure_months | S1: tenure_bucket | T1: avg_performance_rating | U1: avg_band_salary | V1: salary_position | W1: performance_level | X1: pay_performance_index | Y1: pay_performance_index
A2: E100000 | B2: F | C2: 42 | D2: Graduate | E2: Finance | F2: Financial Analyst | G2: 44030 | H2: M274 | I2: Pune | J2: Contract | K2: =_xlfn.XLOOKUP(A2,attrition_cleaned!$A:$A,attrition_cleaned!$B:$B,"Missing") -> No | M2: =_xlfn.XLOOKUP(A2,compensation_cleaned!$A:$A,compensation_cleaned!$B:$B,"Missing") -> 417763 | N2: =_xlfn.XLOOKUP(A2,compensation_cleaned!$A:$A,compensation_cleaned!$C:$C,"Missing") -> 45322 | O2: =_xlfn.XLOOKUP(A2,compensation_cleaned!$A:$A,compensation_cleaned!$D:$D,"Missing") -> L1 | P2: =_xlfn.XLOOKUP(A2,engagement_pivot!$A:$A,engagement_pivot!$B:$B,"Missing") -> 2.3333333 | Q2: =IF( _xlfn.XLOOKUP(A2, engagement_pivot!A:A, engagement_pivot!C:C, 0) > 0, "Yes", "No" ) -> Yes | R2: =IF(K2="Yes",DATEDIF(G2,L2,"M"),DATEDIF(G2,DATE(2023,12,31),"M")) -> 41 | S2: =IF(R2<=12,"0–12 months", IF(R2<=36,"13–36 months","37+ months")) -> 37+ months | T2: =_xlfn.XLOOKUP(A2,performance_pivot!$A:$A,performance_pivot!$B:$B,"Missing") -> 4 | U2: =_xlfn.XLOOKUP(A2,compensation_cleaned!$A:$A,compensation_cleaned!$F:$F,"Missing") -> 499723.04 | V2: =IF(M2>U2,"Above Avg Pay","Below Avg Pay") -> Below Avg Pay | W2: =IF(T2>=4,"High Performer","Low/Avg Performer") -> High Performer | Y2: =IF( AND(V2="Above Avg Pay",W2="High Performer"),"Well Aligned", IF( AND(V2="Below Avg Pay",W2="High Performer"),"Underpaid High Performer", IF( AND(V2="Above Avg Pay",W2="Low/Avg Performer"),"Overpaid Low Performer", "Low Pay & Low Performance" ) ) ) -> Underpaid High Performer | AE2: Total
A3: E100001 | B3: M | C3: 23 | D3: Postgraduate | E3: Finance | F3: Accountant | G3: 42866 | H3: M237 | I3: Hyderabad | J3: Full-time | K3: =_xlfn.XLOOKUP(A3,attrition_cleaned!$A:$A,attrition_cleaned!$B:$B,"Missing") -> No | M3: =_xlfn.XLOOKUP(A3,compensation_cleaned!$A:$A,compensation_cleaned!$B:$B,"Missing") -> 1114335 | N3: =_xlfn.XLOOKUP(A3,compensation_cleaned!$A:$A,compensation_cleaned!$C:$C,"Missing") -> 92842 | O3: =_xlfn.XLOOKUP(A3,compensation_cleaned!$A:$A,compensation_cleaned!$D:$D,"Missing") -> L3 | P3: =_xlfn.XLOOKUP(A3,engagement_pivot!$A:$A,engagement_pivot!$B:$B,"Missing") -> 2.6666667 | Q3: =IF( _xlfn.XLOOKUP(A3, engagement_pivot!A:A, engagement_pivot!C:C, 0) > 0, "Yes", "No" ) -> Yes | R3: =IF(K3="Yes",DATEDIF(G3,L3,"M"),DATEDIF(G3,DATE(2023,12,31),"M")) -> 79 | S3: =IF(R3<=12,"0–12 months", IF(R3<=36,"13–36 months","37+ months")) -> 37+ months | T3: =_xlfn.XLOOKUP(A3,performance_pivot!$A:$A,performance_pivot!$B:$B,"Missing") -> 3.25 | U3: =_xlfn.XLOOKUP(A3,compensation_cleaned!$A:$A,compensation_cleaned!$F:$F,"Missing") -> 1044648.5 | V3: =IF(M3>U3,"Above Avg Pay","Below Avg Pay") -> Above Avg Pay | W3: =IF(T3>=4,"High Performer","Low/Avg Performer") -> Low/Avg Performer | Y3: =IF( AND(V3="Above Avg Pay",W3="High Performer"),"Well Aligned", IF( AND(V3="Below Avg Pay",W3="High Performer"),"Underpaid High Performer", IF( AND(V3="Above Avg Pay",W3="Low/Avg Performer"),"Overpaid Low Performer", "Low Pay & Low Performance" ) ) ) -> Overpaid Low Performer | AD3: High Tenure | AE3: =COUNTIF(S:S,"37+ months") -> 1679
A4: E100002 | B4: M | C4: 33 | D4: Graduate | E4: Operations | F4: Operations Analyst | G4: 43195 | H4: M258 | I4: Hyderabad | J4: Full-time | K4: =_xlfn.XLOOKUP(A4,attrition_cleaned!$A:$A,attrition_cleaned!$B:$B,"Missing") -> No | M4: =_xlfn.XLOOKUP(A4,compensation_cleaned!$A:$A,compensation_cleaned!$B:$B,"Missing") -> 819575 | N4: =_xlfn.XLOOKUP(A4,compensation_cleaned!$A:$A,compensation_cleaned!$C:$C,"Missing") -> 70960 | O4: =_xlfn.XLOOKUP(A4,compensation_cleaned!$A:$A,compensation_cleaned!$D:$D,"Missing") -> L2 | P4: =_xlfn.XLOOKUP(A4,engagement_pivot!$A:$A,engagement_pivot!$B:$B,"Missing") -> 2 | Q4: =IF( _xlfn.XLOOKUP(A4, engagement_pivot!A:A, engagement_pivot!C:C, 0) > 0, "Yes", "No" ) -> Yes | R4: =IF(K4="Yes",DATEDIF(G4,L4,"M"),DATEDIF(G4,DATE(2023,12,31),"M")) -> 68 | S4: =IF(R4<=12,"0–12 months", IF(R4<=36,"13–36 months","37+ months")) -> 37+ months | T4: =_xlfn.XLOOKUP(A4,performance_pivot!$A:$A,performance_pivot!$B:$B,"Missing") -> 3 | U4: =_xlfn.XLOOKUP(A4,compensation_cleaned!$A:$A,compensation_cleaned!$F:$F,"Missing") -> 746435.4 | V4: =IF(M4>U4,"Above Avg Pay","Below Avg Pay") -> Above Avg Pay | W4: =IF(T4>=4,"High Performer","Low/Avg Performer") -> Low/Avg Performer | Y4: =IF( AND(V4="Above Avg Pay",W4="High Performer"),"Well Aligned", IF( AND(V4="Below Avg Pay",W4="High Performer"),"Underpaid High Performer", IF( AND(V4="Above Avg Pay",W4="Low/Avg Performer"),"Overpaid Low Performer", "Low Pay & Low Performance" ) ) ) -> Overpaid Low Performer | AD4: Mid Tenure | AE4: =COUNTIF(S:S,"13–36 months") -> 1048
A5: E100003 | B5: M | C5: 36 | D5: Graduate | E5: Finance | F5: Accountant | G5: 44542 | H5: M307 | I5: Delhi | J5: Full-time | K5: =_xlfn.XLOOKUP(A5,attrition_cleaned!$A:$A,attrition_cleaned!$B:$B,"Missing") -> No | M5: =_xlfn.XLOOKUP(A5,compensation_cleaned!$A:$A,compensation_cleaned!$B:$B,"Missing") -> 485874 | N5: =_xlfn.XLOOKUP(A5,compensation_cleaned!$A:$A,compensation_cleaned!$C:$C,"Missing") -> 29469 | O5: =_xlfn.XLOOKUP(A5,compensation_cleaned!$A:$A,compensation_cleaned!$D:$D,"Missing") -> L1 | P5: =_xlfn.XLOOKUP(A5,engagement_pivot!$A:$A,engagement_pivot!$B:$B,"Missing") -> 2 | Q5: =IF( _xlfn.XLOOKUP(A5, engagement_pivot!A:A, engagement_pivot!C:C, 0) > 0, "Yes", "No" ) -> Yes | R5: =IF(K5="Yes",DATEDIF(G5,L5,"M"),DATEDIF(G5,DATE(2023,12,31),"M")) -> 24 | S5: =IF(R5<=12,"0–12 months", IF(R5<=36,"13–36 months","37+ months")) -> 13–36 months | T5: =_xlfn.XLOOKUP(A5,performance_pivot!$A:$A,performance_pivot!$B:$B,"Missing") -> 4.25 | U5: =_xlfn.XLOOKUP(A5,compensation_cleaned!$A:$A,compensation_cleaned!$F:$F,"Missing") -> 499723.04 | V5: =IF(M5>U5,"Above Avg Pay","Below Avg Pay") -> Below Avg Pay | W5: =IF(T5>=4,"High Performer","Low/Avg Performer") -> High Performer | Y5: =IF( AND(V5="Above Avg Pay",W5="High Performer"),"Well Aligned", IF( AND(V5="Below Avg Pay",W5="High Performer"),"Underpaid High Performer", IF( AND(V5="Above Avg Pay",W5="Low/Avg Performer"),"Overpaid Low Performer", "Low Pay & Low Performance" ) ) ) -> Underpaid High Performer | AD5: Low Tenure | AE5: =COUNTIF(S:S,"0–12 months") -> 473
A6: E100004 | B6: M | C6: 28 | D6: Graduate | E6: Sales | F6: Sales Executive | G6: 43382 | H6: M288 | I6: Delhi | J6: Full-time | K6: =_xlfn.XLOOKUP(A6,attrition_cleaned!$A:$A,attrition_cleaned!$B:$B,"Missing") -> No | M6: =_xlfn.XLOOKUP(A6,compensation_cleaned!$A:$A,compensation_cleaned!$B:$B,"Missing") -> 825704 | N6: =_xlfn.XLOOKUP(A6,compensation_cleaned!$A:$A,compensation_cleaned!$C:$C,"Missing") -> 45542 | O6: =_xlfn.XLOOKUP(A6,compensation_cleaned!$A:$A,compensation_cleaned!$D:$D,"Missing") -> L2 | P6: =_xlfn.XLOOKUP(A6,engagement_pivot!$A:$A,engagement_pivot!$B:$B,"Missing") -> 1.6666667 | Q6: =IF( _xlfn.XLOOKUP(A6, engagement_pivot!A:A, engagement_pivot!C:C, 0) > 0, "Yes", "No" ) -> Yes | R6: =IF(K6="Yes",DATEDIF(G6,L6,"M"),DATEDIF(G6,DATE(2023,12,31),"M")) -> 62 | S6: =IF(R6<=12,"0–12 months", IF(R6<=36,"13–36 months","37+ months")) -> 37+ months | T6: =_xlfn.XLOOKUP(A6,performance_pivot!$A:$A,performance_pivot!$B:$B,"Missing") -> 4 | U6: =_xlfn.XLOOKUP(A6,compensation_cleaned!$A:$A,compensation_cleaned!$F:$F,"Missing") -> 746435.4 | V6: =IF(M6>U6,"Above Avg Pay","Below Avg Pay") -> Above Avg Pay | W6: =IF(T6>=4,"High Performer","Low/Avg Performer") -> High Performer | Y6: =IF( AND(V6="Above Avg Pay",W6="High Performer"),"Well Aligned", IF( AND(V6="Below Avg Pay",W6="High Performer"),"Underpaid High Performer", IF( AND(V6="Above Avg Pay",W6="Low/Avg Performer"),"Overpaid Low Performer", "Low Pay & Low Performance" ) ) ) -> Well Aligned
A7: E100005 | B7: M | C7: 28 | D7: Graduate | E7: HR | F7: HR Executive | G7: 44099 | H7: M207 | I7: Pune | J7: Contract | K7: =_xlfn.XLOOKUP(A7,attrition_cleaned!$A:$A,attrition_cleaned!$B:$B,"Missing") -> No | M7: =_xlfn.XLOOKUP(A7,compensation_cleaned!$A:$A,compensation_cleaned!$B:$B,"Missing") -> 851431 | N7: =_xlfn.XLOOKUP(A7,compensation_cleaned!$A:$A,compensation_cleaned!$C:$C,"Missing") -> 110027 | O7: =_xlfn.XLOOKUP(A7,compensation_cleaned!$A:$A,compensation_cleaned!$D:$D,"Missing") -> L2 | P7: =_xlfn.XLOOKUP(A7,engagement_pivot!$A:$A,engagement_pivot!$B:$B,"Missing") -> 4 | Q7: =IF( _xlfn.XLOOKUP(A7, engagement_pivot!A:A, engagement_pivot!C:C, 0) > 0, "Yes", "No" ) -> Yes | R7: =IF(K7="Yes",DATEDIF(G7,L7,"M"),DATEDIF(G7,DATE(2023,12,31),"M")) -> 39 | S7: =IF(R7<=12,"0–12 months", IF(R7<=36,"13–36 months","37+ months")) -> 37+ months | T7: =_xlfn.XLOOKUP(A7,performance_pivot!$A:$A,performance_pivot!$B:$B,"Missing") -> 4.5 | U7: =_xlfn.XLOOKUP(A7,compensation_cleaned!$A:$A,compensation_cleaned!$F:$F,"Missing") -> 746435.4 | V7: =IF(M7>U7,"Above Avg Pay","Below Avg Pay") -> Above Avg Pay | W7: =IF(T7>=4,"High Performer","Low/Avg Performer") -> High Performer | Y7: =IF( AND(V7="Above Avg Pay",W7="High Performer"),"Well Aligned", IF( AND(V7="Below Avg Pay",W7="High Performer"),"Underpaid High Performer", IF( AND(V7="Above Avg Pay",W7="Low/Avg Performer"),"Overpaid Low Performer", "Low Pay & Low Performance" ) ) ) -> Well Aligned | AE7: Total
A8: E100006 | B8: M | C8: 31 | D8: Graduate | E8: Finance | F8: Accountant | G8: 43757 | H8: M345 | I8: Hyderabad | J8: Full-time | K8: =_xlfn.XLOOKUP(A8,attrition_cleaned!$A:$A,attrition_cleaned!$B:$B,"Missing") -> No | M8: =_xlfn.XLOOKUP(A8,compensation_cleaned!$A:$A,compensation_cleaned!$B:$B,"Missing") -> 660855 | N8: =_xlfn.XLOOKUP(A8,compensation_cleaned!$A:$A,compensation_cleaned!$C:$C,"Missing") -> 53466 | O8: =_xlfn.XLOOKUP(A8,compensation_cleaned!$A:$A,compensation_cleaned!$D:$D,"Missing") -> L2 | P8: =_xlfn.XLOOKUP(A8,engagement_pivot!$A:$A,engagement_pivot!$B:$B,"Missing") -> 5 | Q8: =IF( _xlfn.XLOOKUP(A8, engagement_pivot!A:A, engagement_pivot!C:C, 0) > 0, "Yes", "No" ) -> Yes | R8: =IF(K8="Yes",DATEDIF(G8,L8,"M"),DATEDIF(G8,DATE(2023,12,31),"M")) -> 50 | S8: =IF(R8<=12,"0–12 months", IF(R8<=36,"13–36 months","37+ months")) -> 37+ months | T8: =_xlfn.XLOOKUP(A8,performance_pivot!$A:$A,performance_pivot!$B:$B,"Missing") -> 4 | U8: =_xlfn.XLOOKUP(A8,compensation_cleaned!$A:$A,compensation_cleaned!$F:$F,"Missing") -> 746435.4 | V8: =IF(M8>U8,"Above Avg Pay","Below Avg Pay") -> Below Avg Pay | W8: =IF(T8>=4,"High Performer","Low/Avg Performer") -> High Performer | Y8: =IF( AND(V8="Above Avg Pay",W8="High Performer"),"Well Aligned", IF( AND(V8="Below Avg Pay",W8="High Performer"),"Underpaid High Performer", IF( AND(V8="Above Avg Pay",W8="Low/Avg Performer"),"Overpaid Low Performer", "Low Pay & Low Performance" ) ) ) -> Underpaid High Performer | AD8: Well Aligned | AE8: =COUNTIF(Y:Y,"Well Aligned") -> 622
A9: E100007 | B9: M | C9: 37 | D9: Graduate | E9: HR | F9: HR Business Partner | G9: 43731 | H9: M239 | I9: Mumbai | J9: Full-time | K9: =_xlfn.XLOOKUP(A9,attrition_cleaned!$A:$A,attrition_cleaned!$B:$B,"Missing") -> No | M9: =_xlfn.XLOOKUP(A9,compensation_cleaned!$A:$A,compensation_cleaned!$B:$B,"Missing") -> 1541591 | N9: =_xlfn.XLOOKUP(A9,compensation_cleaned!$A:$A,compensation_cleaned!$C:$C,"Missing") -> 167329 | O9: =_xlfn.XLOOKUP(A9,compensation_cleaned!$A:$A,compensation_cleaned!$D:$D,"Missing") -> L4 | P9: =_xlfn.XLOOKUP(A9,engagement_pivot!$A:$A,engagement_pivot!$B:$B,"Missing") -> 2 | Q9: =IF( _xlfn.XLOOKUP(A9, engagement_pivot!A:A, engagement_pivot!C:C, 0) > 0, "Yes", "No" ) -> Yes | R9: =IF(K9="Yes",DATEDIF(G9,L9,"M"),DATEDIF(G9,DATE(2023,12,31),"M")) -> 51 | S9: =IF(R9<=12,"0–12 months", IF(R9<=36,"13–36 months","37+ months")) -> 37+ months | T9: =_xlfn.XLOOKUP(A9,performance_pivot!$A:$A,performance_pivot!$B:$B,"Missing") -> 4 | U9: =_xlfn.XLOOKUP(A9,compensation_cleaned!$A:$A,compensation_cleaned!$F:$F,"Missing") -> 1044648.5 | V9: =IF(M9>U9,"Above Avg Pay","Below Avg Pay") -> Above Avg Pay | W9: =IF(T9>=4,"High Performer","Low/Avg Performer") -> High Performer | Y9: =IF( AND(V9="Above Avg Pay",W9="High Performer"),"Well Aligned", IF( AND(V9="Below Avg Pay",W9="High Performer"),"Underpaid High Performer", IF( AND(V9="Above Avg Pay",W9="Low/Avg Performer"),"Overpaid Low Performer", "Low Pay & Low Performance" ) ) ) -> Well Aligned | AD9: Underpaid High Performer | AE9: =COUNTIF(Y:Y,"Underpaid High Performer") -> 456
A10: E100008 | B10: M | C10: 34 | D10: Graduate | E10: HR | F10: HR Executive | G10: 43812 | H10: M214 | I10: Mumbai | J10: Full-time | K10: =_xlfn.XLOOKUP(A10,attrition_cleaned!$A:$A,attrition_cleaned!$B:$B,"Missing") -> No | M10: =_xlfn.XLOOKUP(A10,compensation_cleaned!$A:$A,compensation_cleaned!$B:$B,"Missing") -> 418481 | N10: =_xlfn.XLOOKUP(A10,compensation_cleaned!$A:$A,compensation_cleaned!$C:$C,"Missing") -> 38859 | O10: =_xlfn.XLOOKUP(A10,compensation_cleaned!$A:$A,compensation_cleaned!$D:$D,"Missing") -> L1 | P10: =_xlfn.XLOOKUP(A10,engagement_pivot!$A:$A,engagement_pivot!$B:$B,"Missing") -> 2 | Q10: =IF( _xlfn.XLOOKUP(A10, engagement_pivot!A:A, engagement_pivot!C:C, 0) > 0, "Yes", "No" ) -> Yes | R10: =IF(K10="Yes",DATEDIF(G10,L10,"M"),DATEDIF(G10,DATE(2023,12,31),"M")) -> 48 | S10: =IF(R10<=12,"0–12 months", IF(R10<=36,"13–36 months","37+ months")) -> 37+ months | T10: =_xlfn.XLOOKUP(A10,performance_pivot!$A:$A,performance_pivot!$B:$B,"Missing") -> 3.5 | U10: =_xlfn.XLOOKUP(A10,compensation_cleaned!$A:$A,compensation_cleaned!$F:$F,"Missing") -> 499723.04 | V10: =IF(M10>U10,"Above Avg Pay","Below Avg Pay") -> Below Avg Pay | W10: =IF(T10>=4,"High Performer","Low/Avg Performer") -> Low/Avg Performer | Y10: =IF( AND(V10="Above Avg Pay",W10="High Performer"),"Well Aligned", IF( AND(V10="Below Avg Pay",W10="High Performer"),"Underpaid High Performer", IF( AND(V10="Above Avg Pay",W10="Low/Avg Performer"),"Overpaid Low Performer", "Low Pay & Low Performance" ) ) ) -> Low Pay & Low Performance | AD10: Overpaid Low Performer | AE10: =COUNTIF(Y:Y,"Overpaid Low Performer") -> 1230
A11: E100009 | B11: M | C11: 32 | D11: Graduate | E11: IT | F11: Software Engineer | G11: 44763 | H11: M335 | I11: Pune | J11: Full-time | K11: =_xlfn.XLOOKUP(A11,attrition_cleaned!$A:$A,attrition_cleaned!$B:$B,"Missing") -> No | M11: =_xlfn.XLOOKUP(A11,compensation_cleaned!$A:$A,compensation_cleaned!$B:$B,"Missing") -> 757662 | N11: =_xlfn.XLOOKUP(A11,compensation_cleaned!$A:$A,compensation_cleaned!$C:$C,"Missing") -> 97007 | O11: =_xlfn.XLOOKUP(A11,compensation_cleaned!$A:$A,compensation_cleaned!$D:$D,"Missing") -> L2 | P11: =_xlfn.XLOOKUP(A11,engagement_pivot!$A:$A,engagement_pivot!$B:$B,"Missing") -> 3 | Q11: =IF( _xlfn.XLOOKUP(A11, engagement_pivot!A:A, engagement_pivot!C:C, 0) > 0, "Yes", "No" ) -> Yes | R11: =IF(K11="Yes",DATEDIF(G11,L11,"M"),DATEDIF(G11,DATE(2023,12,31),"M")) -> 17 | S11: =IF(R11<=12,"0–12 months", IF(R11<=36,"13–36 months","37+ months")) -> 13–36 months | T11: =_xlfn.XLOOKUP(A11,performance_pivot!$A:$A,performance_pivot!$B:$B,"Missing") -> 4.25 | U11: =_xlfn.XLOOKUP(A11,compensation_cleaned!$A:$A,compensation_cleaned!$F:$F,"Missing") -> 746435.4 | V11: =IF(M11>U11,"Above Avg Pay","Below Avg Pay") -> Above Avg Pay | W11: =IF(T11>=4,"High Performer","Low/Avg Performer") -> High Performer | Y11: =IF( AND(V11="Above Avg Pay",W11="High Performer"),"Well Aligned", IF( AND(V11="Below Avg Pay",W11="High Performer"),"Underpaid High Performer", IF( AND(V11="Above Avg Pay",W11="Low/Avg Performer"),"Overpaid Low Performer", "Low Pay & Low Performance" ) ) ) -> Well Aligned | AD11: Low Pay & Low Performance | AE11: =COUNTIF(Y:Y,"Low Pay & Low Performance") -> 892
A12: E100010 | B12: F | C12: 28 | D12: Postgraduate | E12: Sales | F12: Sales Executive | G12: 45014 | H12: M211 | I12: Hyderabad | J12: Full-time | K12: =_xlfn.XLOOKUP(A12,attrition_cleaned!$A:$A,attrition_cleaned!$B:$B,"Missing") -> No | M12: =_xlfn.XLOOKUP(A12,compensation_cleaned!$A:$A,compensation_cleaned!$B:$B,"Missing") -> 1192590 | N12: =_xlfn.XLOOKUP(A12,compensation_cleaned!$A:$A,compensation_cleaned!$C:$C,"Missing") -> 110531 | O12: =_xlfn.XLOOKUP(A12,compensation_cleaned!$A:$A,compensation_cleaned!$D:$D,"Missing") -> L3 | P12: =_xlfn.XLOOKUP(A12,engagement_pivot!$A:$A,engagement_pivot!$B:$B,"Missing") -> 5 | Q12: =IF( _xlfn.XLOOKUP(A12, engagement_pivot!A:A, engagement_pivot!C:C, 0) > 0, "Yes", "No" ) -> Yes | R12: =IF(K12="Yes",DATEDIF(G12,L12,"M"),DATEDIF(G12,DATE(2023,12,31),"M")) -> 9 | S12: =IF(R12<=12,"0–12 months", IF(R12<=36,"13–36 months","37+ months")) -> 0–12 months | T12: =_xlfn.XLOOKUP(A12,performance_pivot!$A:$A,performance_pivot!$B:$B,"Missing") -> 3 | U12: =_xlfn.XLOOKUP(A12,compensation_cleaned!$A:$A,compensation_cleaned!$F:$F,"Missing") -> 1044648.5 | V12: =IF(M12>U12,"Above Avg Pay","Below Avg Pay") -> Above Avg Pay | W12: =IF(T12>=4,"High Performer","Low/Avg Performer") -> Low/Avg Performer | Y12: =IF( AND(V12="Above Avg Pay",W12="High Performer"),"Well Aligned", IF( AND(V12="Below Avg Pay",W12="High Performer"),"Underpaid High Performer", IF( AND(V12="Above Avg Pay",W12="Low/Avg Performer"),"Overpaid Low Performer", "Low Pay & Low Performance" ) ) ) -> Overpaid Low Performer
A13: E100011 | B13: M | C13: 24 | D13: Graduate | E13: Operations | F13: Operations Analyst | G13: 44631 | H13: M300 | I13: Chennai | J13: Full-time | K13: =_xlfn.XLOOKUP(A13,attrition_cleaned!$A:$A,attrition_cleaned!$B:$B,"Missing") -> No | M13: =_xlfn.XLOOKUP(A13,compensation_cleaned!$A:$A,compensation_cleaned!$B:$B,"Missing") -> 1160686 | N13: =_xlfn.XLOOKUP(A13,compensation_cleaned!$A:$A,compensation_cleaned!$C:$C,"Missing") -> 70987 | O13: =_xlfn.XLOOKUP(A13,compensation_cleaned!$A:$A,compensation_cleaned!$D:$D,"Missing") -> L3 | P13: =_xlfn.XLOOKUP(A13,engagement_pivot!$A:$A,engagement_pivot!$B:$B,"Missing") -> 2.5 | Q13: =IF( _xlfn.XLOOKUP(A13, engagement_pivot!A:A, engagement_pivot!C:C, 0) > 0, "Yes", "No" ) -> Yes | R13: =IF(K13="Yes",DATEDIF(G13,L13,"M"),DATEDIF(G13,DATE(2023,12,31),"M")) -> 21 | S13: =IF(R13<=12,"0–12 months", IF(R13<=36,"13–36 months","37+ months")) -> 13–36 months | T13: =_xlfn.XLOOKUP(A13,performance_pivot!$A:$A,performance_pivot!$B:$B,"Missing") -> 3 | U13: =_xlfn.XLOOKUP(A13,compensation_cleaned!$A:$A,compensation_cleaned!$F:$F,"Missing") -> 1044648.5 | V13: =IF(M13>U13,"Above Avg Pay","Below Avg Pay") -> Above Avg Pay | W13: =IF(T13>=4,"High Performer","Low/Avg Performer") -> Low/Avg Performer | Y13: =IF( AND(V13="Above Avg Pay",W13="High Performer"),"Well Aligned", IF( AND(V13="Below Avg Pay",W13="High Performer"),"Underpaid High Performer", IF( AND(V13="Above Avg Pay",W13="Low/Avg Performer"),"Overpaid Low Performer", "Low Pay & Low Performance" ) ) ) -> Overpaid Low Performer
A14: E100012 | B14: F | C14: 28 | D14: Graduate | E14: Operations | F14: Process Manager | G14: 43238 | H14: M214 | I14: Hyderabad | J14: Full-time | K14: =_xlfn.XLOOKUP(A14,attrition_cleaned!$A:$A,attrition_cleaned!$B:$B,"Missing") -> No | M14: =_xlfn.XLOOKUP(A14,compensation_cleaned!$A:$A,compensation_cleaned!$B:$B,"Missing") -> 1060040 | N14: =_xlfn.XLOOKUP(A14,compensation_cleaned!$A:$A,compensation_cleaned!$C:$C,"Missing") -> 94821 | O14: =_xlfn.XLOOKUP(A14,compensation_cleaned!$A:$A,compensation_cleaned!$D:$D,"Missing") -> L3 | P14: =_xlfn.XLOOKUP(A14,engagement_pivot!$A:$A,engagement_pivot!$B:$B,"Missing") -> 2 | Q14: =IF( _xlfn.XLOOKUP(A14, engagement_pivot!A:A, engagement_pivot!C:C, 0) > 0, "Yes", "No" ) -> Yes | R14: =IF(K14="Yes",DATEDIF(G14,L14,"M"),DATEDIF(G14,DATE(2023,12,31),"M")) -> 67 | S14: =IF(R14<=12,"0–12 months", IF(R14<=36,"13–36 months","37+ months")) -> 37+ months | T14: =_xlfn.XLOOKUP(A14,performance_pivot!$A:$A,performance_pivot!$B:$B,"Missing") -> 3.75 | U14: =_xlfn.XLOOKUP(A14,compensation_cleaned!$A:$A,compensation_cleaned!$F:$F,"Missing") -> 1044648.5 | V14: =IF(M14>U14,"Above Avg Pay","Below Avg Pay") -> Above Avg Pay | W14: =IF(T14>=4,"High Performer","Low/Avg Performer") -> Low/Avg Performer | Y14: =IF( AND(V14="Above Avg Pay",W14="High Performer"),"Well Aligned", IF( AND(V14="Below Avg Pay",W14="High Performer"),"Underpaid High Performer", IF( AND(V14="Above Avg Pay",W14="Low/Avg Performer"),"Overpaid Low Performer", "Low Pay & Low Performance" ) ) ) -> Overpaid Low Performer
A15: E100013 | B15: F | C15: 41 | D15: Graduate | E15: Operations | F15: Operations Analyst | G15: 43599 | H15: M331 | I15: Chennai | J15: Full-time | K15: =_xlfn.XLOOKUP(A15,attrition_cleaned!$A:$A,attrition_cleaned!$B:$B,"Missing") -> No | M15: =_xlfn.XLOOKUP(A15,compensation_cleaned!$A:$A,compensation_cleaned!$B:$B,"Missing") -> 1163414 | N15: =_xlfn.XLOOKUP(A15,compensation_cleaned!$A:$A,compensation_cleaned!$C:$C,"Missing") -> 116603 | O15: =_xlfn.XLOOKUP(A15,compensation_cleaned!$A:$A,compensation_cleaned!$D:$D,"Missing") -> L3 | P15: =_xlfn.XLOOKUP(A15,engagement_pivot!$A:$A,engagement_pivot!$B:$B,"Missing") -> 4 | Q15: =IF( _xlfn.XLOOKUP(A15, engagement_pivot!A:A, engagement_pivot!C:C, 0) > 0, "Yes", "No" ) -> Yes | R15: =IF(K15="Yes",DATEDIF(G15,L15,"M"),DATEDIF(G15,DATE(2023,12,31),"M")) -> 55 | S15: =IF(R15<=12,"0–12 months", IF(R15<=36,"13–36 months","37+ months")) -> 37+ months | T15: =_xlfn.XLOOKUP(A15,performance_pivot!$A:$A,performance_pivot!$B:$B,"Missing") -> 2 | U15: =_xlfn.XLOOKUP(A15,compensation_cleaned!$A:$A,compensation_cleaned!$F:$F,"Missing") -> 1044648.5 | V15: =IF(M15>U15,"Above Avg Pay","Below Avg Pay") -> Above Avg Pay | W15: =IF(T15>=4,"High Performer","Low/Avg Performer") -> Low/Avg Performer | Y15: =IF( AND(V15="Above Avg Pay",W15="High Performer"),"Well Aligned", IF( AND(V15="Below Avg Pay",W15="High Performer"),"Underpaid High Performer", IF( AND(V15="Above Avg Pay",W15="Low/Avg Performer"),"Overpaid Low Performer", "Low Pay & Low Performance" ) ) ) -> Overpaid Low Performer
A16: E100014 | B16: M | C16: 28 | D16: Graduate | E16: Operations | F16: Operations Analyst | G16: 43276 | H16: M285 | I16: Delhi | J16: Contract | K16: =_xlfn.XLOOKUP(A16,attrition_cleaned!$A:$A,attrition_cleaned!$B:$B,"Missing") -> No | M16: =_xlfn.XLOOKUP(A16,compensation_cleaned!$A:$A,compensation_cleaned!$B:$B,"Missing") -> 532901 | N16: =_xlfn.XLOOKUP(A16,compensation_cleaned!$A:$A,compensation_cleaned!$C:$C,"Missing") -> 57968 | O16: =_xlfn.XLOOKUP(A16,compensation_cleaned!$A:$A,compensation_cleaned!$D:$D,"Missing") -> L1 | P16: =_xlfn.XLOOKUP(A16,engagement_pivot!$A:$A,engagement_pivot!$B:$B,"Missing") -> 4.5 | Q16: =IF( _xlfn.XLOOKUP(A16, engagement_pivot!A:A, engagement_pivot!C:C, 0) > 0, "Yes", "No" ) -> Yes | R16: =IF(K16="Yes",DATEDIF(G16,L16,"M"),DATEDIF(G16,DATE(2023,12,31),"M")) -> 66 | S16: =IF(R16<=12,"0–12 months", IF(R16<=36,"13–36 months","37+ months")) -> 37+ months | T16: =_xlfn.XLOOKUP(A16,performance_pivot!$A:$A,performance_pivot!$B:$B,"Missing") -> 3.75 | U16: =_xlfn.XLOOKUP(A16,compensation_cleaned!$A:$A,compensation_cleaned!$F:$F,"Missing") -> 499723.04 | V16: =IF(M16>U16,"Above Avg Pay","Below Avg Pay") -> Above Avg Pay | W16: =IF(T16>=4,"High Performer","Low/Avg Performer") -> Low/Avg Performer | Y16: =IF( AND(V16="Above Avg Pay",W16="High Performer"),"Well Aligned", IF( AND(V16="Below Avg Pay",W16="High Performer"),"Underpaid High Performer", IF( AND(V16="Above Avg Pay",W16="Low/Avg Performer"),"Overpaid Low Performer", "Low Pay & Low Performance" ) ) ) -> Overpaid Low Performer
A17: E100015 | B17: F | C17: 33 | D17: Graduate | E17: Operations | F17: Process Manager | G17: 43531 | H17: M274 | I17: Hyderabad | J17: Full-time | K17: =_xlfn.XLOOKUP(A17,attrition_cleaned!$A:$A,attrition_cleaned!$B:$B,"Missing") -> No | M17: =_xlfn.XLOOKUP(A17,compensation_cleaned!$A:$A,compensation_cleaned!$B:$B,"Missing") -> 422000 | N17: =_xlfn.XLOOKUP(A17,compensation_cleaned!$A:$A,compensation_cleaned!$C:$C,"Missing") -> 29980 | O17: =_xlfn.XLOOKUP(A17,compensation_cleaned!$A:$A,compensation_cleaned!$D:$D,"Missing") -> L1 | P17: =_xlfn.XLOOKUP(A17,engagement_pivot!$A:$A,engagement_pivot!$B:$B,"Missing") -> 3.5 | Q17: =IF( _xlfn.XLOOKUP(A17, engagement_pivot!A:A, engagement_pivot!C:C, 0) > 0, "Yes", "No" ) -> Yes | R17: =IF(K17="Yes",DATEDIF(G17,L17,"M"),DATEDIF(G17,DATE(2023,12,31),"M")) -> 57 | S17: =IF(R17<=12,"0–12 months", IF(R17<=36,"13–36 months","37+ months")) -> 37+ months | T17: =_xlfn.XLOOKUP(A17,performance_pivot!$A:$A,performance_pivot!$B:$B,"Missing") -> 4 | U17: =_xlfn.XLOOKUP(A17,compensation_cleaned!$A:$A,compensation_cleaned!$F:$F,"Missing") -> 499723.04 | V17: =IF(M17>U17,"Above Avg Pay","Below Avg Pay") -> Below Avg Pay | W17: =IF(T17>=4,"High Performer","Low/Avg Performer") -> High Performer | Y17: =IF( AND(V17="Above Avg Pay",W17="High Performer"),"Well Aligned", IF( AND(V17="Below Avg Pay",W17="High Performer"),"Underpaid High Performer", IF( AND(V17="Above Avg Pay",W17="Low/Avg Performer"),"Overpaid Low Performer", "Low Pay & Low Performance" ) ) ) -> Underpaid High Performer
A18: E100016 | B18: M | C18: 41 | D18: Graduate | E18: IT | F18: QA Engineer | G18: 44973 | H18: M202 | I18: Chennai | J18: Full-time | K18: =_xlfn.XLOOKUP(A18,attrition_cleaned!$A:$A,attrition_cleaned!$B:$B,"Missing") -> No | M18: =_xlfn.XLOOKUP(A18,compensation_cleaned!$A:$A,compensation_cleaned!$B:$B,"Missing") -> 747356 | N18: =_xlfn.XLOOKUP(A18,compensation_cleaned!$A:$A,compensation_cleaned!$C:$C,"Missing") -> 104502 | O18: =_xlfn.XLOOKUP(A18,compensation_cleaned!$A:$A,compensation_cleaned!$D:$D,"Missing") -> L2 | P18: =_xlfn.XLOOKUP(A18,engagement_pivot!$A:$A,engagement_pivot!$B:$B,"Missing") -> 3 | Q18: =IF( _xlfn.XLOOKUP(A18, engagement_pivot!A:A, engagement_pivot!C:C, 0) > 0, "Yes", "No" ) -> Yes | R18: =IF(K18="Yes",DATEDIF(G18,L18,"M"),DATEDIF(G18,DATE(2023,12,31),"M")) -> 10 | S18: =IF(R18<=12,"0–12 months", IF(R18<=36,"13–36 months","37+ months")) -> 0–12 months | T18: =_xlfn.XLOOKUP(A18,performance_pivot!$A:$A,performance_pivot!$B:$B,"Missing") -> 4 | U18: =_xlfn.XLOOKUP(A18,compensation_cleaned!$A:$A,compensation_cleaned!$F:$F,"Missing") -> 746435.4 | V18: =IF(M18>U18,"Above Avg Pay","Below Avg Pay") -> Above Avg Pay | W18: =IF(T18>=4,"High Performer","Low/Avg Performer") -> High Performer | Y18: =IF( AND(V18="Above Avg Pay",W18="High Performer"),"Well Aligned", IF( AND(V18="Below Avg Pay",W18="High Performer"),"Underpaid High Performer", IF( AND(V18="Above Avg Pay",W18="Low/Avg Performer"),"Overpaid Low Performer", "Low Pay & Low Performance" ) ) ) -> Well Aligned
A19: E100017 | B19: M | C19: 36 | D19: Graduate | E19: IT | F19: Data Analyst | G19: 43993 | H19: M295 | I19: Bangalore | J19: Full-time | K19: =_xlfn.XLOOKUP(A19,attrition_cleaned!$A:$A,attrition_cleaned!$B:$B,"Missing") -> No | M19: =_xlfn.XLOOKUP(A19,compensation_cleaned!$A:$A,compensation_cleaned!$B:$B,"Missing") -> 1102364 | N19: =_xlfn.XLOOKUP(A19,compensation_cleaned!$A:$A,compensation_cleaned!$C:$C,"Missing") -> 120500 | O19: =_xlfn.XLOOKUP(A19,compensation_cleaned!$A:$A,compensation_cleaned!$D:$D,"Missing") -> L3 | P19: =_xlfn.XLOOKUP(A19,engagement_pivot!$A:$A,engagement_pivot!$B:$B,"Missing") -> 4 | Q19: =IF( _xlfn.XLOOKUP(A19, engagement_pivot!A:A, engagement_pivot!C:C, 0) > 0, "Yes", "No" ) -> Yes | R19: =IF(K19="Yes",DATEDIF(G19,L19,"M"),DATEDIF(G19,DATE(2023,12,31),"M")) -> 42 | S19: =IF(R19<=12,"0–12 months", IF(R19<=36,"13–36 months","37+ months")) -> 37+ months | T19: =_xlfn.XLOOKUP(A19,performance_pivot!$A:$A,performance_pivot!$B:$B,"Missing") -> 4 | U19: =_xlfn.XLOOKUP(A19,compensation_cleaned!$A:$A,compensation_cleaned!$F:$F,"Missing") -> 1044648.5 | V19: =IF(M19>U19,"Above Avg Pay","Below Avg Pay") -> Above Avg Pay | W19: =IF(T19>=4,"High Performer","Low/Avg Performer") -> High Performer | Y19: =IF( AND(V19="Above Avg Pay",W19="High Performer"),"Well Aligned", IF( AND(V19="Below Avg Pay",W19="High Performer"),"Underpaid High Performer", IF( AND(V19="Above Avg Pay",W19="Low/Avg Performer"),"Overpaid Low Performer", "Low Pay & Low Performance" ) ) ) -> Well Aligned
A20: E100018 | B20: M | C20: 28 | D20: Graduate | E20: IT | F20: Data Analyst | G20: 43299 | H20: M312 | I20: Mumbai | J20: Full-time | K20: =_xlfn.XLOOKUP(A20,attrition_cleaned!$A:$A,attrition_cleaned!$B:$B,"Missing") -> No | M20: =_xlfn.XLOOKUP(A20,compensation_cleaned!$A:$A,compensation_cleaned!$B:$B,"Missing") -> 1109204 | N20: =_xlfn.XLOOKUP(A20,compensation_cleaned!$A:$A,compensation_cleaned!$C:$C,"Missing") -> 129090 | O20: =_xlfn.XLOOKUP(A20,compensation_cleaned!$A:$A,compensation_cleaned!$D:$D,"Missing") -> L3 | P20: =_xlfn.XLOOKUP(A20,engagement_pivot!$A:$A,engagement_pivot!$B:$B,"Missing") -> 4 | Q20: =IF( _xlfn.XLOOKUP(A20, engagement_pivot!A:A, engagement_pivot!C:C, 0) > 0, "Yes", "No" ) -> Yes | R20: =IF(K20="Yes",DATEDIF(G20,L20,"M"),DATEDIF(G20,DATE(2023,12,31),"M")) -> 65 | S20: =IF(R20<=12,"0–12 months", IF(R20<=36,"13–36 months","37+ months")) -> 37+ months | T20: =_xlfn.XLOOKUP(A20,performance_pivot!$A:$A,performance_pivot!$B:$B,"Missing") -> 3 | U20: =_xlfn.XLOOKUP(A20,compensation_cleaned!$A:$A,compensation_cleaned!$F:$F,"Missing") -> 1044648.5 | V20: =IF(M20>U20,"Above Avg Pay","Below Avg Pay") -> Above Avg Pay | W20: =IF(T20>=4,"High Performer","Low/Avg Performer") -> Low/Avg Performer | Y20: =IF( AND(V20="Above Avg Pay",W20="High Performer"),"Well Aligned", IF( AND(V20="Below Avg Pay",W20="High Performer"),"Underpaid High Performer", IF( AND(V20="Above Avg Pay",W20="Low/Avg Performer"),"Overpaid Low Performer", "Low Pay & Low Performance" ) ) ) -> Overpaid Low Performer
A21: E100019 | B21: F | C21: 43 | D21: Graduate | E21: IT | F21: QA Engineer | G21: 44896 | H21: M328 | I21: Pune | J21: Full-time | K21: =_xlfn.XLOOKUP(A21,attrition_cleaned!$A:$A,attrition_cleaned!$B:$B,"Missing") -> No | M21: =_xlfn.XLOOKUP(A21,compensation_cleaned!$A:$A,compensation_cleaned!$B:$B,"Missing") -> 574279 | N21: =_xlfn.XLOOKUP(A21,compensation_cleaned!$A:$A,compensation_cleaned!$C:$C,"Missing") -> 46639 | O21: =_xlfn.XLOOKUP(A21,compensation_cleaned!$A:$A,compensation_cleaned!$D:$D,"Missing") -> L1 | P21: =_xlfn.XLOOKUP(A21,engagement_pivot!$A:$A,engagement_pivot!$B:$B,"Missing") -> 1 | Q21: =IF( _xlfn.XLOOKUP(A21, engagement_pivot!A:A, engagement_pivot!C:C, 0) > 0, "Yes", "No" ) -> Yes | R21: =IF(K21="Yes",DATEDIF(G21,L21,"M"),DATEDIF(G21,DATE(2023,12,31),"M")) -> 12 | S21: =IF(R21<=12,"0–12 months", IF(R21<=36,"13–36 months","37+ months")) -> 0–12 months | T21: =_xlfn.XLOOKUP(A21,performance_pivot!$A:$A,performance_pivot!$B:$B,"Missing") -> 3 | U21: =_xlfn.XLOOKUP(A21,compensation_cleaned!$A:$A,compensation_cleaned!$F:$F,"Missing") -> 499723.04 | V21: =IF(M21>U21,"Above Avg Pay","Below Avg Pay") -> Above Avg Pay | W21: =IF(T21>=4,"High Performer","Low/Avg Performer") -> Low/Avg Performer | Y21: =IF( AND(V21="Above Avg Pay",W21="High Performer"),"Well Aligned", IF( AND(V21="Below Avg Pay",W21="High Performer"),"Underpaid High Performer", IF( AND(V21="Above Avg Pay",W21="Low/Avg Performer"),"Overpaid Low Performer", "Low Pay & Low Performance" ) ) ) -> Overpaid Low Performer
A22: E100020 | B22: M | C22: 44 | D22: Postgraduate | E22: Operations | F22: Process Manager | G22: 44431 | H22: M322 | I22: Bangalore | J22: Full-time | K22: =_xlfn.XLOOKUP(A22,attrition_cleaned!$A:$A,attrition_cleaned!$B:$B,"Missing") -> No | M22: =_xlfn.XLOOKUP(A22,compensation_cleaned!$A:$A,compensation_cleaned!$B:$B,"Missing") -> 476531 | N22: =_xlfn.XLOOKUP(A22,compensation_cleaned!$A:$A,compensation_cleaned!$C:$C,"Missing") -> 56986 | O22: =_xlfn.XLOOKUP(A22,compensation_cleaned!$A:$A,compensation_cleaned!$D:$D,"Missing") -> L1 | P22: =_xlfn.XLOOKUP(A22,engagement_pivot!$A:$A,engagement_pivot!$B:$B,"Missing") -> 1.5 | Q22: =IF( _xlfn.XLOOKUP(A22, engagement_pivot!A:A, engagement_pivot!C:C, 0) > 0, "Yes", "No" ) -> Yes | R22: =IF(K22="Yes",DATEDIF(G22,L22,"M"),DATEDIF(G22,DATE(2023,12,31),"M")) -> 28 | S22: =IF(R22<=12,"0–12 months", IF(R22<=36,"13–36 months","37+ months")) -> 13–36 months | T22: =_xlfn.XLOOKUP(A22,performance_pivot!$A:$A,performance_pivot!$B:$B,"Missing") -> 3 | U22: =_xlfn.XLOOKUP(A22,compensation_cleaned!$A:$A,compensation_cleaned!$F:$F,"Missing") -> 499723.04 | V22: =IF(M22>U22,"Above Avg Pay","Below Avg Pay") -> Below Avg Pay | W22: =IF(T22>=4,"High Performer","Low/Avg Performer") -> Low/Avg Performer | Y22: =IF( AND(V22="Above Avg Pay",W22="High Performer"),"Well Aligned", IF( AND(V22="Below Avg Pay",W22="High Performer"),"Underpaid High Performer", IF( AND(V22="Above Avg Pay",W22="Low/Avg Performer"),"Overpaid Low Performer", "Low Pay & Low Performance" ) ) ) -> Low Pay & Low Performance
A23: E100021 | B23: M | C23: 37 | D23: Postgraduate | E23: Operations | F23: Process Manager | G23: 42933 | H23: M323 | I23: Pune | J23: Full-time | K23: =_xlfn.XLOOKUP(A23,attrition_cleaned!$A:$A,attrition_cleaned!$B:$B,"Missing") -> No | M23: =_xlfn.XLOOKUP(A23,compensation_cleaned!$A:$A,compensation_cleaned!$B:$B,"Missing") -> 524971 | N23: =_xlfn.XLOOKUP(A23,compensation_cleaned!$A:$A,compensation_cleaned!$C:$C,"Missing") -> 58749 | O23: =_xlfn.XLOOKUP(A23,compensation_cleaned!$A:$A,compensation_cleaned!$D:$D,"Missing") -> L1 | P23: =_xlfn.XLOOKUP(A23,engagement_pivot!$A:$A,engagement_pivot!$B:$B,"Missing") -> 2.6666667 | Q23: =IF( _xlfn.XLOOKUP(A23, engagement_pivot!A:A, engagement_pivot!C:C, 0) > 0, "Yes", "No" ) -> Yes | R23: =IF(K23="Yes",DATEDIF(G23,L23,"M"),DATEDIF(G23,DATE(2023,12,31),"M")) -> 77 | S23: =IF(R23<=12,"0–12 months", IF(R23<=36,"13–36 months","37+ months")) -> 37+ months | T23: =_xlfn.XLOOKUP(A23,performance_pivot!$A:$A,performance_pivot!$B:$B,"Missing") -> 2.6666667 | U23: =_xlfn.XLOOKUP(A23,compensation_cleaned!$A:$A,compensation_cleaned!$F:$F,"Missing") -> 499723.04 | V23: =IF(M23>U23,"Above Avg Pay","Below Avg Pay") -> Above Avg Pay | W23: =IF(T23>=4,"High Performer","Low/Avg Performer") -> Low/Avg Performer | Y23: =IF( AND(V23="Above Avg Pay",W23="High Performer"),"Well Aligned", IF( AND(V23="Below Avg Pay",W23="High Performer"),"Underpaid High Performer", IF( AND(V23="Above Avg Pay",W23="Low/Avg Performer"),"Overpaid Low Performer", "Low Pay & Low Performance" ) ) ) -> Overpaid Low Performer
A24: E100022 | B24: M | C24: 25 | D24: Graduate | E24: Operations | F24: Operations Analyst | G24: 43395 | H24: M346 | I24: Delhi | J24: Full-time | K24: =_xlfn.XLOOKUP(A24,attrition_cleaned!$A:$A,attrition_cleaned!$B:$B,"Missing") -> Yes | L24: 44899 | M24: =_xlfn.XLOOKUP(A24,compensation_cleaned!$A:$A,compensation_cleaned!$B:$B,"Missing") -> 694503 | N24: =_xlfn.XLOOKUP(A24,compensation_cleaned!$A:$A,compensation_cleaned!$C:$C,"Missing") -> 56111 | O24: =_xlfn.XLOOKUP(A24,compensation_cleaned!$A:$A,compensation_cleaned!$D:$D,"Missing") -> L2 | P24: =_xlfn.XLOOKUP(A24,engagement_pivot!$A:$A,engagement_pivot!$B:$B,"Missing") -> 4 | Q24: =IF( _xlfn.XLOOKUP(A24, engagement_pivot!A:A, engagement_pivot!C:C, 0) > 0, "Yes", "No" ) -> Yes | R24: =IF(K24="Yes",DATEDIF(G24,L24,"M"),DATEDIF(G24,DATE(2023,12,31),"M")) -> 49 | S24: =IF(R24<=12,"0–12 months", IF(R24<=36,"13–36 months","37+ months")) -> 37+ months | T24: =_xlfn.XLOOKUP(A24,performance_pivot!$A:$A,performance_pivot!$B:$B,"Missing") -> 2.3333333 | U24: =_xlfn.XLOOKUP(A24,compensation_cleaned!$A:$A,compensation_cleaned!$F:$F,"Missing") -> 746435.4 | V24: =IF(M24>U24,"Above Avg Pay","Below Avg Pay") -> Below Avg Pay | W24: =IF(T24>=4,"High Performer","Low/Avg Performer") -> Low/Avg Performer | Y24: =IF( AND(V24="Above Avg Pay",W24="High Performer"),"Well Aligned", IF( AND(V24="Below Avg Pay",W24="High Performer"),"Underpaid High Performer", IF( AND(V24="Above Avg Pay",W24="Low/Avg Performer"),"Overpaid Low Performer", "Low Pay & Low Performance" ) ) ) -> Low Pay & Low Performance
A25: E100023 | B25: M | C25: 39 | D25: Postgraduate | E25: Finance | F25: Financial Analyst | G25: 44695 | H25: M210 | I25: Delhi | J25: Full-time | K25: =_xlfn.XLOOKUP(A25,attrition_cleaned!$A:$A,attrition_cleaned!$B:$B,"Missing") -> No | M25: =_xlfn.XLOOKUP(A25,compensation_cleaned!$A:$A,compensation_cleaned!$B:$B,"Missing") -> 637439 | N25: =_xlfn.XLOOKUP(A25,compensation_cleaned!$A:$A,compensation_cleaned!$C:$C,"Missing") -> 69877 | O25: =_xlfn.XLOOKUP(A25,compensation_cleaned!$A:$A,compensation_cleaned!$D:$D,"Missing") -> L2 | P25: =_xlfn.XLOOKUP(A25,engagement_pivot!$A:$A,engagement_pivot!$B:$B,"Missing") -> 4 | Q25: =IF( _xlfn.XLOOKUP(A25, engagement_pivot!A:A, engagement_pivot!C:C, 0) > 0, "Yes", "No" ) -> Yes | R25: =IF(K25="Yes",DATEDIF(G25,L25,"M"),DATEDIF(G25,DATE(2023,12,31),"M")) -> 19 | S25: =IF(R25<=12,"0–12 months", IF(R25<=36,"13–36 months","37+ months")) -> 13–36 months | T25: =_xlfn.XLOOKUP(A25,performance_pivot!$A:$A,performance_pivot!$B:$B,"Missing") -> 3.5 | U25: =_xlfn.XLOOKUP(A25,compensation_cleaned!$A:$A,compensation_cleaned!$F:$F,"Missing") -> 746435.4 | V25: =IF(M25>U25,"Above Avg Pay","Below Avg Pay") -> Below Avg Pay | W25: =IF(T25>=4,"High Performer","Low/Avg Performer") -> Low/Avg Performer | Y25: =IF( AND(V25="Above Avg Pay",W25="High Performer"),"Well Aligned", IF( AND(V25="Below Avg Pay",W25="High Performer"),"Underpaid High Performer", IF( AND(V25="Above Avg Pay",W25="Low/Avg Performer"),"Overpaid Low Performer", "Low Pay & Low Performance" ) ) ) -> Low Pay & Low Performance
A26: E100024 | B26: F | C26: 24 | D26: Graduate | E26: HR | F26: HR Executive | G26: 44174 | H26: M343 | I26: Hyderabad | J26: Contract | K26: =_xlfn.XLOOKUP(A26,attrition_cleaned!$A:$A,attrition_cleaned!$B:$B,"Missing") -> No | M26: =_xlfn.XLOOKUP(A26,compensation_cleaned!$A:$A,compensation_cleaned!$B:$B,"Missing") -> 716079 | N26: =_xlfn.XLOOKUP(A26,compensation_cleaned!$A:$A,compensation_cleaned!$C:$C,"Missing") -> 63086 | O26: =_xlfn.XLOOKUP(A26,compensation_cleaned!$A:$A,compensation_cleaned!$D:$D,"Missing") -> L2 | P26: =_xlfn.XLOOKUP(A26,engagement_pivot!$A:$A,engagement_pivot!$B:$B,"Missing") -> 2.3333333 | Q26: =IF( _xlfn.XLOOKUP(A26, engagement_pivot!A:A, engagement_pivot!C:C, 0) > 0, "Yes", "No" ) -> Yes | R26: =IF(K26="Yes",DATEDIF(G26,L26,"M"),DATEDIF(G26,DATE(2023,12,31),"M")) -> 36 | S26: =IF(R26<=12,"0–12 months", IF(R26<=36,"13–36 months","37+ months")) -> 13–36 months | T26: =_xlfn.XLOOKUP(A26,performance_pivot!$A:$A,performance_pivot!$B:$B,"Missing") -> 3.6666667 | U26: =_xlfn.XLOOKUP(A26,compensation_cleaned!$A:$A,compensation_cleaned!$F:$F,"Missing") -> 746435.4 | V26: =IF(M26>U26,"Above Avg Pay","Below Avg Pay") -> Below Avg Pay | W26: =IF(T26>=4,"High Performer","Low/Avg Performer") -> Low/Avg Performer | Y26: =IF( AND(V26="Above Avg Pay",W26="High Performer"),"Well Aligned", IF( AND(V26="Below Avg Pay",W26="High Performer"),"Underpaid High Performer", IF( AND(V26="Above Avg Pay",W26="Low/Avg Performer"),"Overpaid Low Performer", "Low Pay & Low Performance" ) ) ) -> Low Pay & Low Performance
A27: E100025 | B27: M | C27: 37 | D27: Postgraduate | E27: Finance | F27: Accountant | G27: 43616 | H27: M236 | I27: Pune | J27: Full-time | K27: =_xlfn.XLOOKUP(A27,attrition_cleaned!$A:$A,attrition_cleaned!$B:$B,"Missing") -> Yes | L27: 44569 | M27: =_xlfn.XLOOKUP(A27,compensation_cleaned!$A:$A,compensation_cleaned!$B:$B,"Missing") -> 768411 | N27: =_xlfn.XLOOKUP(A27,compensation_cleaned!$A:$A,compensation_cleaned!$C:$C,"Missing") -> 94536 | O27: =_xlfn.XLOOKUP(A27,compensation_cleaned!$A:$A,compensation_cleaned!$D:$D,"Missing") -> L2 | P27: =_xlfn.XLOOKUP(A27,engagement_pivot!$A:$A,engagement_pivot!$B:$B,"Missing") -> 1 | Q27: =IF( _xlfn.XLOOKUP(A27, engagement_pivot!A:A, engagement_pivot!C:C, 0) > 0, "Yes", "No" ) -> Yes | R27: =IF(K27="Yes",DATEDIF(G27,L27,"M"),DATEDIF(G27,DATE(2023,12,31),"M")) -> 31 | S27: =IF(R27<=12,"0–12 months", IF(R27<=36,"13–36 months","37+ months")) -> 13–36 months | T27: =_xlfn.XLOOKUP(A27,performance_pivot!$A:$A,performance_pivot!$B:$B,"Missing") -> 4 | U27: =_xlfn.XLOOKUP(A27,compensation_cleaned!$A:$A,compensation_cleaned!$F:$F,"Missing") -> 746435.4 | V27: =IF(M27>U27,"Above Avg Pay","Below Avg Pay") -> Above Avg Pay | W27: =IF(T27>=4,"High Performer","Low/Avg Performer") -> High Performer | Y27: =IF( AND(V27="Above Avg Pay",W27="High Performer"),"Well Aligned", IF( AND(V27="Below Avg Pay",W27="High Performer"),"Underpaid High Performer", IF( AND(V27="Above Avg Pay",W27="Low/Avg Performer"),"Overpaid Low Performer", "Low Pay & Low Performance" ) ) ) -> Well Aligned
A28: E100026 | B28: F | C28: 24 | D28: Postgraduate | E28: IT | F28: QA Engineer | G28: 44418 | H28: M253 | I28: Bangalore | J28: Full-time | K28: =_xlfn.XLOOKUP(A28,attrition_cleaned!$A:$A,attrition_cleaned!$B:$B,"Missing") -> No | M28: =_xlfn.XLOOKUP(A28,compensation_cleaned!$A:$A,compensation_cleaned!$B:$B,"Missing") -> 715565 | N28: =_xlfn.XLOOKUP(A28,compensation_cleaned!$A:$A,compensation_cleaned!$C:$C,"Missing") -> 81470 | O28: =_xlfn.XLOOKUP(A28,compensation_cleaned!$A:$A,compensation_cleaned!$D:$D,"Missing") -> L2 | P28: =_xlfn.XLOOKUP(A28,engagement_pivot!$A:$A,engagement_pivot!$B:$B,"Missing") -> 3.5 | Q28: =IF( _xlfn.XLOOKUP(A28, engagement_pivot!A:A, engagement_pivot!C:C, 0) > 0, "Yes", "No" ) -> Yes | R28: =IF(K28="Yes",DATEDIF(G28,L28,"M"),DATEDIF(G28,DATE(2023,12,31),"M")) -> 28 | S28: =IF(R28<=12,"0–12 months", IF(R28<=36,"13–36 months","37+ months")) -> 13–36 months | T28: =_xlfn.XLOOKUP(A28,performance_pivot!$A:$A,performance_pivot!$B:$B,"Missing") -> 4.25 | U28: =_xlfn.XLOOKUP(A28,compensation_cleaned!$A:$A,compensation_cleaned!$F:$F,"Missing") -> 746435.4 | V28: =IF(M28>U28,"Above Avg Pay","Below Avg Pay") -> Below Avg Pay | W28: =IF(T28>=4,"High Performer","Low/Avg Performer") -> High Performer | Y28: =IF( AND(V28="Above Avg Pay",W28="High Performer"),"Well Aligned", IF( AND(V28="Below Avg Pay",W28="High Performer"),"Underpaid High Performer", IF( AND(V28="Above Avg Pay",W28="Low/Avg Performer"),"Overpaid Low Performer", "Low Pay & Low Performance" ) ) ) -> Underpaid High Performer
A29: E100027 | B29: F | C29: 41 | D29: Graduate | E29: Sales | F29: Sales Executive | G29: 44179 | H29: M311 | I29: Chennai | J29: Contract | K29: =_xlfn.XLOOKUP(A29,attrition_cleaned!$A:$A,attrition_cleaned!$B:$B,"Missing") -> No | M29: =_xlfn.XLOOKUP(A29,compensation_cleaned!$A:$A,compensation_cleaned!$B:$B,"Missing") -> 901095 | N29: =_xlfn.XLOOKUP(A29,compensation_cleaned!$A:$A,compensation_cleaned!$C:$C,"Missing") -> 102199 | O29: =_xlfn.XLOOKUP(A29,compensation_cleaned!$A:$A,compensation_cleaned!$D:$D,"Missing") -> L3 | P29: =_xlfn.XLOOKUP(A29,engagement_pivot!$A:$A,engagement_pivot!$B:$B,"Missing") -> 3.5 | Q29: =IF( _xlfn.XLOOKUP(A29, engagement_pivot!A:A, engagement_pivot!C:C, 0) > 0, "Yes", "No" ) -> Yes | R29: =IF(K29="Yes",DATEDIF(G29,L29,"M"),DATEDIF(G29,DATE(2023,12,31),"M")) -> 36 | S29: =IF(R29<=12,"0–12 months", IF(R29<=36,"13–36 months","37+ months")) -> 13–36 months | T29: =_xlfn.XLOOKUP(A29,performance_pivot!$A:$A,performance_pivot!$B:$B,"Missing") -> 2.5 | U29: =_xlfn.XLOOKUP(A29,compensation_cleaned!$A:$A,compensation_cleaned!$F:$F,"Missing") -> 1044648.5 | V29: =IF(M29>U29,"Above Avg Pay","Below Avg Pay") -> Below Avg Pay | W29: =IF(T29>=4,"High Performer","Low/Avg Performer") -> Low/Avg Performer | Y29: =IF( AND(V29="Above Avg Pay",W29="High Performer"),"Well Aligned", IF( AND(V29="Below Avg Pay",W29="High Performer"),"Underpaid High Performer", IF( AND(V29="Above Avg Pay",W29="Low/Avg Performer"),"Overpaid Low Performer", "Low Pay & Low Performance" ) ) ) -> Low Pay & Low Performance
A30: E100028 | B30: M | C30: 23 | D30: Postgraduate | E30: IT | F30: Software Engineer | G30: 44655 | H30: M267 | I30: Bangalore | J30: Full-time | K30: =_xlfn.XLOOKUP(A30,attrition_cleaned!$A:$A,attrition_cleaned!$B:$B,"Missing") -> No | M30: =_xlfn.XLOOKUP(A30,compensation_cleaned!$A:$A,compensation_cleaned!$B:$B,"Missing") -> 1537237 | N30: =_xlfn.XLOOKUP(A30,compensation_cleaned!$A:$A,compensation_cleaned!$C:$C,"Missing") -> 224170 | O30: =_xlfn.XLOOKUP(A30,compensation_cleaned!$A:$A,compensation_cleaned!$D:$D,"Missing") -> L4 | P30: =_xlfn.XLOOKUP(A30,engagement_pivot!$A:$A,engagement_pivot!$B:$B,"Missing") -> 3.5 | Q30: =IF( _xlfn.XLOOKUP(A30, engagement_pivot!A:A, engagement_pivot!C:C, 0) > 0, "Yes", "No" ) -> Yes | R30: =IF(K30="Yes",DATEDIF(G30,L30,"M"),DATEDIF(G30,DATE(2023,12,31),"M")) -> 20 | S30: =IF(R30<=12,"0–12 months", IF(R30<=36,"13–36 months","37+ months")) -> 13–36 months | T30: =_xlfn.XLOOKUP(A30,performance_pivot!$A:$A,performance_pivot!$B:$B,"Missing") -> 3.5 | U30: =_xlfn.XLOOKUP(A30,compensation_cleaned!$A:$A,compensation_cleaned!$F:$F,"Missing") -> 1044648.5 | V30: =IF(M30>U30,"Above Avg Pay","Below Avg Pay") -> Above Avg Pay | W30: =IF(T30>=4,"High Performer","Low/Avg Performer") -> Low/Avg Performer | Y30: =IF( AND(V30="Above Avg Pay",W30="High Performer"),"Well Aligned", IF( AND(V30="Below Avg Pay",W30="High Performer"),"Underpaid High Performer", IF( AND(V30="Above Avg Pay",W30="Low/Avg Performer"),"Overpaid Low Performer", "Low Pay & Low Performance" ) ) ) -> Overpaid Low Performer
A31: E100029 | B31: F | C31: 24 | D31: Postgraduate | E31: Finance | F31: Accountant | G31: 44655 | H31: M232 | I31: Delhi | J31: Full-time | K31: =_xlfn.XLOOKUP(A31,attrition_cleaned!$A:$A,attrition_cleaned!$B:$B,"Missing") -> No | M31: =_xlfn.XLOOKUP(A31,compensation_cleaned!$A:$A,compensation_cleaned!$B:$B,"Missing") -> 1506029 | N31: =_xlfn.XLOOKUP(A31,compensation_cleaned!$A:$A,compensation_cleaned!$C:$C,"Missing") -> 171792 | O31: =_xlfn.XLOOKUP(A31,compensation_cleaned!$A:$A,compensation_cleaned!$D:$D,"Missing") -> L4 | P31: =_xlfn.XLOOKUP(A31,engagement_pivot!$A:$A,engagement_pivot!$B:$B,"Missing") -> 3.3333333 | Q31: =IF( _xlfn.XLOOKUP(A31, engagement_pivot!A:A, engagement_pivot!C:C, 0) > 0, "Yes", "No" ) -> Yes | R31: =IF(K31="Yes",DATEDIF(G31,L31,"M"),DATEDIF(G31,DATE(2023,12,31),"M")) -> 20 | S31: =IF(R31<=12,"0–12 months", IF(R31<=36,"13–36 months","37+ months")) -> 13–36 months | T31: =_xlfn.XLOOKUP(A31,performance_pivot!$A:$A,performance_pivot!$B:$B,"Missing") -> 3.3333333 | U31: =_xlfn.XLOOKUP(A31,compensation_cleaned!$A:$A,compensation_cleaned!$F:$F,"Missing") -> 1044648.5 | V31: =IF(M31>U31,"Above Avg Pay","Below Avg Pay") -> Above Avg Pay | W31: =IF(T31>=4,"High Performer","Low/Avg Performer") -> Low/Avg Performer | Y31: =IF( AND(V31="Above Avg Pay",W31="High Performer"),"Well Aligned", IF( AND(V31="Below Avg Pay",W31="High Performer"),"Underpaid High Performer", IF( AND(V31="Above Avg Pay",W31="Low/Avg Performer"),"Overpaid Low Performer", "Low Pay & Low Performance" ) ) ) -> Overpaid Low Performer
A32: E100030 | B32: F | C32: 23 | D32: Graduate | E32: Operations | F32: Operations Analyst | G32: 45221 | H32: M296 | I32: Delhi | J32: Full-time | K32: =_xlfn.XLOOKUP(A32,attrition_cleaned!$A:$A,attrition_cleaned!$B:$B,"Missing") -> No | M32: =_xlfn.XLOOKUP(A32,compensation_cleaned!$A:$A,compensation_cleaned!$B:$B,"Missing") -> 1330865 | N32: =_xlfn.XLOOKUP(A32,compensation_cleaned!$A:$A,compensation_cleaned!$C:$C,"Missing") -> 86298 | O32: =_xlfn.XLOOKUP(A32,compensation_cleaned!$A:$A,compensation_cleaned!$D:$D,"Missing") -> L4 | P32: =_xlfn.XLOOKUP(A32,engagement_pivot!$A:$A,engagement_pivot!$B:$B,"Missing") -> 5 | Q32: =IF( _xlfn.XLOOKUP(A32, engagement_pivot!A:A, engagement_pivot!C:C, 0) > 0, "Yes", "No" ) -> Yes | R32: =IF(K32="Yes",DATEDIF(G32,L32,"M"),DATEDIF(G32,DATE(2023,12,31),"M")) -> 2 | S32: =IF(R32<=12,"0–12 months", IF(R32<=36,"13–36 months","37+ months")) -> 0–12 months | T32: =_xlfn.XLOOKUP(A32,performance_pivot!$A:$A,performance_pivot!$B:$B,"Missing") -> 3 | U32: =_xlfn.XLOOKUP(A32,compensation_cleaned!$A:$A,compensation_cleaned!$F:$F,"Missing") -> 1044648.5 | V32: =IF(M32>U32,"Above Avg Pay","Below Avg Pay") -> Above Avg Pay | W32: =IF(T32>=4,"High Performer","Low/Avg Performer") -> Low/Avg Performer | Y32: =IF( AND(V32="Above Avg Pay",W32="High Performer"),"Well Aligned", IF( AND(V32="Below Avg Pay",W32="High Performer"),"Underpaid High Performer", IF( AND(V32="Above Avg Pay",W32="Low/Avg Performer"),"Overpaid Low Performer", "Low Pay & Low Performance" ) ) ) -> Overpaid Low Performer
A33: E100031 | B33: M | C33: 24 | D33: Postgraduate | E33: IT | F33: Software Engineer | G33: 43551 | H33: M216 | I33: Delhi | J33: Contract | K33: =_xlfn.XLOOKUP(A33,attrition_cleaned!$A:$A,attrition_cleaned!$B:$B,"Missing") -> Yes | L33: 44718 | M33: =_xlfn.XLOOKUP(A33,compensation_cleaned!$A:$A,compensation_cleaned!$B:$B,"Missing") -> 1214015 | N33: =_xlfn.XLOOKUP(A33,compensation_cleaned!$A:$A,compensation_cleaned!$C:$C,"Missing") -> 135971 | O33: =_xlfn.XLOOKUP(A33,compensation_cleaned!$A:$A,compensation_cleaned!$D:$D,"Missing") -> L4 | P33: =_xlfn.XLOOKUP(A33,engagement_pivot!$A:$A,engagement_pivot!$B:$B,"Missing") -> 3 | Q33: =IF( _xlfn.XLOOKUP(A33, engagement_pivot!A:A, engagement_pivot!C:C, 0) > 0, "Yes", "No" ) -> Yes | R33: =IF(K33="Yes",DATEDIF(G33,L33,"M"),DATEDIF(G33,DATE(2023,12,31),"M")) -> 38 | S33: =IF(R33<=12,"0–12 months", IF(R33<=36,"13–36 months","37+ months")) -> 37+ months | T33: =_xlfn.XLOOKUP(A33,performance_pivot!$A:$A,performance_pivot!$B:$B,"Missing") -> 2.5 | U33: =_xlfn.XLOOKUP(A33,compensation_cleaned!$A:$A,compensation_cleaned!$F:$F,"Missing") -> 1044648.5 | V33: =IF(M33>U33,"Above Avg Pay","Below Avg Pay") -> Above Avg Pay | W33: =IF(T33>=4,"High Performer","Low/Avg Performer") -> Low/Avg Performer | Y33: =IF( AND(V33="Above Avg Pay",W33="High Performer"),"Well Aligned", IF( AND(V33="Below Avg Pay",W33="High Performer"),"Underpaid High Performer", IF( AND(V33="Above Avg Pay",W33="Low/Avg Performer"),"Overpaid Low Performer", "Low Pay & Low Performance" ) ) ) -> Overpaid Low Performer
A34: E100032 | B34: F | C34: 26 | D34: Postgraduate | E34: Operations | F34: Process Manager | G34: 44882 | H34: M245 | I34: Mumbai | J34: Full-time | K34: =_xlfn.XLOOKUP(A34,attrition_cleaned!$A:$A,attrition_cleaned!$B:$B,"Missing") -> Yes | L34: 45226 | M34: =_xlfn.XLOOKUP(A34,compensation_cleaned!$A:$A,compensation_cleaned!$B:$B,"Missing") -> 905850 | N34: =_xlfn.XLOOKUP(A34,compensation_cleaned!$A:$A,compensation_cleaned!$C:$C,"Missing") -> 53220 | O34: =_xlfn.XLOOKUP(A34,compensation_cleaned!$A:$A,compensation_cleaned!$D:$D,"Missing") -> L3 | P34: =_xlfn.XLOOKUP(A34,engagement_pivot!$A:$A,engagement_pivot!$B:$B,"Missing") -> 4 | Q34: =IF( _xlfn.XLOOKUP(A34, engagement_pivot!A:A, engagement_pivot!C:C, 0) > 0, "Yes", "No" ) -> Yes | R34: =IF(K34="Yes",DATEDIF(G34,L34,"M"),DATEDIF(G34,DATE(2023,12,31),"M")) -> 11 | S34: =IF(R34<=12,"0–12 months", IF(R34<=36,"13–36 months","37+ months")) -> 0–12 months | T34: =_xlfn.XLOOKUP(A34,performance_pivot!$A:$A,performance_pivot!$B:$B,"Missing") -> 3.5 | U34: =_xlfn.XLOOKUP(A34,compensation_cleaned!$A:$A,compensation_cleaned!$F:$F,"Missing") -> 1044648.5 | V34: =IF(M34>U34,"Above Avg Pay","Below Avg Pay") -> Below Avg Pay | W34: =IF(T34>=4,"High Performer","Low/Avg Performer") -> Low/Avg Performer | Y34: =IF( AND(V34="Above Avg Pay",W34="High Performer"),"Well Aligned", IF( AND(V34="Below Avg Pay",W34="High Performer"),"Underpaid High Performer", IF( AND(V34="Above Avg Pay",W34="Low/Avg Performer"),"Overpaid Low Performer", "Low Pay & Low Performance" ) ) ) -> Low Pay & Low Performance
A35: E100033 | B35: M | C35: 42 | D35: Graduate | E35: Finance | F35: Financial Analyst | G35: 43875 | H35: M266 | I35: Hyderabad | J35: Full-time | K35: =_xlfn.XLOOKUP(A35,attrition_cleaned!$A:$A,attrition_cleaned!$B:$B,"Missing") -> Yes | L35: 45626 | M35: =_xlfn.XLOOKUP(A35,compensation_cleaned!$A:$A,compensation_cleaned!$B:$B,"Missing") -> 700865 | N35: =_xlfn.XLOOKUP(A35,compensation_cleaned!$A:$A,compensation_cleaned!$C:$C,"Missing") -> 101103 | O35: =_xlfn.XLOOKUP(A35,compensation_cleaned!$A:$A,compensation_cleaned!$D:$D,"Missing") -> L2 | P35: =_xlfn.XLOOKUP(A35,engagement_pivot!$A:$A,engagement_pivot!$B:$B,"Missing") -> 1 | Q35: =IF( _xlfn.XLOOKUP(A35, engagement_pivot!A:A, engagement_pivot!C:C, 0) > 0, "Yes", "No" ) -> Yes | R35: =IF(K35="Yes",DATEDIF(G35,L35,"M"),DATEDIF(G35,DATE(2023,12,31),"M")) -> 57 | S35: =IF(R35<=12,"0–12 months", IF(R35<=36,"13–36 months","37+ months")) -> 37+ months | T35: =_xlfn.XLOOKUP(A35,performance_pivot!$A:$A,performance_pivot!$B:$B,"Missing") -> 3.5 | U35: =_xlfn.XLOOKUP(A35,compensation_cleaned!$A:$A,compensation_cleaned!$F:$F,"Missing") -> 746435.4 | V35: =IF(M35>U35,"Above Avg Pay","Below Avg Pay") -> Below Avg Pay | W35: =IF(T35>=4,"High Performer","Low/Avg Performer") -> Low/Avg Performer | Y35: =IF( AND(V35="Above Avg Pay",W35="High Performer"),"Well Aligned", IF( AND(V35="Below Avg Pay",W35="High Performer"),"Underpaid High Performer", IF( AND(V35="Above Avg Pay",W35="Low/Avg Performer"),"Overpaid Low Performer", "Low Pay & Low Performance" ) ) ) -> Low Pay & Low Performance
A36: E100034 | B36: M | C36: 39 | D36: Graduate | E36: HR | F36: HR Executive | G36: 44631 | H36: M285 | I36: Hyderabad | J36: Full-time | K36: =_xlfn.XLOOKUP(A36,attrition_cleaned!$A:$A,attrition_cleaned!$B:$B,"Missing") -> No | M36: =_xlfn.XLOOKUP(A36,compensation_cleaned!$A:$A,compensation_cleaned!$B:$B,"Missing") -> 499219 | N36: =_xlfn.XLOOKUP(A36,compensation_cleaned!$A:$A,compensation_cleaned!$C:$C,"Missing") -> 52512 | O36: =_xlfn.XLOOKUP(A36,compensation_cleaned!$A:$A,compensation_cleaned!$D:$D,"Missing") -> L1 | P36: =_xlfn.XLOOKUP(A36,engagement_pivot!$A:$A,engagement_pivot!$B:$B,"Missing") -> 3 | Q36: =IF( _xlfn.XLOOKUP(A36, engagement_pivot!A:A, engagement_pivot!C:C, 0) > 0, "Yes", "No" ) -> Yes | R36: =IF(K36="Yes",DATEDIF(G36,L36,"M"),DATEDIF(G36,DATE(2023,12,31),"M")) -> 21 | S36: =IF(R36<=12,"0–12 months", IF(R36<=36,"13–36 months","37+ months")) -> 13–36 months | T36: =_xlfn.XLOOKUP(A36,performance_pivot!$A:$A,performance_pivot!$B:$B,"Missing") -> 3.6666667 | U36: =_xlfn.XLOOKUP(A36,compensation_cleaned!$A:$A,compensation_cleaned!$F:$F,"Missing") -> 499723.04 | V36: =IF(M36>U36,"Above Avg Pay","Below Avg Pay") -> Below Avg Pay | W36: =IF(T36>=4,"High Performer","Low/Avg Performer") -> Low/Avg Performer | Y36: =IF( AND(V36="Above Avg Pay",W36="High Performer"),"Well Aligned", IF( AND(V36="Below Avg Pay",W36="High Performer"),"Underpaid High Performer", IF( AND(V36="Above Avg Pay",W36="Low/Avg Performer"),"Overpaid Low Performer", "Low Pay & Low Performance" ) ) ) -> Low Pay & Low Performance
A37: E100035 | B37: F | C37: 30 | D37: Postgraduate | E37: HR | F37: HR Business Partner | G37: 43520 | H37: M238 | I37: Mumbai | J37: Full-time | K37: =_xlfn.XLOOKUP(A37,attrition_cleaned!$A:$A,attrition_cleaned!$B:$B,"Missing") -> No | M37: =_xlfn.XLOOKUP(A37,compensation_cleaned!$A:$A,compensation_cleaned!$B:$B,"Missing") -> 928965 | N37: =_xlfn.XLOOKUP(A37,compensation_cleaned!$A:$A,compensation_cleaned!$C:$C,"Missing") -> 106238 | O37: =_xlfn.XLOOKUP(A37,compensation_cleaned!$A:$A,compensation_cleaned!$D:$D,"Missing") -> L3 | P37: =_xlfn.XLOOKUP(A37,engagement_pivot!$A:$A,engagement_pivot!$B:$B,"Missing") -> 3.5 | Q37: =IF( _xlfn.XLOOKUP(A37, engagement_pivot!A:A, engagement_pivot!C:C, 0) > 0, "Yes", "No" ) -> Yes | R37: =IF(K37="Yes",DATEDIF(G37,L37,"M"),DATEDIF(G37,DATE(2023,12,31),"M")) -> 58 | S37: =IF(R37<=12,"0–12 months", IF(R37<=36,"13–36 months","37+ months")) -> 37+ months | T37: =_xlfn.XLOOKUP(A37,performance_pivot!$A:$A,performance_pivot!$B:$B,"Missing") -> 4.5 | U37: =_xlfn.XLOOKUP(A37,compensation_cleaned!$A:$A,compensation_cleaned!$F:$F,"Missing") -> 1044648.5 | V37: =IF(M37>U37,"Above Avg Pay","Below Avg Pay") -> Below Avg Pay | W37: =IF(T37>=4,"High Performer","Low/Avg Performer") -> High Performer | Y37: =IF( AND(V37="Above Avg Pay",W37="High Performer"),"Well Aligned", IF( AND(V37="Below Avg Pay",W37="High Performer"),"Underpaid High Performer", IF( AND(V37="Above Avg Pay",W37="Low/Avg Performer"),"Overpaid Low Performer", "Low Pay & Low Performance" ) ) ) -> Underpaid High Performer
A38: E100036 | B38: F | C38: 34 | D38: Graduate | E38: HR | F38: HR Executive | G38: 44577 | H38: M334 | I38: Bangalore | J38: Full-time | K38: =_xlfn.XLOOKUP(A38,attrition_cleaned!$A:$A,attrition_cleaned!$B:$B,"Missing") -> No | M38: =_xlfn.XLOOKUP(A38,compensation_cleaned!$A:$A,compensation_cleaned!$B:$B,"Missing") -> 617133 | N38: =_xlfn.XLOOKUP(A38,compensation_cleaned!$A:$A,compensation_cleaned!$C:$C,"Missing") -> 88207 | O38: =_xlfn.XLOOKUP(A38,compensation_cleaned!$A:$A,compensation_cleaned!$D:$D,"Missing") -> L2 | P38: =_xlfn.XLOOKUP(A38,engagement_pivot!$A:$A,engagement_pivot!$B:$B,"Missing") -> 2.6666667 | Q38: =IF( _xlfn.XLOOKUP(A38, engagement_pivot!A:A, engagement_pivot!C:C, 0) > 0, "Yes", "No" ) -> Yes | R38: =IF(K38="Yes",DATEDIF(G38,L38,"M"),DATEDIF(G38,DATE(2023,12,31),"M")) -> 23 | S38: =IF(R38<=12,"0–12 months", IF(R38<=36,"13–36 months","37+ months")) -> 13–36 months | T38: =_xlfn.XLOOKUP(A38,performance_pivot!$A:$A,performance_pivot!$B:$B,"Missing") -> 2.75 | U38: =_xlfn.XLOOKUP(A38,compensation_cleaned!$A:$A,compensation_cleaned!$F:$F,"Missing") -> 746435.4 | V38: =IF(M38>U38,"Above Avg Pay","Below Avg Pay") -> Below Avg Pay | W38: =IF(T38>=4,"High Performer","Low/Avg Performer") -> Low/Avg Performer | Y38: =IF( AND(V38="Above Avg Pay",W38="High Performer"),"Well Aligned", IF( AND(V38="Below Avg Pay",W38="High Performer"),"Underpaid High Performer", IF( AND(V38="Above Avg Pay",W38="Low/Avg Performer"),"Overpaid Low Performer", "Low Pay & Low Performance" ) ) ) -> Low Pay & Low Performance
A39: E100037 | B39: M | C39: 40 | D39: Graduate | E39: Finance | F39: Financial Analyst | G39: 43135 | H39: M291 | I39: Hyderabad | J39: Full-time | K39: =_xlfn.XLOOKUP(A39,attrition_cleaned!$A:$A,attrition_cleaned!$B:$B,"Missing") -> Yes | L39: 43750 | M39: =_xlfn.XLOOKUP(A39,compensation_cleaned!$A:$A,compensation_cleaned!$B:$B,"Missing") -> 919399 | N39: =_xlfn.XLOOKUP(A39,compensation_cleaned!$A:$A,compensation_cleaned!$C:$C,"Missing") -> 99092 | O39: =_xlfn.XLOOKUP(A39,compensation_cleaned!$A:$A,compensation_cleaned!$D:$D,"Missing") -> L3 | P39: =_xlfn.XLOOKUP(A39,engagement_pivot!$A:$A,engagement_pivot!$B:$B,"Missing") -> 3.5 | Q39: =IF( _xlfn.XLOOKUP(A39, engagement_pivot!A:A, engagement_pivot!C:C, 0) > 0, "Yes", "No" ) -> Yes | R39: =IF(K39="Yes",DATEDIF(G39,L39,"M"),DATEDIF(G39,DATE(2023,12,31),"M")) -> 20 | S39: =IF(R39<=12,"0–12 months", IF(R39<=36,"13–36 months","37+ months")) -> 13–36 months | T39: =_xlfn.XLOOKUP(A39,performance_pivot!$A:$A,performance_pivot!$B:$B,"Missing") -> 4 | U39: =_xlfn.XLOOKUP(A39,compensation_cleaned!$A:$A,compensation_cleaned!$F:$F,"Missing") -> 1044648.5 | V39: =IF(M39>U39,"Above Avg Pay","Below Avg Pay") -> Below Avg Pay | W39: =IF(T39>=4,"High Performer","Low/Avg Performer") -> High Performer | Y39: =IF( AND(V39="Above Avg Pay",W39="High Performer"),"Well Aligned", IF( AND(V39="Below Avg Pay",W39="High Performer"),"Underpaid High Performer", IF( AND(V39="Above Avg Pay",W39="Low/Avg Performer"),"Overpaid Low Performer", "Low Pay & Low Performance" ) ) ) -> Underpaid High Performer
A40: E100038 | B40: F | C40: 43 | D40: Graduate | E40: Sales | F40: Sales Executive | G40: 43310 | H40: M285 | I40: Bangalore | J40: Full-time | K40: =_xlfn.XLOOKUP(A40,attrition_cleaned!$A:$A,attrition_cleaned!$B:$B,"Missing") -> No | M40: =_xlfn.XLOOKUP(A40,compensation_cleaned!$A:$A,compensation_cleaned!$B:$B,"Missing") -> 508631 | N40: =_xlfn.XLOOKUP(A40,compensation_cleaned!$A:$A,compensation_cleaned!$C:$C,"Missing") -> 44796 | O40: =_xlfn.XLOOKUP(A40,compensation_cleaned!$A:$A,compensation_cleaned!$D:$D,"Missing") -> L1 | P40: =_xlfn.XLOOKUP(A40,engagement_pivot!$A:$A,engagement_pivot!$B:$B,"Missing") -> 2.5 | Q40: =IF( _xlfn.XLOOKUP(A40, engagement_pivot!A:A, engagement_pivot!C:C, 0) > 0, "Yes", "No" ) -> Yes | R40: =IF(K40="Yes",DATEDIF(G40,L40,"M"),DATEDIF(G40,DATE(2023,12,31),"M")) -> 65 | S40: =IF(R40<=12,"0–12 months", IF(R40<=36,"13–36 months","37+ months")) -> 37+ months | T40: =_xlfn.XLOOKUP(A40,performance_pivot!$A:$A,performance_pivot!$B:$B,"Missing") -> 3.25 | U40: =_xlfn.XLOOKUP(A40,compensation_cleaned!$A:$A,compensation_cleaned!$F:$F,"Missing") -> 499723.04 | V40: =IF(M40>U40,"Above Avg Pay","Below Avg Pay") -> Above Avg Pay | W40: =IF(T40>=4,"High Performer","Low/Avg Performer") -> Low/Avg Performer | Y40: =IF( AND(V40="Above Avg Pay",W40="High Performer"),"Well Aligned", IF( AND(V40="Below Avg Pay",W40="High Performer"),"Underpaid High Performer", IF( AND(V40="Above Avg Pay",W40="Low/Avg Performer"),"Overpaid Low Performer", "Low Pay & Low Performance" ) ) ) -> Overpaid Low Performer
A41: E100039 | B41: F | C41: 33 | D41: Postgraduate | E41: Sales | F41: Account Manager | G41: 45047 | H41: M302 | I41: Delhi | J41: Full-time | K41: =_xlfn.XLOOKUP(A41,attrition_cleaned!$A:$A,attrition_cleaned!$B:$B,"Missing") -> No | M41: =_xlfn.XLOOKUP(A41,compensation_cleaned!$A:$A,compensation_cleaned!$B:$B,"Missing") -> 789138 | N41: =_xlfn.XLOOKUP(A41,compensation_cleaned!$A:$A,compensation_cleaned!$C:$C,"Missing") -> 100170 | O41: =_xlfn.XLOOKUP(A41,compensation_cleaned!$A:$A,compensation_cleaned!$D:$D,"Missing") -> L2 | P41: =_xlfn.XLOOKUP(A41,engagement_pivot!$A:$A,engagement_pivot!$B:$B,"Missing") -> 2 | Q41: =IF( _xlfn.XLOOKUP(A41, engagement_pivot!A:A, engagement_pivot!C:C, 0) > 0, "Yes", "No" ) -> Yes | R41: =IF(K41="Yes",DATEDIF(G41,L41,"M"),DATEDIF(G41,DATE(2023,12,31),"M")) -> 7 | S41: =IF(R41<=12,"0–12 months", IF(R41<=36,"13–36 months","37+ months")) -> 0–12 months | T41: =_xlfn.XLOOKUP(A41,performance_pivot!$A:$A,performance_pivot!$B:$B,"Missing") -> 3.25 | U41: =_xlfn.XLOOKUP(A41,compensation_cleaned!$A:$A,compensation_cleaned!$F:$F,"Missing") -> 746435.4 | V41: =IF(M41>U41,"Above Avg Pay","Below Avg Pay") -> Above Avg Pay | W41: =IF(T41>=4,"High Performer","Low/Avg Performer") -> Low/Avg Performer | Y41: =IF( AND(V41="Above Avg Pay",W41="High Performer"),"Well Aligned", IF( AND(V41="Below Avg Pay",W41="High Performer"),"Underpaid High Performer", IF( AND(V41="Above Avg Pay",W41="Low/Avg Performer"),"Overpaid Low Performer", "Low Pay & Low Performance" ) ) ) -> Overpaid Low Performer
A42: E100040 | B42: F | C42: 29 | D42: Postgraduate | E42: Finance | F42: Accountant | G42: 42782 | H42: M212 | I42: Hyderabad | J42: Full-time | K42: =_xlfn.XLOOKUP(A42,attrition_cleaned!$A:$A,attrition_cleaned!$B:$B,"Missing") -> Yes | L42: 44017 | M42: =_xlfn.XLOOKUP(A42,compensation_cleaned!$A:$A,compensation_cleaned!$B:$B,"Missing") -> 454148 | N42: =_xlfn.XLOOKUP(A42,compensation_cleaned!$A:$A,compensation_cleaned!$C:$C,"Missing") -> 23955 | O42: =_xlfn.XLOOKUP(A42,compensation_cleaned!$A:$A,compensation_cleaned!$D:$D,"Missing") -> L1 | P42: =_xlfn.XLOOKUP(A42,engagement_pivot!$A:$A,engagement_pivot!$B:$B,"Missing") -> 4 | Q42: =IF( _xlfn.XLOOKUP(A42, engagement_pivot!A:A, engagement_pivot!C:C, 0) > 0, "Yes", "No" ) -> Yes | R42: =IF(K42="Yes",DATEDIF(G42,L42,"M"),DATEDIF(G42,DATE(2023,12,31),"M")) -> 40 | S42: =IF(R42<=12,"0–12 months", IF(R42<=36,"13–36 months","37+ months")) -> 37+ months | T42: =_xlfn.XLOOKUP(A42,performance_pivot!$A:$A,performance_pivot!$B:$B,"Missing") -> 4 | U42: =_xlfn.XLOOKUP(A42,compensation_cleaned!$A:$A,compensation_cleaned!$F:$F,"Missing") -> 499723.04 | V42: =IF(M42>U42,"Above Avg Pay","Below Avg Pay") -> Below Avg Pay | W42: =IF(T42>=4,"High Performer","Low/Avg Performer") -> High Performer | Y42: =IF( AND(V42="Above Avg Pay",W42="High Performer"),"Well Aligned", IF( AND(V42="Below Avg Pay",W42="High Performer"),"Underpaid High Performer", IF( AND(V42="Above Avg Pay",W42="Low/Avg Performer"),"Overpaid Low Performer", "Low Pay & Low Performance" ) ) ) -> Underpaid High Performer
A43: E100041 | B43: M | C43: 44 | D43: Graduate | E43: Sales | F43: Sales Executive | G43: 42855 | H43: M316 | I43: Chennai | J43: Full-time | K43: =_xlfn.XLOOKUP(A43,attrition_cleaned!$A:$A,attrition_cleaned!$B:$B,"Missing") -> No | M43: =_xlfn.XLOOKUP(A43,compensation_cleaned!$A:$A,compensation_cleaned!$B:$B,"Missing") -> 776322 | N43: =_xlfn.XLOOKUP(A43,compensation_cleaned!$A:$A,compensation_cleaned!$C:$C,"Missing") -> 108642 | O43: =_xlfn.XLOOKUP(A43,compensation_cleaned!$A:$A,compensation_cleaned!$D:$D,"Missing") -> L2 | P43: =_xlfn.XLOOKUP(A43,engagement_pivot!$A:$A,engagement_pivot!$B:$B,"Missing") -> 4 | Q43: =IF( _xlfn.XLOOKUP(A43, engagement_pivot!A:A, engagement_pivot!C:C, 0) > 0, "Yes", "No" ) -> Yes | R43: =IF(K43="Yes",DATEDIF(G43,L43,"M"),DATEDIF(G43,DATE(2023,12,31),"M")) -> 80 | S43: =IF(R43<=12,"0–12 months", IF(R43<=36,"13–36 months","37+ months")) -> 37+ months | T43: =_xlfn.XLOOKUP(A43,performance_pivot!$A:$A,performance_pivot!$B:$B,"Missing") -> 2 | U43: =_xlfn.XLOOKUP(A43,compensation_cleaned!$A:$A,compensation_cleaned!$F:$F,"Missing") -> 746435.4 | V43: =IF(M43>U43,"Above Avg Pay","Below Avg Pay") -> Above Avg Pay | W43: =IF(T43>=4,"High Performer","Low/Avg Performer") -> Low/Avg Performer | Y43: =IF( AND(V43="Above Avg Pay",W43="High Performer"),"Well Aligned", IF( AND(V43="Below Avg Pay",W43="High Performer"),"Underpaid High Performer", IF( AND(V43="Above Avg Pay",W43="Low/Avg Performer"),"Overpaid Low Performer", "Low Pay & Low Performance" ) ) ) -> Overpaid Low Performer
A44: E100042 | B44: M | C44: 22 | D44: Graduate | E44: IT | F44: Software Engineer | G44: 44400 | H44: M295 | I44: Chennai | J44: Full-time | K44: =_xlfn.XLOOKUP(A44,attrition_cleaned!$A:$A,attrition_cleaned!$B:$B,"Missing") -> No | M44: =_xlfn.XLOOKUP(A44,compensation_cleaned!$A:$A,compensation_cleaned!$B:$B,"Missing") -> 1322715 | N44: =_xlfn.XLOOKUP(A44,compensation_cleaned!$A:$A,compensation_cleaned!$C:$C,"Missing") -> 161129 | O44: =_xlfn.XLOOKUP(A44,compensation_cleaned!$A:$A,compensation_cleaned!$D:$D,"Missing") -> L4 | P44: =_xlfn.XLOOKUP(A44,engagement_pivot!$A:$A,engagement_pivot!$B:$B,"Missing") -> 3 | Q44: =IF( _xlfn.XLOOKUP(A44, engagement_pivot!A:A, engagement_pivot!C:C, 0) > 0, "Yes", "No" ) -> Yes | R44: =IF(K44="Yes",DATEDIF(G44,L44,"M"),DATEDIF(G44,DATE(2023,12,31),"M")) -> 29 | S44: =IF(R44<=12,"0–12 months", IF(R44<=36,"13–36 months","37+ months")) -> 13–36 months | T44: =_xlfn.XLOOKUP(A44,performance_pivot!$A:$A,performance_pivot!$B:$B,"Missing") -> 4.5 | U44: =_xlfn.XLOOKUP(A44,compensation_cleaned!$A:$A,compensation_cleaned!$F:$F,"Missing") -> 1044648.5 | V44: =IF(M44>U44,"Above Avg Pay","Below Avg Pay") -> Above Avg Pay | W44: =IF(T44>=4,"High Performer","Low/Avg Performer") -> High Performer | Y44: =IF( AND(V44="Above Avg Pay",W44="High Performer"),"Well Aligned", IF( AND(V44="Below Avg Pay",W44="High Performer"),"Underpaid High Performer", IF( AND(V44="Above Avg Pay",W44="Low/Avg Performer"),"Overpaid Low Performer", "Low Pay & Low Performance" ) ) ) -> Well Aligned
A45: E100043 | B45: F | C45: 28 | D45: Postgraduate | E45: IT | F45: Software Engineer | G45: 43632 | H45: M268 | I45: Chennai | J45: Full-time | K45: =_xlfn.XLOOKUP(A45,attrition_cleaned!$A:$A,attrition_cleaned!$B:$B,"Missing") -> Yes | L45: 44154 | M45: =_xlfn.XLOOKUP(A45,compensation_cleaned!$A:$A,compensation_cleaned!$B:$B,"Missing") -> 727265 | N45: =_xlfn.XLOOKUP(A45,compensation_cleaned!$A:$A,compensation_cleaned!$C:$C,"Missing") -> 86759 | O45: =_xlfn.XLOOKUP(A45,compensation_cleaned!$A:$A,compensation_cleaned!$D:$D,"Missing") -> L2 | P45: =_xlfn.XLOOKUP(A45,engagement_pivot!$A:$A,engagement_pivot!$B:$B,"Missing") -> 3 | Q45: =IF( _xlfn.XLOOKUP(A45, engagement_pivot!A:A, engagement_pivot!C:C, 0) > 0, "Yes", "No" ) -> Yes | R45: =IF(K45="Yes",DATEDIF(G45,L45,"M"),DATEDIF(G45,DATE(2023,12,31),"M")) -> 17 | S45: =IF(R45<=12,"0–12 months", IF(R45<=36,"13–36 months","37+ months")) -> 13–36 months | T45: =_xlfn.XLOOKUP(A45,performance_pivot!$A:$A,performance_pivot!$B:$B,"Missing") -> 5 | U45: =_xlfn.XLOOKUP(A45,compensation_cleaned!$A:$A,compensation_cleaned!$F:$F,"Missing") -> 746435.4 | V45: =IF(M45>U45,"Above Avg Pay","Below Avg Pay") -> Below Avg Pay | W45: =IF(T45>=4,"High Performer","Low/Avg Performer") -> High Performer | Y45: =IF( AND(V45="Above Avg Pay",W45="High Performer"),"Well Aligned", IF( AND(V45="Below Avg Pay",W45="High Performer"),"Underpaid High Performer", IF( AND(V45="Above Avg Pay",W45="Low/Avg Performer"),"Overpaid Low Performer", "Low Pay & Low Performance" ) ) ) -> Underpaid High Performer
A46: E100044 | B46: M | C46: 26 | D46: Graduate | E46: Sales | F46: Account Manager | G46: 42889 | H46: M228 | I46: Chennai | J46: Full-time | K46: =_xlfn.XLOOKUP(A46,attrition_cleaned!$A:$A,attrition_cleaned!$B:$B,"Missing") -> No | M46: =_xlfn.XLOOKUP(A46,compensation_cleaned!$A:$A,compensation_cleaned!$B:$B,"Missing") -> 625829 | N46: =_xlfn.XLOOKUP(A46,compensation_cleaned!$A:$A,compensation_cleaned!$C:$C,"Missing") -> 70097 | O46: =_xlfn.XLOOKUP(A46,compensation_cleaned!$A:$A,compensation_cleaned!$D:$D,"Missing") -> L2 | P46: =_xlfn.XLOOKUP(A46,engagement_pivot!$A:$A,engagement_pivot!$B:$B,"Missing") -> 4.5 | Q46: =IF( _xlfn.XLOOKUP(A46, engagement_pivot!A:A, engagement_pivot!C:C, 0) > 0, "Yes", "No" ) -> Yes | R46: =IF(K46="Yes",DATEDIF(G46,L46,"M"),DATEDIF(G46,DATE(2023,12,31),"M")) -> 78 | S46: =IF(R46<=12,"0–12 months", IF(R46<=36,"13–36 months","37+ months")) -> 37+ months | T46: =_xlfn.XLOOKUP(A46,performance_pivot!$A:$A,performance_pivot!$B:$B,"Missing") -> 4 | U46: =_xlfn.XLOOKUP(A46,compensation_cleaned!$A:$A,compensation_cleaned!$F:$F,"Missing") -> 746435.4 | V46: =IF(M46>U46,"Above Avg Pay","Below Avg Pay") -> Below Avg Pay | W46: =IF(T46>=4,"High Performer","Low/Avg Performer") -> High Performer | Y46: =IF( AND(V46="Above Avg Pay",W46="High Performer"),"Well Aligned", IF( AND(V46="Below Avg Pay",W46="High Performer"),"Underpaid High Performer", IF( AND(V46="Above Avg Pay",W46="Low/Avg Performer"),"Overpaid Low Performer", "Low Pay & Low Performance" ) ) ) -> Underpaid High Performer
A47: E100045 | B47: F | C47: 26 | D47: Graduate | E47: IT | F47: Data Analyst | G47: 44509 | H47: M284 | I47: Delhi | J47: Full-time | K47: =_xlfn.XLOOKUP(A47,attrition_cleaned!$A:$A,attrition_cleaned!$B:$B,"Missing") -> Yes | L47: 46131 | M47: =_xlfn.XLOOKUP(A47,compensation_cleaned!$A:$A,compensation_cleaned!$B:$B,"Missing") -> 871125 | N47: =_xlfn.XLOOKUP(A47,compensation_cleaned!$A:$A,compensation_cleaned!$C:$C,"Missing") -> 126635 | O47: =_xlfn.XLOOKUP(A47,compensation_cleaned!$A:$A,compensation_cleaned!$D:$D,"Missing") -> L2 | P47: =_xlfn.XLOOKUP(A47,engagement_pivot!$A:$A,engagement_pivot!$B:$B,"Missing") -> 1 | Q47: =IF( _xlfn.XLOOKUP(A47, engagement_pivot!A:A, engagement_pivot!C:C, 0) > 0, "Yes", "No" ) -> Yes | R47: =IF(K47="Yes",DATEDIF(G47,L47,"M"),DATEDIF(G47,DATE(2023,12,31),"M")) -> 53 | S47: =IF(R47<=12,"0–12 months", IF(R47<=36,"13–36 months","37+ months")) -> 37+ months | T47: =_xlfn.XLOOKUP(A47,performance_pivot!$A:$A,performance_pivot!$B:$B,"Missing") -> 4.5 | U47: =_xlfn.XLOOKUP(A47,compensation_cleaned!$A:$A,compensation_cleaned!$F:$F,"Missing") -> 746435.4 | V47: =IF(M47>U47,"Above Avg Pay","Below Avg Pay") -> Above Avg Pay | W47: =IF(T47>=4,"High Performer","Low/Avg Performer") -> High Performer | Y47: =IF( AND(V47="Above Avg Pay",W47="High Performer"),"Well Aligned", IF( AND(V47="Below Avg Pay",W47="High Performer"),"Underpaid High Performer", IF( AND(V47="Above Avg Pay",W47="Low/Avg Performer"),"Overpaid Low Performer", "Low Pay & Low Performance" ) ) ) -> Well Aligned
A48: E100046 | B48: M | C48: 26 | D48: Postgraduate | E48: Operations | F48: Operations Analyst | G48: 44521 | H48: M337 | I48: Hyderabad | J48: Contract | K48: =_xlfn.XLOOKUP(A48,attrition_cleaned!$A:$A,attrition_cleaned!$B:$B,"Missing") -> No | M48: =_xlfn.XLOOKUP(A48,compensation_cleaned!$A:$A,compensation_cleaned!$B:$B,"Missing") -> 761452 | N48: =_xlfn.XLOOKUP(A48,compensation_cleaned!$A:$A,compensation_cleaned!$C:$C,"Missing") -> 108984 | O48: =_xlfn.XLOOKUP(A48,compensation_cleaned!$A:$A,compensation_cleaned!$D:$D,"Missing") -> L2 | P48: =_xlfn.XLOOKUP(A48,engagement_pivot!$A:$A,engagement_pivot!$B:$B,"Missing") -> 3 | Q48: =IF( _xlfn.XLOOKUP(A48, engagement_pivot!A:A, engagement_pivot!C:C, 0) > 0, "Yes", "No" ) -> Yes | R48: =IF(K48="Yes",DATEDIF(G48,L48,"M"),DATEDIF(G48,DATE(2023,12,31),"M")) -> 25 | S48: =IF(R48<=12,"0–12 months", IF(R48<=36,"13–36 months","37+ months")) -> 13–36 months | T48: =_xlfn.XLOOKUP(A48,performance_pivot!$A:$A,performance_pivot!$B:$B,"Missing") -> 3 | U48: =_xlfn.XLOOKUP(A48,compensation_cleaned!$A:$A,compensation_cleaned!$F:$F,"Missing") -> 746435.4 | V48: =IF(M48>U48,"Above Avg Pay","Below Avg Pay") -> Above Avg Pay | W48: =IF(T48>=4,"High Performer","Low/Avg Performer") -> Low/Avg Performer | Y48: =IF( AND(V48="Above Avg Pay",W48="High Performer"),"Well Aligned", IF( AND(V48="Below Avg Pay",W48="High Performer"),"Underpaid High Performer", IF( AND(V48="Above Avg Pay",W48="Low/Avg Performer"),"Overpaid Low Performer", "Low Pay & Low Performance" ) ) ) -> Overpaid Low Performer
A49: E100047 | B49: M | C49: 37 | D49: Graduate | E49: IT | F49: Software Engineer | G49: 43251 | H49: M327 | I49: Pune | J49: Full-time | K49: =_xlfn.XLOOKUP(A49,attrition_cleaned!$A:$A,attrition_cleaned!$B:$B,"Missing") -> No | M49: =_xlfn.XLOOKUP(A49,compensation_cleaned!$A:$A,compensation_cleaned!$B:$B,"Missing") -> 870288 | N49: =_xlfn.XLOOKUP(A49,compensation_cleaned!$A:$A,compensation_cleaned!$C:$C,"Missing") -> 73659 | O49: =_xlfn.XLOOKUP(A49,compensation_cleaned!$A:$A,compensation_cleaned!$D:$D,"Missing") -> L2 | P49: =_xlfn.XLOOKUP(A49,engagement_pivot!$A:$A,engagement_pivot!$B:$B,"Missing") -> 3 | Q49: =IF( _xlfn.XLOOKUP(A49, engagement_pivot!A:A, engagement_pivot!C:C, 0) > 0, "Yes", "No" ) -> Yes | R49: =IF(K49="Yes",DATEDIF(G49,L49,"M"),DATEDIF(G49,DATE(2023,12,31),"M")) -> 67 | S49: =IF(R49<=12,"0–12 months", IF(R49<=36,"13–36 months","37+ months")) -> 37+ months | T49: =_xlfn.XLOOKUP(A49,performance_pivot!$A:$A,performance_pivot!$B:$B,"Missing") -> 4 | U49: =_xlfn.XLOOKUP(A49,compensation_cleaned!$A:$A,compensation_cleaned!$F:$F,"Missing") -> 746435.4 | V49: =IF(M49>U49,"Above Avg Pay","Below Avg Pay") -> Above Avg Pay | W49: =IF(T49>=4,"High Performer","Low/Avg Performer") -> High Performer | Y49: =IF( AND(V49="Above Avg Pay",W49="High Performer"),"Well Aligned", IF( AND(V49="Below Avg Pay",W49="High Performer"),"Underpaid High Performer", IF( AND(V49="Above Avg Pay",W49="Low/Avg Performer"),"Overpaid Low Performer", "Low Pay & Low Performance" ) ) ) -> Well Aligned
A50: E100048 | B50: M | C50: 40 | D50: Postgraduate | E50: Finance | F50: Accountant | G50: 45163 | H50: M211 | I50: Pune | J50: Full-time | K50: =_xlfn.XLOOKUP(A50,attrition_cleaned!$A:$A,attrition_cleaned!$B:$B,"Missing") -> No | M50: =_xlfn.XLOOKUP(A50,compensation_cleaned!$A:$A,compensation_cleaned!$B:$B,"Missing") -> 1361068 | N50: =_xlfn.XLOOKUP(A50,compensation_cleaned!$A:$A,compensation_cleaned!$C:$C,"Missing") -> 133993 | O50: =_xlfn.XLOOKUP(A50,compensation_cleaned!$A:$A,compensation_cleaned!$D:$D,"Missing") -> L4 | P50: =_xlfn.XLOOKUP(A50,engagement_pivot!$A:$A,engagement_pivot!$B:$B,"Missing") -> 1 | Q50: =IF( _xlfn.XLOOKUP(A50, engagement_pivot!A:A, engagement_pivot!C:C, 0) > 0, "Yes", "No" ) -> Yes | R50: =IF(K50="Yes",DATEDIF(G50,L50,"M"),DATEDIF(G50,DATE(2023,12,31),"M")) -> 4 | S50: =IF(R50<=12,"0–12 months", IF(R50<=36,"13–36 months","37+ months")) -> 0–12 months | T50: =_xlfn.XLOOKUP(A50,performance_pivot!$A:$A,performance_pivot!$B:$B,"Missing") -> 2.75 | U50: =_xlfn.XLOOKUP(A50,compensation_cleaned!$A:$A,compensation_cleaned!$F:$F,"Missing") -> 1044648.5 | V50: =IF(M50>U50,"Above Avg Pay","Below Avg Pay") -> Above Avg Pay | W50: =IF(T50>=4,"High Performer","Low/Avg Performer") -> Low/Avg Performer | Y50: =IF( AND(V50="Above Avg Pay",W50="High Performer"),"Well Aligned", IF( AND(V50="Below Avg Pay",W50="High Performer"),"Underpaid High Performer", IF( AND(V50="Above Avg Pay",W50="Low/Avg Performer"),"Overpaid Low Performer", "Low Pay & Low Performance" ) ) ) -> Overpaid Low Performer
A51: E100049 | B51: M | C51: 35 | D51: Graduate | E51: HR | F51: HR Executive | G51: 43020 | H51: M234 | I51: Bangalore | J51: Full-time | K51: =_xlfn.XLOOKUP(A51,attrition_cleaned!$A:$A,attrition_cleaned!$B:$B,"Missing") -> No | M51: =_xlfn.XLOOKUP(A51,compensation_cleaned!$A:$A,compensation_cleaned!$B:$B,"Missing") -> 783818 | N51: =_xlfn.XLOOKUP(A51,compensation_cleaned!$A:$A,compensation_cleaned!$C:$C,"Missing") -> 72460 | O51: =_xlfn.XLOOKUP(A51,compensation_cleaned!$A:$A,compensation_cleaned!$D:$D,"Missing") -> L2 | P51: =_xlfn.XLOOKUP(A51,engagement_pivot!$A:$A,engagement_pivot!$B:$B,"Missing") -> 2 | Q51: =IF( _xlfn.XLOOKUP(A51, engagement_pivot!A:A, engagement_pivot!C:C, 0) > 0, "Yes", "No" ) -> Yes | R51: =IF(K51="Yes",DATEDIF(G51,L51,"M"),DATEDIF(G51,DATE(2023,12,31),"M")) -> 74 | S51: =IF(R51<=12,"0–12 months", IF(R51<=36,"13–36 months","37+ months")) -> 37+ months | T51: =_xlfn.XLOOKUP(A51,performance_pivot!$A:$A,performance_pivot!$B:$B,"Missing") -> 3.75 | U51: =_xlfn.XLOOKUP(A51,compensation_cleaned!$A:$A,compensation_cleaned!$F:$F,"Missing") -> 746435.4 | V51: =IF(M51>U51,"Above Avg Pay","Below Avg Pay") -> Above Avg Pay | W51: =IF(T51>=4,"High Performer","Low/Avg Performer") -> Low/Avg Performer | Y51: =IF( AND(V51="Above Avg Pay",W51="High Performer"),"Well Aligned", IF( AND(V51="Below Avg Pay",W51="High Performer"),"Underpaid High Performer", IF( AND(V51="Above Avg Pay",W51="Low/Avg Performer"),"Overpaid Low Performer", "Low Pay & Low Performance" ) ) ) -> Overpaid Low Performer
A52: E100050 | B52: M | C52: 40 | D52: Graduate | E52: Operations | F52: Process Manager | G52: 44361 | H52: M257 | I52: Mumbai | J52: Full-time | K52: =_xlfn.XLOOKUP(A52,attrition_cleaned!$A:$A,attrition_cleaned!$B:$B,"Missing") -> Yes | L52: 44765 | M52: =_xlfn.XLOOKUP(A52,compensation_cleaned!$A:$A,compensation_cleaned!$B:$B,"Missing") -> 1002345 | N52: =_xlfn.XLOOKUP(A52,compensation_cleaned!$A:$A,compensation_cleaned!$C:$C,"Missing") -> 114352 | O52: =_xlfn.XLOOKUP(A52,compensation_cleaned!$A:$A,compensation_cleaned!$D:$D,"Missing") -> L3 | P52: =_xlfn.XLOOKUP(A52,engagement_pivot!$A:$A,engagement_pivot!$B:$B,"Missing") -> 2.6666667 | Q52: =IF( _xlfn.XLOOKUP(A52, engagement_pivot!A:A, engagement_pivot!C:C, 0) > 0, "Yes", "No" ) -> Yes | R52: =IF(K52="Yes",DATEDIF(G52,L52,"M"),DATEDIF(G52,DATE(2023,12,31),"M")) -> 13 | S52: =IF(R52<=12,"0–12 months", IF(R52<=36,"13–36 months","37+ months")) -> 13–36 months | T52: =_xlfn.XLOOKUP(A52,performance_pivot!$A:$A,performance_pivot!$B:$B,"Missing") -> 2.6666667 | U52: =_xlfn.XLOOKUP(A52,compensation_cleaned!$A:$A,compensation_cleaned!$F:$F,"Missing") -> 1044648.5 | V52: =IF(M52>U52,"Above Avg Pay","Below Avg Pay") -> Below Avg Pay | W52: =IF(T52>=4,"High Performer","Low/Avg Performer") -> Low/Avg Performer | Y52: =IF( AND(V52="Above Avg Pay",W52="High Performer"),"Well Aligned", IF( AND(V52="Below Avg Pay",W52="High Performer"),"Underpaid High Performer", IF( AND(V52="Above Avg Pay",W52="Low/Avg Performer"),"Overpaid Low Performer", "Low Pay & Low Performance" ) ) ) -> Low Pay & Low Performance
A53: E100051 | B53: F | C53: 25 | D53: Graduate | E53: Sales | F53: Sales Executive | G53: 43464 | H53: M298 | I53: Delhi | J53: Full-time | K53: =_xlfn.XLOOKUP(A53,attrition_cleaned!$A:$A,attrition_cleaned!$B:$B,"Missing") -> No | M53: =_xlfn.XLOOKUP(A53,compensation_cleaned!$A:$A,compensation_cleaned!$B:$B,"Missing") -> 1421131 | N53: =_xlfn.XLOOKUP(A53,compensation_cleaned!$A:$A,compensation_cleaned!$C:$C,"Missing") -> 105920 | O53: =_xlfn.XLOOKUP(A53,compensation_cleaned!$A:$A,compensation_cleaned!$D:$D,"Missing") -> L4 | P53: =_xlfn.XLOOKUP(A53,engagement_pivot!$A:$A,engagement_pivot!$B:$B,"Missing") -> 3.5 | Q53: =IF( _xlfn.XLOOKUP(A53, engagement_pivot!A:A, engagement_pivot!C:C, 0) > 0, "Yes", "No" ) -> Yes | R53: =IF(K53="Yes",DATEDIF(G53,L53,"M"),DATEDIF(G53,DATE(2023,12,31),"M")) -> 60 | S53: =IF(R53<=12,"0–12 months", IF(R53<=36,"13–36 months","37+ months")) -> 37+ months | T53: =_xlfn.XLOOKUP(A53,performance_pivot!$A:$A,performance_pivot!$B:$B,"Missing") -> 2 | U53: =_xlfn.XLOOKUP(A53,compensation_cleaned!$A:$A,compensation_cleaned!$F:$F,"Missing") -> 1044648.5 | V53: =IF(M53>U53,"Above Avg Pay","Below Avg Pay") -> Above Avg Pay | W53: =IF(T53>=4,"High Performer","Low/Avg Performer") -> Low/Avg Performer | Y53: =IF( AND(V53="Above Avg Pay",W53="High Performer"),"Well Aligned", IF( AND(V53="Below Avg Pay",W53="High Performer"),"Underpaid High Performer", IF( AND(V53="Above Avg Pay",W53="Low/Avg Performer"),"Overpaid Low Performer", "Low Pay & Low Performance" ) ) ) -> Overpaid Low Performer
A54: E100052 | B54: F | C54: 24 | D54: Graduate | E54: Operations | F54: Process Manager | G54: 44284 | H54: M216 | I54: Bangalore | J54: Full-time | K54: =_xlfn.XLOOKUP(A54,attrition_cleaned!$A:$A,attrition_cleaned!$B:$B,"Missing") -> No | M54: =_xlfn.XLOOKUP(A54,compensation_cleaned!$A:$A,compensation_cleaned!$B:$B,"Missing") -> 822835 | N54: =_xlfn.XLOOKUP(A54,compensation_cleaned!$A:$A,compensation_cleaned!$C:$C,"Missing") -> 112504 | O54: =_xlfn.XLOOKUP(A54,compensation_cleaned!$A:$A,compensation_cleaned!$D:$D,"Missing") -> L2 | P54: =_xlfn.XLOOKUP(A54,engagement_pivot!$A:$A,engagement_pivot!$B:$B,"Missing") -> 1 | Q54: =IF( _xlfn.XLOOKUP(A54, engagement_pivot!A:A, engagement_pivot!C:C, 0) > 0, "Yes", "No" ) -> Yes | R54: =IF(K54="Yes",DATEDIF(G54,L54,"M"),DATEDIF(G54,DATE(2023,12,31),"M")) -> 33 | S54: =IF(R54<=12,"0–12 months", IF(R54<=36,"13–36 months","37+ months")) -> 13–36 months | T54: =_xlfn.XLOOKUP(A54,performance_pivot!$A:$A,performance_pivot!$B:$B,"Missing") -> 3 | U54: =_xlfn.XLOOKUP(A54,compensation_cleaned!$A:$A,compensation_cleaned!$F:$F,"Missing") -> 746435.4 | V54: =IF(M54>U54,"Above Avg Pay","Below Avg Pay") -> Above Avg Pay | W54: =IF(T54>=4,"High Performer","Low/Avg Performer") -> Low/Avg Performer | Y54: =IF( AND(V54="Above Avg Pay",W54="High Performer"),"Well Aligned", IF( AND(V54="Below Avg Pay",W54="High Performer"),"Underpaid High Performer", IF( AND(V54="Above Avg Pay",W54="Low/Avg Performer"),"Overpaid Low Performer", "Low Pay & Low Performance" ) ) ) -> Overpaid Low Performer
A55: E100053 | B55: F | C55: 38 | D55: Graduate | E55: IT | F55: Data Analyst | G55: 43132 | H55: M346 | I55: Delhi | J55: Full-time | K55: =_xlfn.XLOOKUP(A55,attrition_cleaned!$A:$A,attrition_cleaned!$B:$B,"Missing") -> No | M55: =_xlfn.XLOOKUP(A55,compensation_cleaned!$A:$A,compensation_cleaned!$B:$B,"Missing") -> 747105 | N55: =_xlfn.XLOOKUP(A55,compensation_cleaned!$A:$A,compensation_cleaned!$C:$C,"Missing") -> 41909 | O55: =_xlfn.XLOOKUP(A55,compensation_cleaned!$A:$A,compensation_cleaned!$D:$D,"Missing") -> L2 | P55: =_xlfn.XLOOKUP(A55,engagement_pivot!$A:$A,engagement_pivot!$B:$B,"Missing") -> 3 | Q55: =IF( _xlfn.XLOOKUP(A55, engagement_pivot!A:A, engagement_pivot!C:C, 0) > 0, "Yes", "No" ) -> Yes | R55: =IF(K55="Yes",DATEDIF(G55,L55,"M"),DATEDIF(G55,DATE(2023,12,31),"M")) -> 70 | S55: =IF(R55<=12,"0–12 months", IF(R55<=36,"13–36 months","37+ months")) -> 37+ months | T55: =_xlfn.XLOOKUP(A55,performance_pivot!$A:$A,performance_pivot!$B:$B,"Missing") -> 3.5 | U55: =_xlfn.XLOOKUP(A55,compensation_cleaned!$A:$A,compensation_cleaned!$F:$F,"Missing") -> 746435.4 | V55: =IF(M55>U55,"Above Avg Pay","Below Avg Pay") -> Above Avg Pay | W55: =IF(T55>=4,"High Performer","Low/Avg Performer") -> Low/Avg Performer | Y55: =IF( AND(V55="Above Avg Pay",W55="High Performer"),"Well Aligned", IF( AND(V55="Below Avg Pay",W55="High Performer"),"Underpaid High Performer", IF( AND(V55="Above Avg Pay",W55="Low/Avg Performer"),"Overpaid Low Performer", "Low Pay & Low Performance" ) ) ) -> Overpaid Low Performer
A56: E100054 | B56: M | C56: 37 | D56: Graduate | E56: Finance | F56: Accountant | G56: 43586 | H56: M298 | I56: Delhi | J56: Full-time | K56: =_xlfn.XLOOKUP(A56,attrition_cleaned!$A:$A,attrition_cleaned!$B:$B,"Missing") -> No | M56: =_xlfn.XLOOKUP(A56,compensation_cleaned!$A:$A,compensation_cleaned!$B:$B,"Missing") -> 760682 | N56: =_xlfn.XLOOKUP(A56,compensation_cleaned!$A:$A,compensation_cleaned!$C:$C,"Missing") -> 70918 | O56: =_xlfn.XLOOKUP(A56,compensation_cleaned!$A:$A,compensation_cleaned!$D:$D,"Missing") -> L2 | P56: =_xlfn.XLOOKUP(A56,engagement_pivot!$A:$A,engagement_pivot!$B:$B,"Missing") -> 4 | Q56: =IF( _xlfn.XLOOKUP(A56, engagement_pivot!A:A, engagement_pivot!C:C, 0) > 0, "Yes", "No" ) -> Yes | R56: =IF(K56="Yes",DATEDIF(G56,L56,"M"),DATEDIF(G56,DATE(2023,12,31),"M")) -> 55 | S56: =IF(R56<=12,"0–12 months", IF(R56<=36,"13–36 months","37+ months")) -> 37+ months | T56: =_xlfn.XLOOKUP(A56,performance_pivot!$A:$A,performance_pivot!$B:$B,"Missing") -> 3 | U56: =_xlfn.XLOOKUP(A56,compensation_cleaned!$A:$A,compensation_cleaned!$F:$F,"Missing") -> 746435.4 | V56: =IF(M56>U56,"Above Avg Pay","Below Avg Pay") -> Above Avg Pay | W56: =IF(T56>=4,"High Performer","Low/Avg Performer") -> Low/Avg Performer | Y56: =IF( AND(V56="Above Avg Pay",W56="High Performer"),"Well Aligned", IF( AND(V56="Below Avg Pay",W56="High Performer"),"Underpaid High Performer", IF( AND(V56="Above Avg Pay",W56="Low/Avg Performer"),"Overpaid Low Performer", "Low Pay & Low Performance" ) ) ) -> Overpaid Low Performer
A57: E100055 | B57: F | C57: 34 | D57: Postgraduate | E57: Sales | F57: Sales Executive | G57: 43903 | H57: M341 | I57: Hyderabad | J57: Full-time | K57: =_xlfn.XLOOKUP(A57,attrition_cleaned!$A:$A,attrition_cleaned!$B:$B,"Missing") -> No | M57: =_xlfn.XLOOKUP(A57,compensation_cleaned!$A:$A,compensation_cleaned!$B:$B,"Missing") -> 982005 | N57: =_xlfn.XLOOKUP(A57,compensation_cleaned!$A:$A,compensation_cleaned!$C:$C,"Missing") -> 113292 | O57: =_xlfn.XLOOKUP(A57,compensation_cleaned!$A:$A,compensation_cleaned!$D:$D,"Missing") -> L3 | P57: =_xlfn.XLOOKUP(A57,engagement_pivot!$A:$A,engagement_pivot!$B:$B,"Missing") -> 3 | Q57: =IF( _xlfn.XLOOKUP(A57, engagement_pivot!A:A, engagement_pivot!C:C, 0) > 0, "Yes", "No" ) -> Yes | R57: =IF(K57="Yes",DATEDIF(G57,L57,"M"),DATEDIF(G57,DATE(2023,12,31),"M")) -> 45 | S57: =IF(R57<=12,"0–12 months", IF(R57<=36,"13–36 months","37+ months")) -> 37+ months | T57: =_xlfn.XLOOKUP(A57,performance_pivot!$A:$A,performance_pivot!$B:$B,"Missing") -> 5 | U57: =_xlfn.XLOOKUP(A57,compensation_cleaned!$A:$A,compensation_cleaned!$F:$F,"Missing") -> 1044648.5 | V57: =IF(M57>U57,"Above Avg Pay","Below Avg Pay") -> Below Avg Pay | W57: =IF(T57>=4,"High Performer","Low/Avg Performer") -> High Performer | Y57: =IF( AND(V57="Above Avg Pay",W57="High Performer"),"Well Aligned", IF( AND(V57="Below Avg Pay",W57="High Performer"),"Underpaid High Performer", IF( AND(V57="Above Avg Pay",W57="Low/Avg Performer"),"Overpaid Low Performer", "Low Pay & Low Performance" ) ) ) -> Underpaid High Performer
A58: E100056 | B58: M | C58: 31 | D58: Postgraduate | E58: Operations | F58: Operations Analyst | G58: 43486 | H58: M344 | I58: Mumbai | J58: Full-time | K58: =_xlfn.XLOOKUP(A58,attrition_cleaned!$A:$A,attrition_cleaned!$B:$B,"Missing") -> Yes | L58: 45042 | M58: =_xlfn.XLOOKUP(A58,compensation_cleaned!$A:$A,compensation_cleaned!$B:$B,"Missing") -> 609132 | N58: =_xlfn.XLOOKUP(A58,compensation_cleaned!$A:$A,compensation_cleaned!$C:$C,"Missing") -> 73972 | O58: =_xlfn.XLOOKUP(A58,compensation_cleaned!$A:$A,compensation_cleaned!$D:$D,"Missing") -> L2 | P58: =_xlfn.XLOOKUP(A58,engagement_pivot!$A:$A,engagement_pivot!$B:$B,"Missing") -> 3 | Q58: =IF( _xlfn.XLOOKUP(A58, engagement_pivot!A:A, engagement_pivot!C:C, 0) > 0, "Yes", "No" ) -> Yes | R58: =IF(K58="Yes",DATEDIF(G58,L58,"M"),DATEDIF(G58,DATE(2023,12,31),"M")) -> 51 | S58: =IF(R58<=12,"0–12 months", IF(R58<=36,"13–36 months","37+ months")) -> 37+ months | T58: =_xlfn.XLOOKUP(A58,performance_pivot!$A:$A,performance_pivot!$B:$B,"Missing") -> 3.5 | U58: =_xlfn.XLOOKUP(A58,compensation_cleaned!$A:$A,compensation_cleaned!$F:$F,"Missing") -> 746435.4 | V58: =IF(M58>U58,"Above Avg Pay","Below Avg Pay") -> Below Avg Pay | W58: =IF(T58>=4,"High Performer","Low/Avg Performer") -> Low/Avg Performer | Y58: =IF( AND(V58="Above Avg Pay",W58="High Performer"),"Well Aligned", IF( AND(V58="Below Avg Pay",W58="High Performer"),"Underpaid High Performer", IF( AND(V58="Above Avg Pay",W58="Low/Avg Performer"),"Overpaid Low Performer", "Low Pay & Low Performance" ) ) ) -> Low Pay & Low Performance
A59: E100057 | B59: M | C59: 23 | D59: Graduate | E59: Operations | F59: Process Manager | G59: 44953 | H59: M282 | I59: Mumbai | J59: Full-time | K59: =_xlfn.XLOOKUP(A59,attrition_cleaned!$A:$A,attrition_cleaned!$B:$B,"Missing") -> No | M59: =_xlfn.XLOOKUP(A59,compensation_cleaned!$A:$A,compensation_cleaned!$B:$B,"Missing") -> 1434089 | N59: =_xlfn.XLOOKUP(A59,compensation_cleaned!$A:$A,compensation_cleaned!$C:$C,"Missing") -> 159489 | O59: =_xlfn.XLOOKUP(A59,compensation_cleaned!$A:$A,compensation_cleaned!$D:$D,"Missing") -> L4 | P59: =_xlfn.XLOOKUP(A59,engagement_pivot!$A:$A,engagement_pivot!$B:$B,"Missing") -> 4.6666667 | Q59: =IF( _xlfn.XLOOKUP(A59, engagement_pivot!A:A, engagement_pivot!C:C, 0) > 0, "Yes", "No" ) -> Yes | R59: =IF(K59="Yes",DATEDIF(G59,L59,"M"),DATEDIF(G59,DATE(2023,12,31),"M")) -> 11 | S59: =IF(R59<=12,"0–12 months", IF(R59<=36,"13–36 months","37+ months")) -> 0–12 months | T59: =_xlfn.XLOOKUP(A59,performance_pivot!$A:$A,performance_pivot!$B:$B,"Missing") -> 2 | U59: =_xlfn.XLOOKUP(A59,compensation_cleaned!$A:$A,compensation_cleaned!$F:$F,"Missing") -> 1044648.5 | V59: =IF(M59>U59,"Above Avg Pay","Below Avg Pay") -> Above Avg Pay | W59: =IF(T59>=4,"High Performer","Low/Avg Performer") -> Low/Avg Performer | Y59: =IF( AND(V59="Above Avg Pay",W59="High Performer"),"Well Aligned", IF( AND(V59="Below Avg Pay",W59="High Performer"),"Underpaid High Performer", IF( AND(V59="Above Avg Pay",W59="Low/Avg Performer"),"Overpaid Low Performer", "Low Pay & Low Performance" ) ) ) -> Overpaid Low Performer
A60: E100058 | B60: F | C60: 34 | D60: Postgraduate | E60: Finance | F60: Financial Analyst | G60: 43246 | H60: M269 | I60: Delhi | J60: Full-time | K60: =_xlfn.XLOOKUP(A60,attrition_cleaned!$A:$A,attrition_cleaned!$B:$B,"Missing") -> Yes | L60: 45044 | M60: =_xlfn.XLOOKUP(A60,compensation_cleaned!$A:$A,compensation_cleaned!$B:$B,"Missing") -> 663348 | N60: =_xlfn.XLOOKUP(A60,compensation_cleaned!$A:$A,compensation_cleaned!$C:$C,"Missing") -> 70269 | O60: =_xlfn.XLOOKUP(A60,compensation_cleaned!$A:$A,compensation_cleaned!$D:$D,"Missing") -> L2 | P60: =_xlfn.XLOOKUP(A60,engagement_pivot!$A:$A,engagement_pivot!$B:$B,"Missing") -> 4 | Q60: =IF( _xlfn.XLOOKUP(A60, engagement_pivot!A:A, engagement_pivot!C:C, 0) > 0, "Yes", "No" ) -> Yes | R60: =IF(K60="Yes",DATEDIF(G60,L60,"M"),DATEDIF(G60,DATE(2023,12,31),"M")) -> 59 | S60: =IF(R60<=12,"0–12 months", IF(R60<=36,"13–36 months","37+ months")) -> 37+ months | T60: =_xlfn.XLOOKUP(A60,performance_pivot!$A:$A,performance_pivot!$B:$B,"Missing") -> 2.75 | U60: =_xlfn.XLOOKUP(A60,compensation_cleaned!$A:$A,compensation_cleaned!$F:$F,"Missing") -> 746435.4 | V60: =IF(M60>U60,"Above Avg Pay","Below Avg Pay") -> Below Avg Pay | W60: =IF(T60>=4,"High Performer","Low/Avg Performer") -> Low/Avg Performer | Y60: =IF( AND(V60="Above Avg Pay",W60="High Performer"),"Well Aligned", IF( AND(V60="Below Avg Pay",W60="High Performer"),"Underpaid High Performer", IF( AND(V60="Above Avg Pay",W60="Low/Avg Performer"),"Overpaid Low Performer", "Low Pay & Low Performance" ) ) ) -> Low Pay & Low Performance
A61: E100059 | B61: F | C61: 31 | D61: Postgraduate | E61: Operations | F61: Process Manager | G61: 43941 | H61: M238 | I61: Chennai | J61: Full-time | K61: =_xlfn.XLOOKUP(A61,attrition_cleaned!$A:$A,attrition_cleaned!$B:$B,"Missing") -> No | M61: =_xlfn.XLOOKUP(A61,compensation_cleaned!$A:$A,compensation_cleaned!$B:$B,"Missing") -> 1330188 | N61: =_xlfn.XLOOKUP(A61,compensation_cleaned!$A:$A,compensation_cleaned!$C:$C,"Missing") -> 170603 | O61: =_xlfn.XLOOKUP(A61,compensation_cleaned!$A:$A,compensation_cleaned!$D:$D,"Missing") -> L4 | P61: =_xlfn.XLOOKUP(A61,engagement_pivot!$A:$A,engagement_pivot!$B:$B,"Missing") -> 3.5 | Q61: =IF( _xlfn.XLOOKUP(A61, engagement_pivot!A:A, engagement_pivot!C:C, 0) > 0, "Yes", "No" ) -> Yes | R61: =IF(K61="Yes",DATEDIF(G61,L61,"M"),DATEDIF(G61,DATE(2023,12,31),"M")) -> 44 | S61: =IF(R61<=12,"0–12 months", IF(R61<=36,"13–36 months","37+ months")) -> 37+ months | T61: =_xlfn.XLOOKUP(A61,performance_pivot!$A:$A,performance_pivot!$B:$B,"Missing") -> 4.5 | U61: =_xlfn.XLOOKUP(A61,compensation_cleaned!$A:$A,compensation_cleaned!$F:$F,"Missing") -> 1044648.5 | V61: =IF(M61>U61,"Above Avg Pay","Below Avg Pay") -> Above Avg Pay | W61: =IF(T61>=4,"High Performer","Low/Avg Performer") -> High Performer | Y61: =IF( AND(V61="Above Avg Pay",W61="High Performer"),"Well Aligned", IF( AND(V61="Below Avg Pay",W61="High Performer"),"Underpaid High Performer", IF( AND(V61="Above Avg Pay",W61="Low/Avg Performer"),"Overpaid Low Performer", "Low Pay & Low Performance" ) ) ) -> Well Aligned
A62: E100060 | B62: M | C62: 41 | D62: Graduate | E62: Operations | F62: Process Manager | G62: 43979 | H62: M260 | I62: Bangalore | J62: Full-time | K62: =_xlfn.XLOOKUP(A62,attrition_cleaned!$A:$A,attrition_cleaned!$B:$B,"Missing") -> No | M62: =_xlfn.XLOOKUP(A62,compensation_cleaned!$A:$A,compensation_cleaned!$B:$B,"Missing") -> 820632 | N62: =_xlfn.XLOOKUP(A62,compensation_cleaned!$A:$A,compensation_cleaned!$C:$C,"Missing") -> 80415 | O62: =_xlfn.XLOOKUP(A62,compensation_cleaned!$A:$A,compensation_cleaned!$D:$D,"Missing") -> L2 | P62: =_xlfn.XLOOKUP(A62,engagement_pivot!$A:$A,engagement_pivot!$B:$B,"Missing") -> 3.3333333 | Q62: =IF( _xlfn.XLOOKUP(A62, engagement_pivot!A:A, engagement_pivot!C:C, 0) > 0, "Yes", "No" ) -> Yes | R62: =IF(K62="Yes",DATEDIF(G62,L62,"M"),DATEDIF(G62,DATE(2023,12,31),"M")) -> 43 | S62: =IF(R62<=12,"0–12 months", IF(R62<=36,"13–36 months","37+ months")) -> 37+ months | T62: =_xlfn.XLOOKUP(A62,performance_pivot!$A:$A,performance_pivot!$B:$B,"Missing") -> 3.75 | U62: =_xlfn.XLOOKUP(A62,compensation_cleaned!$A:$A,compensation_cleaned!$F:$F,"Missing") -> 746435.4 | V62: =IF(M62>U62,"Above Avg Pay","Below Avg Pay") -> Above Avg Pay | W62: =IF(T62>=4,"High Performer","Low/Avg Performer") -> Low/Avg Performer | Y62: =IF( AND(V62="Above Avg Pay",W62="High Performer"),"Well Aligned", IF( AND(V62="Below Avg Pay",W62="High Performer"),"Underpaid High Performer", IF( AND(V62="Above Avg Pay",W62="Low/Avg Performer"),"Overpaid Low Performer", "Low Pay & Low Performance" ) ) ) -> Overpaid Low Performer
A63: E100061 | B63: F | C63: 38 | D63: Graduate | E63: Sales | F63: Sales Executive | G63: 45131 | H63: M316 | I63: Chennai | J63: Full-time | K63: =_xlfn.XLOOKUP(A63,attrition_cleaned!$A:$A,attrition_cleaned!$B:$B,"Missing") -> No | M63: =_xlfn.XLOOKUP(A63,compensation_cleaned!$A:$A,compensation_cleaned!$B:$B,"Missing") -> 1015831 | N63: =_xlfn.XLOOKUP(A63,compensation_cleaned!$A:$A,compensation_cleaned!$C:$C,"Missing") -> 130843 | O63: =_xlfn.XLOOKUP(A63,compensation_cleaned!$A:$A,compensation_cleaned!$D:$D,"Missing") -> L3 | P63: =_xlfn.XLOOKUP(A63,engagement_pivot!$A:$A,engagement_pivot!$B:$B,"Missing") -> 3.3333333 | Q63: =IF( _xlfn.XLOOKUP(A63, engagement_pivot!A:A, engagement_pivot!C:C, 0) > 0, "Yes", "No" ) -> Yes | R63: =IF(K63="Yes",DATEDIF(G63,L63,"M"),DATEDIF(G63,DATE(2023,12,31),"M")) -> 5 | S63: =IF(R63<=12,"0–12 months", IF(R63<=36,"13–36 months","37+ months")) -> 0–12 months | T63: =_xlfn.XLOOKUP(A63,performance_pivot!$A:$A,performance_pivot!$B:$B,"Missing") -> 3.5 | U63: =_xlfn.XLOOKUP(A63,compensation_cleaned!$A:$A,compensation_cleaned!$F:$F,"Missing") -> 1044648.5 | V63: =IF(M63>U63,"Above Avg Pay","Below Avg Pay") -> Below Avg Pay | W63: =IF(T63>=4,"High Performer","Low/Avg Performer") -> Low/Avg Performer | Y63: =IF( AND(V63="Above Avg Pay",W63="High Performer"),"Well Aligned", IF( AND(V63="Below Avg Pay",W63="High Performer"),"Underpaid High Performer", IF( AND(V63="Above Avg Pay",W63="Low/Avg Performer"),"Overpaid Low Performer", "Low Pay & Low Performance" ) ) ) -> Low Pay & Low Performance
A64: E100062 | B64: M | C64: 42 | D64: Graduate | E64: Operations | F64: Process Manager | G64: 44956 | H64: M346 | I64: Delhi | J64: Full-time | K64: =_xlfn.XLOOKUP(A64,attrition_cleaned!$A:$A,attrition_cleaned!$B:$B,"Missing") -> No | M64: =_xlfn.XLOOKUP(A64,compensation_cleaned!$A:$A,compensation_cleaned!$B:$B,"Missing") -> 746496 | N64: =_xlfn.XLOOKUP(A64,compensation_cleaned!$A:$A,compensation_cleaned!$C:$C,"Missing") -> 40220 | O64: =_xlfn.XLOOKUP(A64,compensation_cleaned!$A:$A,compensation_cleaned!$D:$D,"Missing") -> L2 | P64: =_xlfn.XLOOKUP(A64,engagement_pivot!$A:$A,engagement_pivot!$B:$B,"Missing") -> 4 | Q64: =IF( _xlfn.XLOOKUP(A64, engagement_pivot!A:A, engagement_pivot!C:C, 0) > 0, "Yes", "No" ) -> Yes | R64: =IF(K64="Yes",DATEDIF(G64,L64,"M"),DATEDIF(G64,DATE(2023,12,31),"M")) -> 11 | S64: =IF(R64<=12,"0–12 months", IF(R64<=36,"13–36 months","37+ months")) -> 0–12 months | T64: =_xlfn.XLOOKUP(A64,performance_pivot!$A:$A,performance_pivot!$B:$B,"Missing") -> 3 | U64: =_xlfn.XLOOKUP(A64,compensation_cleaned!$A:$A,compensation_cleaned!$F:$F,"Missing") -> 746435.4 | V64: =IF(M64>U64,"Above Avg Pay","Below Avg Pay") -> Above Avg Pay | W64: =IF(T64>=4,"High Performer","Low/Avg Performer") -> Low/Avg Performer | Y64: =IF( AND(V64="Above Avg Pay",W64="High Performer"),"Well Aligned", IF( AND(V64="Below Avg Pay",W64="High Performer"),"Underpaid High Performer", IF( AND(V64="Above Avg Pay",W64="Low/Avg Performer"),"Overpaid Low Performer", "Low Pay & Low Performance" ) ) ) -> Overpaid Low Performer
A65: E100063 | B65: M | C65: 22 | D65: Graduate | E65: IT | F65: Software Engineer | G65: 44285 | H65: M317 | I65: Pune | J65: Contract | K65: =_xlfn.XLOOKUP(A65,attrition_cleaned!$A:$A,attrition_cleaned!$B:$B,"Missing") -> No | M65: =_xlfn.XLOOKUP(A65,compensation_cleaned!$A:$A,compensation_cleaned!$B:$B,"Missing") -> 552836 | N65: =_xlfn.XLOOKUP(A65,compensation_cleaned!$A:$A,compensation_cleaned!$C:$C,"Missing") -> 32147 | O65: =_xlfn.XLOOKUP(A65,compensation_cleaned!$A:$A,compensation_cleaned!$D:$D,"Missing") -> L1 | P65: =_xlfn.XLOOKUP(A65,engagement_pivot!$A:$A,engagement_pivot!$B:$B,"Missing") -> 3 | Q65: =IF( _xlfn.XLOOKUP(A65, engagement_pivot!A:A, engagement_pivot!C:C, 0) > 0, "Yes", "No" ) -> Yes | R65: =IF(K65="Yes",DATEDIF(G65,L65,"M"),DATEDIF(G65,DATE(2023,12,31),"M")) -> 33 | S65: =IF(R65<=12,"0–12 months", IF(R65<=36,"13–36 months","37+ months")) -> 13–36 months | T65: =_xlfn.XLOOKUP(A65,performance_pivot!$A:$A,performance_pivot!$B:$B,"Missing") -> 3 | U65: =_xlfn.XLOOKUP(A65,compensation_cleaned!$A:$A,compensation_cleaned!$F:$F,"Missing") -> 499723.04 | V65: =IF(M65>U65,"Above Avg Pay","Below Avg Pay") -> Above Avg Pay | W65: =IF(T65>=4,"High Performer","Low/Avg Performer") -> Low/Avg Performer | Y65: =IF( AND(V65="Above Avg Pay",W65="High Performer"),"Well Aligned", IF( AND(V65="Below Avg Pay",W65="High Performer"),"Underpaid High Performer", IF( AND(V65="Above Avg Pay",W65="Low/Avg Performer"),"Overpaid Low Performer", "Low Pay & Low Performance" ) ) ) -> Overpaid Low Performer
A66: E100064 | B66: F | C66: 37 | D66: Postgraduate | E66: IT | F66: QA Engineer | G66: 43771 | H66: M316 | I66: Hyderabad | J66: Full-time | K66: =_xlfn.XLOOKUP(A66,attrition_cleaned!$A:$A,attrition_cleaned!$B:$B,"Missing") -> No | M66: =_xlfn.XLOOKUP(A66,compensation_cleaned!$A:$A,compensation_cleaned!$B:$B,"Missing") -> 1460507 | N66: =_xlfn.XLOOKUP(A66,compensation_cleaned!$A:$A,compensation_cleaned!$C:$C,"Missing") -> 148818 | O66: =_xlfn.XLOOKUP(A66,compensation_cleaned!$A:$A,compensation_cleaned!$D:$D,"Missing") -> L4 | P66: =_xlfn.XLOOKUP(A66,engagement_pivot!$A:$A,engagement_pivot!$B:$B,"Missing") -> 1 | Q66: =IF( _xlfn.XLOOKUP(A66, engagement_pivot!A:A, engagement_pivot!C:C, 0) > 0, "Yes", "No" ) -> Yes | R66: =IF(K66="Yes",DATEDIF(G66,L66,"M"),DATEDIF(G66,DATE(2023,12,31),"M")) -> 49 | S66: =IF(R66<=12,"0–12 months", IF(R66<=36,"13–36 months","37+ months")) -> 37+ months | T66: =_xlfn.XLOOKUP(A66,performance_pivot!$A:$A,performance_pivot!$B:$B,"Missing") -> 4 | U66: =_xlfn.XLOOKUP(A66,compensation_cleaned!$A:$A,compensation_cleaned!$F:$F,"Missing") -> 1044648.5 | V66: =IF(M66>U66,"Above Avg Pay","Below Avg Pay") -> Above Avg Pay | W66: =IF(T66>=4,"High Performer","Low/Avg Performer") -> High Performer | Y66: =IF( AND(V66="Above Avg Pay",W66="High Performer"),"Well Aligned", IF( AND(V66="Below Avg Pay",W66="High Performer"),"Underpaid High Performer", IF( AND(V66="Above Avg Pay",W66="Low/Avg Performer"),"Overpaid Low Performer", "Low Pay & Low Performance" ) ) ) -> Well Aligned
A67: E100065 | B67: M | C67: 30 | D67: Graduate | E67: HR | F67: HR Business Partner | G67: 43275 | H67: M344 | I67: Bangalore | J67: Full-time | K67: =_xlfn.XLOOKUP(A67,attrition_cleaned!$A:$A,attrition_cleaned!$B:$B,"Missing") -> No | M67: =_xlfn.XLOOKUP(A67,compensation_cleaned!$A:$A,compensation_cleaned!$B:$B,"Missing") -> 1407969 | N67: =_xlfn.XLOOKUP(A67,compensation_cleaned!$A:$A,compensation_cleaned!$C:$C,"Missing") -> 202325 | O67: =_xlfn.XLOOKUP(A67,compensation_cleaned!$A:$A,compensation_cleaned!$D:$D,"Missing") -> L4 | P67: =_xlfn.XLOOKUP(A67,engagement_pivot!$A:$A,engagement_pivot!$B:$B,"Missing") -> 3 | Q67: =IF( _xlfn.XLOOKUP(A67, engagement_pivot!A:A, engagement_pivot!C:C, 0) > 0, "Yes", "No" ) -> Yes | R67: =IF(K67="Yes",DATEDIF(G67,L67,"M"),DATEDIF(G67,DATE(2023,12,31),"M")) -> 66 | S67: =IF(R67<=12,"0–12 months", IF(R67<=36,"13–36 months","37+ months")) -> 37+ months | T67: =_xlfn.XLOOKUP(A67,performance_pivot!$A:$A,performance_pivot!$B:$B,"Missing") -> 5 | U67: =_xlfn.XLOOKUP(A67,compensation_cleaned!$A:$A,compensation_cleaned!$F:$F,"Missing") -> 1044648.5 | V67: =IF(M67>U67,"Above Avg Pay","Below Avg Pay") -> Above Avg Pay | W67: =IF(T67>=4,"High Performer","Low/Avg Performer") -> High Performer | Y67: =IF( AND(V67="Above Avg Pay",W67="High Performer"),"Well Aligned", IF( AND(V67="Below Avg Pay",W67="High Performer"),"Underpaid High Performer", IF( AND(V67="Above Avg Pay",W67="Low/Avg Performer"),"Overpaid Low Performer", "Low Pay & Low Performance" ) ) ) -> Well Aligned
A68: E100066 | B68: M | C68: 24 | D68: Postgraduate | E68: Finance | F68: Financial Analyst | G68: 43660 | H68: M281 | I68: Pune | J68: Full-time | K68: =_xlfn.XLOOKUP(A68,attrition_cleaned!$A:$A,attrition_cleaned!$B:$B,"Missing") -> Yes | L68: 44527 | M68: =_xlfn.XLOOKUP(A68,compensation_cleaned!$A:$A,compensation_cleaned!$B:$B,"Missing") -> 1255351 | N68: =_xlfn.XLOOKUP(A68,compensation_cleaned!$A:$A,compensation_cleaned!$C:$C,"Missing") -> 149496 | O68: =_xlfn.XLOOKUP(A68,compensation_cleaned!$A:$A,compensation_cleaned!$D:$D,"Missing") -> L4 | P68: =_xlfn.XLOOKUP(A68,engagement_pivot!$A:$A,engagement_pivot!$B:$B,"Missing") -> 1 | Q68: =IF( _xlfn.XLOOKUP(A68, engagement_pivot!A:A, engagement_pivot!C:C, 0) > 0, "Yes", "No" ) -> Yes | R68: =IF(K68="Yes",DATEDIF(G68,L68,"M"),DATEDIF(G68,DATE(2023,12,31),"M")) -> 28 | S68: =IF(R68<=12,"0–12 months", IF(R68<=36,"13–36 months","37+ months")) -> 13–36 months | T68: =_xlfn.XLOOKUP(A68,performance_pivot!$A:$A,performance_pivot!$B:$B,"Missing") -> 3.25 | U68: =_xlfn.XLOOKUP(A68,compensation_cleaned!$A:$A,compensation_cleaned!$F:$F,"Missing") -> 1044648.5 | V68: =IF(M68>U68,"Above Avg Pay","Below Avg Pay") -> Above Avg Pay | W68: =IF(T68>=4,"High Performer","Low/Avg Performer") -> Low/Avg Performer | Y68: =IF( AND(V68="Above Avg Pay",W68="High Performer"),"Well Aligned", IF( AND(V68="Below Avg Pay",W68="High Performer"),"Underpaid High Performer", IF( AND(V68="Above Avg Pay",W68="Low/Avg Performer"),"Overpaid Low Performer", "Low Pay & Low Performance" ) ) ) -> Overpaid Low Performer
A69: E100067 | B69: F | C69: 39 | D69: Graduate | E69: IT | F69: Data Analyst | G69: 42745 | H69: M204 | I69: Bangalore | J69: Full-time | K69: =_xlfn.XLOOKUP(A69,attrition_cleaned!$A:$A,attrition_cleaned!$B:$B,"Missing") -> Yes | L69: 43774 | M69: =_xlfn.XLOOKUP(A69,compensation_cleaned!$A:$A,compensation_cleaned!$B:$B,"Missing") -> 1095724 | N69: =_xlfn.XLOOKUP(A69,compensation_cleaned!$A:$A,compensation_cleaned!$C:$C,"Missing") -> 129782 | O69: =_xlfn.XLOOKUP(A69,compensation_cleaned!$A:$A,compensation_cleaned!$D:$D,"Missing") -> L3 | P69: =_xlfn.XLOOKUP(A69,engagement_pivot!$A:$A,engagement_pivot!$B:$B,"Missing") -> 5 | Q69: =IF( _xlfn.XLOOKUP(A69, engagement_pivot!A:A, engagement_pivot!C:C, 0) > 0, "Yes", "No" ) -> Yes | R69: =IF(K69="Yes",DATEDIF(G69,L69,"M"),DATEDIF(G69,DATE(2023,12,31),"M")) -> 33 | S69: =IF(R69<=12,"0–12 months", IF(R69<=36,"13–36 months","37+ months")) -> 13–36 months | T69: =_xlfn.XLOOKUP(A69,performance_pivot!$A:$A,performance_pivot!$B:$B,"Missing") -> 4 | U69: =_xlfn.XLOOKUP(A69,compensation_cleaned!$A:$A,compensation_cleaned!$F:$F,"Missing") -> 1044648.5 | V69: =IF(M69>U69,"Above Avg Pay","Below Avg Pay") -> Above Avg Pay | W69: =IF(T69>=4,"High Performer","Low/Avg Performer") -> High Performer | Y69: =IF( AND(V69="Above Avg Pay",W69="High Performer"),"Well Aligned", IF( AND(V69="Below Avg Pay",W69="High Performer"),"Underpaid High Performer", IF( AND(V69="Above Avg Pay",W69="Low/Avg Performer"),"Overpaid Low Performer", "Low Pay & Low Performance" ) ) ) -> Well Aligned
A70: E100068 | B70: M | C70: 42 | D70: Postgraduate | E70: HR | F70: HR Business Partner | G70: 43998 | H70: M285 | I70: Pune | J70: Full-time | K70: =_xlfn.XLOOKUP(A70,attrition_cleaned!$A:$A,attrition_cleaned!$B:$B,"Missing") -> No | M70: =_xlfn.XLOOKUP(A70,compensation_cleaned!$A:$A,compensation_cleaned!$B:$B,"Missing") -> 406460 | N70: =_xlfn.XLOOKUP(A70,compensation_cleaned!$A:$A,compensation_cleaned!$C:$C,"Missing") -> 45438 | O70: =_xlfn.XLOOKUP(A70,compensation_cleaned!$A:$A,compensation_cleaned!$D:$D,"Missing") -> L1 | P70: =_xlfn.XLOOKUP(A70,engagement_pivot!$A:$A,engagement_pivot!$B:$B,"Missing") -> 3.5 | Q70: =IF( _xlfn.XLOOKUP(A70, engagement_pivot!A:A, engagement_pivot!C:C, 0) > 0, "Yes", "No" ) -> Yes | R70: =IF(K70="Yes",DATEDIF(G70,L70,"M"),DATEDIF(G70,DATE(2023,12,31),"M")) -> 42 | S70: =IF(R70<=12,"0–12 months", IF(R70<=36,"13–36 months","37+ months")) -> 37+ months | T70: =_xlfn.XLOOKUP(A70,performance_pivot!$A:$A,performance_pivot!$B:$B,"Missing") -> 4 | U70: =_xlfn.XLOOKUP(A70,compensation_cleaned!$A:$A,compensation_cleaned!$F:$F,"Missing") -> 499723.04 | V70: =IF(M70>U70,"Above Avg Pay","Below Avg Pay") -> Below Avg Pay | W70: =IF(T70>=4,"High Performer","Low/Avg Performer") -> High Performer | Y70: =IF( AND(V70="Above Avg Pay",W70="High Performer"),"Well Aligned", IF( AND(V70="Below Avg Pay",W70="High Performer"),"Underpaid High Performer", IF( AND(V70="Above Avg Pay",W70="Low/Avg Performer"),"Overpaid Low Performer", "Low Pay & Low Performance" ) ) ) -> Underpaid High Performer
A71: E100069 | B71: M | C71: 22 | D71: Graduate | E71: Operations | F71: Operations Analyst | G71: 44369 | H71: M254 | I71: Chennai | J71: Full-time | K71: =_xlfn.XLOOKUP(A71,attrition_cleaned!$A:$A,attrition_cleaned!$B:$B,"Missing") -> No | M71: =_xlfn.XLOOKUP(A71,compensation_cleaned!$A:$A,compensation_cleaned!$B:$B,"Missing") -> 1002205 | N71: =_xlfn.XLOOKUP(A71,compensation_cleaned!$A:$A,compensation_cleaned!$C:$C,"Missing") -> 67991 | O71: =_xlfn.XLOOKUP(A71,compensation_cleaned!$A:$A,compensation_cleaned!$D:$D,"Missing") -> L3 | P71: =_xlfn.XLOOKUP(A71,engagement_pivot!$A:$A,engagement_pivot!$B:$B,"Missing") -> 3.6666667 | Q71: =IF( _xlfn.XLOOKUP(A71, engagement_pivot!A:A, engagement_pivot!C:C, 0) > 0, "Yes", "No" ) -> Yes | R71: =IF(K71="Yes",DATEDIF(G71,L71,"M"),DATEDIF(G71,DATE(2023,12,31),"M")) -> 30 | S71: =IF(R71<=12,"0–12 months", IF(R71<=36,"13–36 months","37+ months")) -> 13–36 months | T71: =_xlfn.XLOOKUP(A71,performance_pivot!$A:$A,performance_pivot!$B:$B,"Missing") -> 3 | U71: =_xlfn.XLOOKUP(A71,compensation_cleaned!$A:$A,compensation_cleaned!$F:$F,"Missing") -> 1044648.5 | V71: =IF(M71>U71,"Above Avg Pay","Below Avg Pay") -> Below Avg Pay | W71: =IF(T71>=4,"High Performer","Low/Avg Performer") -> Low/Avg Performer | Y71: =IF( AND(V71="Above Avg Pay",W71="High Performer"),"Well Aligned", IF( AND(V71="Below Avg Pay",W71="High Performer"),"Underpaid High Performer", IF( AND(V71="Above Avg Pay",W71="Low/Avg Performer"),"Overpaid Low Performer", "Low Pay & Low Performance" ) ) ) -> Low Pay & Low Performance
A72: E100070 | B72: F | C72: 42 | D72: Graduate | E72: Operations | F72: Operations Analyst | G72: 44404 | H72: M252 | I72: Mumbai | J72: Full-time | K72: =_xlfn.XLOOKUP(A72,attrition_cleaned!$A:$A,attrition_cleaned!$B:$B,"Missing") -> No | M72: =_xlfn.XLOOKUP(A72,compensation_cleaned!$A:$A,compensation_cleaned!$B:$B,"Missing") -> 916213 | N72: =_xlfn.XLOOKUP(A72,compensation_cleaned!$A:$A,compensation_cleaned!$C:$C,"Missing") -> 126367 | O72: =_xlfn.XLOOKUP(A72,compensation_cleaned!$A:$A,compensation_cleaned!$D:$D,"Missing") -> L3 | P72: =_xlfn.XLOOKUP(A72,engagement_pivot!$A:$A,engagement_pivot!$B:$B,"Missing") -> 3 | Q72: =IF( _xlfn.XLOOKUP(A72, engagement_pivot!A:A, engagement_pivot!C:C, 0) > 0, "Yes", "No" ) -> Yes | R72: =IF(K72="Yes",DATEDIF(G72,L72,"M"),DATEDIF(G72,DATE(2023,12,31),"M")) -> 29 | S72: =IF(R72<=12,"0–12 months", IF(R72<=36,"13–36 months","37+ months")) -> 13–36 months | T72: =_xlfn.XLOOKUP(A72,performance_pivot!$A:$A,performance_pivot!$B:$B,"Missing") -> 4 | U72: =_xlfn.XLOOKUP(A72,compensation_cleaned!$A:$A,compensation_cleaned!$F:$F,"Missing") -> 1044648.5 | V72: =IF(M72>U72,"Above Avg Pay","Below Avg Pay") -> Below Avg Pay | W72: =IF(T72>=4,"High Performer","Low/Avg Performer") -> High Performer | Y72: =IF( AND(V72="Above Avg Pay",W72="High Performer"),"Well Aligned", IF( AND(V72="Below Avg Pay",W72="High Performer"),"Underpaid High Performer", IF( AND(V72="Above Avg Pay",W72="Low/Avg Performer"),"Overpaid Low Performer", "Low Pay & Low Performance" ) ) ) -> Underpaid High Performer
A73: E100071 | B73: M | C73: 40 | D73: Graduate | E73: Sales | F73: Sales Executive | G73: 45240 | H73: M203 | I73: Chennai | J73: Contract | K73: =_xlfn.XLOOKUP(A73,attrition_cleaned!$A:$A,attrition_cleaned!$B:$B,"Missing") -> No | M73: =_xlfn.XLOOKUP(A73,compensation_cleaned!$A:$A,compensation_cleaned!$B:$B,"Missing") -> 1190472 | N73: =_xlfn.XLOOKUP(A73,compensation_cleaned!$A:$A,compensation_cleaned!$C:$C,"Missing") -> 92166 | O73: =_xlfn.XLOOKUP(A73,compensation_cleaned!$A:$A,compensation_cleaned!$D:$D,"Missing") -> L3 | P73: =_xlfn.XLOOKUP(A73,engagement_pivot!$A:$A,engagement_pivot!$B:$B,"Missing") -> 5 | Q73: =IF( _xlfn.XLOOKUP(A73, engagement_pivot!A:A, engagement_pivot!C:C, 0) > 0, "Yes", "No" ) -> Yes | R73: =IF(K73="Yes",DATEDIF(G73,L73,"M"),DATEDIF(G73,DATE(2023,12,31),"M")) -> 1 | S73: =IF(R73<=12,"0–12 months", IF(R73<=36,"13–36 months","37+ months")) -> 0–12 months | T73: =_xlfn.XLOOKUP(A73,performance_pivot!$A:$A,performance_pivot!$B:$B,"Missing") -> 3 | U73: =_xlfn.XLOOKUP(A73,compensation_cleaned!$A:$A,compensation_cleaned!$F:$F,"Missing") -> 1044648.5 | V73: =IF(M73>U73,"Above Avg Pay","Below Avg Pay") -> Above Avg Pay | W73: =IF(T73>=4,"High Performer","Low/Avg Performer") -> Low/Avg Performer | Y73: =IF( AND(V73="Above Avg Pay",W73="High Performer"),"Well Aligned", IF( AND(V73="Below Avg Pay",W73="High Performer"),"Underpaid High Performer", IF( AND(V73="Above Avg Pay",W73="Low/Avg Performer"),"Overpaid Low Performer", "Low Pay & Low Performance" ) ) ) -> Overpaid Low Performer
A74: E100072 | B74: M | C74: 23 | D74: Graduate | E74: HR | F74: HR Business Partner | G74: 44878 | H74: M202 | I74: Pune | J74: Full-time | K74: =_xlfn.XLOOKUP(A74,attrition_cleaned!$A:$A,attrition_cleaned!$B:$B,"Missing") -> No | M74: =_xlfn.XLOOKUP(A74,compensation_cleaned!$A:$A,compensation_cleaned!$B:$B,"Missing") -> 991276 | N74: =_xlfn.XLOOKUP(A74,compensation_cleaned!$A:$A,compensation_cleaned!$C:$C,"Missing") -> 134837 | O74: =_xlfn.XLOOKUP(A74,compensation_cleaned!$A:$A,compensation_cleaned!$D:$D,"Missing") -> L3 | P74: =_xlfn.XLOOKUP(A74,engagement_pivot!$A:$A,engagement_pivot!$B:$B,"Missing") -> 1 | Q74: =IF( _xlfn.XLOOKUP(A74, engagement_pivot!A:A, engagement_pivot!C:C, 0) > 0, "Yes", "No" ) -> Yes | R74: =IF(K74="Yes",DATEDIF(G74,L74,"M"),DATEDIF(G74,DATE(2023,12,31),"M")) -> 13 | S74: =IF(R74<=12,"0–12 months", IF(R74<=36,"13–36 months","37+ months")) -> 13–36 months | T74: =_xlfn.XLOOKUP(A74,performance_pivot!$A:$A,performance_pivot!$B:$B,"Missing") -> 3 | U74: =_xlfn.XLOOKUP(A74,compensation_cleaned!$A:$A,compensation_cleaned!$F:$F,"Missing") -> 1044648.5 | V74: =IF(M74>U74,"Above Avg Pay","Below Avg Pay") -> Below Avg Pay | W74: =IF(T74>=4,"High Performer","Low/Avg Performer") -> Low/Avg Performer | Y74: =IF( AND(V74="Above Avg Pay",W74="High Performer"),"Well Aligned", IF( AND(V74="Below Avg Pay",W74="High Performer"),"Underpaid High Performer", IF( AND(V74="Above Avg Pay",W74="Low/Avg Performer"),"Overpaid Low Performer", "Low Pay & Low Performance" ) ) ) -> Low Pay & Low Performance
A75: E100073 | B75: M | C75: 38 | D75: Graduate | E75: IT | F75: Data Analyst | G75: 42971 | H75: M246 | I75: Mumbai | J75: Full-time | K75: =_xlfn.XLOOKUP(A75,attrition_cleaned!$A:$A,attrition_cleaned!$B:$B,"Missing") -> No | M75: =_xlfn.XLOOKUP(A75,compensation_cleaned!$A:$A,compensation_cleaned!$B:$B,"Missing") -> 511391 | N75: =_xlfn.XLOOKUP(A75,compensation_cleaned!$A:$A,compensation_cleaned!$C:$C,"Missing") -> 26047 | O75: =_xlfn.XLOOKUP(A75,compensation_cleaned!$A:$A,compensation_cleaned!$D:$D,"Missing") -> L1 | P75: =_xlfn.XLOOKUP(A75,engagement_pivot!$A:$A,engagement_pivot!$B:$B,"Missing") -> 3 | Q75: =IF( _xlfn.XLOOKUP(A75, engagement_pivot!A:A, engagement_pivot!C:C, 0) > 0, "Yes", "No" ) -> Yes | R75: =IF(K75="Yes",DATEDIF(G75,L75,"M"),DATEDIF(G75,DATE(2023,12,31),"M")) -> 76 | S75: =IF(R75<=12,"0–12 months", IF(R75<=36,"13–36 months","37+ months")) -> 37+ months | T75: =_xlfn.XLOOKUP(A75,performance_pivot!$A:$A,performance_pivot!$B:$B,"Missing") -> 3.75 | U75: =_xlfn.XLOOKUP(A75,compensation_cleaned!$A:$A,compensation_cleaned!$F:$F,"Missing") -> 499723.04 | V75: =IF(M75>U75,"Above Avg Pay","Below Avg Pay") -> Above Avg Pay | W75: =IF(T75>=4,"High Performer","Low/Avg Performer") -> Low/Avg Performer | Y75: =IF( AND(V75="Above Avg Pay",W75="High Performer"),"Well Aligned", IF( AND(V75="Below Avg Pay",W75="High Performer"),"Underpaid High Performer", IF( AND(V75="Above Avg Pay",W75="Low/Avg Performer"),"Overpaid Low Performer", "Low Pay & Low Performance" ) ) ) -> Overpaid Low Performer
A76: E100074 | B76: F | C76: 23 | D76: Graduate | E76: HR | F76: HR Executive | G76: 43170 | H76: M297 | I76: Hyderabad | J76: Full-time | K76: =_xlfn.XLOOKUP(A76,attrition_cleaned!$A:$A,attrition_cleaned!$B:$B,"Missing") -> Yes | L76: 43886 | M76: =_xlfn.XLOOKUP(A76,compensation_cleaned!$A:$A,compensation_cleaned!$B:$B,"Missing") -> 1545849 | N76: =_xlfn.XLOOKUP(A76,compensation_cleaned!$A:$A,compensation_cleaned!$C:$C,"Missing") -> 175191 | O76: =_xlfn.XLOOKUP(A76,compensation_cleaned!$A:$A,compensation_cleaned!$D:$D,"Missing") -> L4 | P76: =_xlfn.XLOOKUP(A76,engagement_pivot!$A:$A,engagement_pivot!$B:$B,"Missing") -> 5 | Q76: =IF( _xlfn.XLOOKUP(A76, engagement_pivot!A:A, engagement_pivot!C:C, 0) > 0, "Yes", "No" ) -> Yes | R76: =IF(K76="Yes",DATEDIF(G76,L76,"M"),DATEDIF(G76,DATE(2023,12,31),"M")) -> 23 | S76: =IF(R76<=12,"0–12 months", IF(R76<=36,"13–36 months","37+ months")) -> 13–36 months | T76: =_xlfn.XLOOKUP(A76,performance_pivot!$A:$A,performance_pivot!$B:$B,"Missing") -> 3.5 | U76: =_xlfn.XLOOKUP(A76,compensation_cleaned!$A:$A,compensation_cleaned!$F:$F,"Missing") -> 1044648.5 | V76: =IF(M76>U76,"Above Avg Pay","Below Avg Pay") -> Above Avg Pay | W76: =IF(T76>=4,"High Performer","Low/Avg Performer") -> Low/Avg Performer | Y76: =IF( AND(V76="Above Avg Pay",W76="High Performer"),"Well Aligned", IF( AND(V76="Below Avg Pay",W76="High Performer"),"Underpaid High Performer", IF( AND(V76="Above Avg Pay",W76="Low/Avg Performer"),"Overpaid Low Performer", "Low Pay & Low Performance" ) ) ) -> Overpaid Low Performer
A77: E100075 | B77: F | C77: 27 | D77: Graduate | E77: Sales | F77: Sales Executive | G77: 43182 | H77: M278 | I77: Delhi | J77: Full-time | K77: =_xlfn.XLOOKUP(A77,attrition_cleaned!$A:$A,attrition_cleaned!$B:$B,"Missing") -> No | M77: =_xlfn.XLOOKUP(A77,compensation_cleaned!$A:$A,compensation_cleaned!$B:$B,"Missing") -> 532973 | N77: =_xlfn.XLOOKUP(A77,compensation_cleaned!$A:$A,compensation_cleaned!$C:$C,"Missing") -> 46760 | O77: =_xlfn.XLOOKUP(A77,compensation_cleaned!$A:$A,compensation_cleaned!$D:$D,"Missing") -> L1 | P77: =_xlfn.XLOOKUP(A77,engagement_pivot!$A:$A,engagement_pivot!$B:$B,"Missing") -> 1.5 | Q77: =IF( _xlfn.XLOOKUP(A77, engagement_pivot!A:A, engagement_pivot!C:C, 0) > 0, "Yes", "No" ) -> Yes | R77: =IF(K77="Yes",DATEDIF(G77,L77,"M"),DATEDIF(G77,DATE(2023,12,31),"M")) -> 69 | S77: =IF(R77<=12,"0–12 months", IF(R77<=36,"13–36 months","37+ months")) -> 37+ months | T77: =_xlfn.XLOOKUP(A77,performance_pivot!$A:$A,performance_pivot!$B:$B,"Missing") -> 4 | U77: =_xlfn.XLOOKUP(A77,compensation_cleaned!$A:$A,compensation_cleaned!$F:$F,"Missing") -> 499723.04 | V77: =IF(M77>U77,"Above Avg Pay","Below Avg Pay") -> Above Avg Pay | W77: =IF(T77>=4,"High Performer","Low/Avg Performer") -> High Performer | Y77: =IF( AND(V77="Above Avg Pay",W77="High Performer"),"Well Aligned", IF( AND(V77="Below Avg Pay",W77="High Performer"),"Underpaid High Performer", IF( AND(V77="Above Avg Pay",W77="Low/Avg Performer"),"Overpaid Low Performer", "Low Pay & Low Performance" ) ) ) -> Well Aligned
A78: E100076 | B78: F | C78: 25 | D78: Graduate | E78: HR | F78: HR Executive | G78: 44864 | H78: M344 | I78: Hyderabad | J78: Full-time | K78: =_xlfn.XLOOKUP(A78,attrition_cleaned!$A:$A,attrition_cleaned!$B:$B,"Missing") -> No | M78: =_xlfn.XLOOKUP(A78,compensation_cleaned!$A:$A,compensation_cleaned!$B:$B,"Missing") -> 990636 | N78: =_xlfn.XLOOKUP(A78,compensation_cleaned!$A:$A,compensation_cleaned!$C:$C,"Missing") -> 57561 | O78: =_xlfn.XLOOKUP(A78,compensation_cleaned!$A:$A,compensation_cleaned!$D:$D,"Missing") -> L3 | P78: =_xlfn.XLOOKUP(A78,engagement_pivot!$A:$A,engagement_pivot!$B:$B,"Missing") -> 4.6666667 | Q78: =IF( _xlfn.XLOOKUP(A78, engagement_pivot!A:A, engagement_pivot!C:C, 0) > 0, "Yes", "No" ) -> Yes | R78: =IF(K78="Yes",DATEDIF(G78,L78,"M"),DATEDIF(G78,DATE(2023,12,31),"M")) -> 14 | S78: =IF(R78<=12,"0–12 months", IF(R78<=36,"13–36 months","37+ months")) -> 13–36 months | T78: =_xlfn.XLOOKUP(A78,performance_pivot!$A:$A,performance_pivot!$B:$B,"Missing") -> 2.6666667 | U78: =_xlfn.XLOOKUP(A78,compensation_cleaned!$A:$A,compensation_cleaned!$F:$F,"Missing") -> 1044648.5 | V78: =IF(M78>U78,"Above Avg Pay","Below Avg Pay") -> Below Avg Pay | W78: =IF(T78>=4,"High Performer","Low/Avg Performer") -> Low/Avg Performer | Y78: =IF( AND(V78="Above Avg Pay",W78="High Performer"),"Well Aligned", IF( AND(V78="Below Avg Pay",W78="High Performer"),"Underpaid High Performer", IF( AND(V78="Above Avg Pay",W78="Low/Avg Performer"),"Overpaid Low Performer", "Low Pay & Low Performance" ) ) ) -> Low Pay & Low Performance
A79: E100077 | B79: F | C79: 42 | D79: Graduate | E79: Finance | F79: Accountant | G79: 42804 | H79: M325 | I79: Pune | J79: Full-time | K79: =_xlfn.XLOOKUP(A79,attrition_cleaned!$A:$A,attrition_cleaned!$B:$B,"Missing") -> No | M79: =_xlfn.XLOOKUP(A79,compensation_cleaned!$A:$A,compensation_cleaned!$B:$B,"Missing") -> 1438906 | N79: =_xlfn.XLOOKUP(A79,compensation_cleaned!$A:$A,compensation_cleaned!$C:$C,"Missing") -> 114350 | O79: =_xlfn.XLOOKUP(A79,compensation_cleaned!$A:$A,compensation_cleaned!$D:$D,"Missing") -> L4 | P79: =_xlfn.XLOOKUP(A79,engagement_pivot!$A:$A,engagement_pivot!$B:$B,"Missing") -> 2.6666667 | Q79: =IF( _xlfn.XLOOKUP(A79, engagement_pivot!A:A, engagement_pivot!C:C, 0) > 0, "Yes", "No" ) -> Yes | R79: =IF(K79="Yes",DATEDIF(G79,L79,"M"),DATEDIF(G79,DATE(2023,12,31),"M")) -> 81 | S79: =IF(R79<=12,"0–12 months", IF(R79<=36,"13–36 months","37+ months")) -> 37+ months | T79: =_xlfn.XLOOKUP(A79,performance_pivot!$A:$A,performance_pivot!$B:$B,"Missing") -> 4 | U79: =_xlfn.XLOOKUP(A79,compensation_cleaned!$A:$A,compensation_cleaned!$F:$F,"Missing") -> 1044648.5 | V79: =IF(M79>U79,"Above Avg Pay","Below Avg Pay") -> Above Avg Pay | W79: =IF(T79>=4,"High Performer","Low/Avg Performer") -> High Performer | Y79: =IF( AND(V79="Above Avg Pay",W79="High Performer"),"Well Aligned", IF( AND(V79="Below Avg Pay",W79="High Performer"),"Underpaid High Performer", IF( AND(V79="Above Avg Pay",W79="Low/Avg Performer"),"Overpaid Low Performer", "Low Pay & Low Performance" ) ) ) -> Well Aligned
A80: E100078 | B80: M | C80: 44 | D80: Graduate | E80: Sales | F80: Sales Executive | G80: 44894 | H80: M317 | I80: Delhi | J80: Full-time | K80: =_xlfn.XLOOKUP(A80,attrition_cleaned!$A:$A,attrition_cleaned!$B:$B,"Missing") -> Yes | L80: 46589 | M80: =_xlfn.XLOOKUP(A80,compensation_cleaned!$A:$A,compensation_cleaned!$B:$B,"Missing") -> 818778 | N80: =_xlfn.XLOOKUP(A80,compensation_cleaned!$A:$A,compensation_cleaned!$C:$C,"Missing") -> 44227 | O80: =_xlfn.XLOOKUP(A80,compensation_cleaned!$A:$A,compensation_cleaned!$D:$D,"Missing") -> L2 | P80: =_xlfn.XLOOKUP(A80,engagement_pivot!$A:$A,engagement_pivot!$B:$B,"Missing") -> 3 | Q80: =IF( _xlfn.XLOOKUP(A80, engagement_pivot!A:A, engagement_pivot!C:C, 0) > 0, "Yes", "No" ) -> Yes | R80: =IF(K80="Yes",DATEDIF(G80,L80,"M"),DATEDIF(G80,DATE(2023,12,31),"M")) -> 55 | S80: =IF(R80<=12,"0–12 months", IF(R80<=36,"13–36 months","37+ months")) -> 37+ months | T80: =_xlfn.XLOOKUP(A80,performance_pivot!$A:$A,performance_pivot!$B:$B,"Missing") -> 3.75 | U80: =_xlfn.XLOOKUP(A80,compensation_cleaned!$A:$A,compensation_cleaned!$F:$F,"Missing") -> 746435.4 | V80: =IF(M80>U80,"Above Avg Pay","Below Avg Pay") -> Above Avg Pay | W80: =IF(T80>=4,"High Performer","Low/Avg Performer") -> Low/Avg Performer | Y80: =IF( AND(V80="Above Avg Pay",W80="High Performer"),"Well Aligned", IF( AND(V80="Below Avg Pay",W80="High Performer"),"Underpaid High Performer", IF( AND(V80="Above Avg Pay",W80="Low/Avg Performer"),"Overpaid Low Performer", "Low Pay & Low Performance" ) ) ) -> Overpaid Low Performer
A81: E100079 | B81: M | C81: 39 | D81: Graduate | E81: IT | F81: QA Engineer | G81: 44623 | H81: M250 | I81: Pune | J81: Full-time | K81: =_xlfn.XLOOKUP(A81,attrition_cleaned!$A:$A,attrition_cleaned!$B:$B,"Missing") -> No | M81: =_xlfn.XLOOKUP(A81,compensation_cleaned!$A:$A,compensation_cleaned!$B:$B,"Missing") -> 754902 | N81: =_xlfn.XLOOKUP(A81,compensation_cleaned!$A:$A,compensation_cleaned!$C:$C,"Missing") -> 62316 | O81: =_xlfn.XLOOKUP(A81,compensation_cleaned!$A:$A,compensation_cleaned!$D:$D,"Missing") -> L2 | P81: =_xlfn.XLOOKUP(A81,engagement_pivot!$A:$A,engagement_pivot!$B:$B,"Missing") -> 1.5 | Q81: =IF( _xlfn.XLOOKUP(A81, engagement_pivot!A:A, engagement_pivot!C:C, 0) > 0, "Yes", "No" ) -> Yes | R81: =IF(K81="Yes",DATEDIF(G81,L81,"M"),DATEDIF(G81,DATE(2023,12,31),"M")) -> 21 | S81: =IF(R81<=12,"0–12 months", IF(R81<=36,"13–36 months","37+ months")) -> 13–36 months | T81: =_xlfn.XLOOKUP(A81,performance_pivot!$A:$A,performance_pivot!$B:$B,"Missing") -> 3.5 | U81: =_xlfn.XLOOKUP(A81,compensation_cleaned!$A:$A,compensation_cleaned!$F:$F,"Missing") -> 746435.4 | V81: =IF(M81>U81,"Above Avg Pay","Below Avg Pay") -> Above Avg Pay | W81: =IF(T81>=4,"High Performer","Low/Avg Performer") -> Low/Avg Performer | Y81: =IF( AND(V81="Above Avg Pay",W81="High Performer"),"Well Aligned", IF( AND(V81="Below Avg Pay",W81="High Performer"),"Underpaid High Performer", IF( AND(V81="Above Avg Pay",W81="Low/Avg Performer"),"Overpaid Low Performer", "Low Pay & Low Performance" ) ) ) -> Overpaid Low Performer
A82: E100080 | B82: M | C82: 42 | D82: Graduate | E82: HR | F82: HR Business Partner | G82: 43417 | H82: M332 | I82: Bangalore | J82: Full-time | K82: =_xlfn.XLOOKUP(A82,attrition_cleaned!$A:$A,attrition_cleaned!$B:$B,"Missing") -> Yes | L82: 44279 | M82: =_xlfn.XLOOKUP(A82,compensation_cleaned!$A:$A,compensation_cleaned!$B:$B,"Missing") -> 542060 | N82: =_xlfn.XLOOKUP(A82,compensation_cleaned!$A:$A,compensation_cleaned!$C:$C,"Missing") -> 35973 | O82: =_xlfn.XLOOKUP(A82,compensation_cleaned!$A:$A,compensation_cleaned!$D:$D,"Missing") -> L1 | P82: =_xlfn.XLOOKUP(A82,engagement_pivot!$A:$A,engagement_pivot!$B:$B,"Missing") -> 2.3333333 | Q82: =IF( _xlfn.XLOOKUP(A82, engagement_pivot!A:A, engagement_pivot!C:C, 0) > 0, "Yes", "No" ) -> Yes | R82: =IF(K82="Yes",DATEDIF(G82,L82,"M"),DATEDIF(G82,DATE(2023,12,31),"M")) -> 28 | S82: =IF(R82<=12,"0–12 months", IF(R82<=36,"13–36 months","37+ months")) -> 13–36 months | T82: =_xlfn.XLOOKUP(A82,performance_pivot!$A:$A,performance_pivot!$B:$B,"Missing") -> 3.6666667 | U82: =_xlfn.XLOOKUP(A82,compensation_cleaned!$A:$A,compensation_cleaned!$F:$F,"Missing") -> 499723.04 | V82: =IF(M82>U82,"Above Avg Pay","Below Avg Pay") -> Above Avg Pay | W82: =IF(T82>=4,"High Performer","Low/Avg Performer") -> Low/Avg Performer | Y82: =IF( AND(V82="Above Avg Pay",W82="High Performer"),"Well Aligned", IF( AND(V82="Below Avg Pay",W82="High Performer"),"Underpaid High Performer", IF( AND(V82="Above Avg Pay",W82="Low/Avg Performer"),"Overpaid Low Performer", "Low Pay & Low Performance" ) ) ) -> Overpaid Low Performer
A83: E100081 | B83: M | C83: 30 | D83: Graduate | E83: HR | F83: HR Executive | G83: 43837 | H83: M246 | I83: Bangalore | J83: Full-time | K83: =_xlfn.XLOOKUP(A83,attrition_cleaned!$A:$A,attrition_cleaned!$B:$B,"Missing") -> No | M83: =_xlfn.XLOOKUP(A83,compensation_cleaned!$A:$A,compensation_cleaned!$B:$B,"Missing") -> 1159199 | N83: =_xlfn.XLOOKUP(A83,compensation_cleaned!$A:$A,compensation_cleaned!$C:$C,"Missing") -> 109962 | O83: =_xlfn.XLOOKUP(A83,compensation_cleaned!$A:$A,compensation_cleaned!$D:$D,"Missing") -> L3 | P83: =_xlfn.XLOOKUP(A83,engagement_pivot!$A:$A,engagement_pivot!$B:$B,"Missing") -> 4.6666667 | Q83: =IF( _xlfn.XLOOKUP(A83, engagement_pivot!A:A, engagement_pivot!C:C, 0) > 0, "Yes", "No" ) -> Yes | R83: =IF(K83="Yes",DATEDIF(G83,L83,"M"),DATEDIF(G83,DATE(2023,12,31),"M")) -> 47 | S83: =IF(R83<=12,"0–12 months", IF(R83<=36,"13–36 months","37+ months")) -> 37+ months | T83: =_xlfn.XLOOKUP(A83,performance_pivot!$A:$A,performance_pivot!$B:$B,"Missing") -> 3 | U83: =_xlfn.XLOOKUP(A83,compensation_cleaned!$A:$A,compensation_cleaned!$F:$F,"Missing") -> 1044648.5 | V83: =IF(M83>U83,"Above Avg Pay","Below Avg Pay") -> Above Avg Pay | W83: =IF(T83>=4,"High Performer","Low/Avg Performer") -> Low/Avg Performer | Y83: =IF( AND(V83="Above Avg Pay",W83="High Performer"),"Well Aligned", IF( AND(V83="Below Avg Pay",W83="High Performer"),"Underpaid High Performer", IF( AND(V83="Above Avg Pay",W83="Low/Avg Performer"),"Overpaid Low Performer", "Low Pay & Low Performance" ) ) ) -> Overpaid Low Performer
A84: E100082 | B84: M | C84: 25 | D84: Postgraduate | E84: Sales | F84: Sales Executive | G84: 42783 | H84: M312 | I84: Pune | J84: Full-time | K84: =_xlfn.XLOOKUP(A84,attrition_cleaned!$A:$A,attrition_cleaned!$B:$B,"Missing") -> Yes | L84: 43933 | M84: =_xlfn.XLOOKUP(A84,compensation_cleaned!$A:$A,compensation_cleaned!$B:$B,"Missing") -> 942607 | N84: =_xlfn.XLOOKUP(A84,compensation_cleaned!$A:$A,compensation_cleaned!$C:$C,"Missing") -> 93520 | O84: =_xlfn.XLOOKUP(A84,compensation_cleaned!$A:$A,compensation_cleaned!$D:$D,"Missing") -> L3 | P84: =_xlfn.XLOOKUP(A84,engagement_pivot!$A:$A,engagement_pivot!$B:$B,"Missing") -> 1 | Q84: =IF( _xlfn.XLOOKUP(A84, engagement_pivot!A:A, engagement_pivot!C:C, 0) > 0, "Yes", "No" ) -> Yes | R84: =IF(K84="Yes",DATEDIF(G84,L84,"M"),DATEDIF(G84,DATE(2023,12,31),"M")) -> 37 | S84: =IF(R84<=12,"0–12 months", IF(R84<=36,"13–36 months","37+ months")) -> 37+ months | T84: =_xlfn.XLOOKUP(A84,performance_pivot!$A:$A,performance_pivot!$B:$B,"Missing") -> 3 | U84: =_xlfn.XLOOKUP(A84,compensation_cleaned!$A:$A,compensation_cleaned!$F:$F,"Missing") -> 1044648.5 | V84: =IF(M84>U84,"Above Avg Pay","Below Avg Pay") -> Below Avg Pay | W84: =IF(T84>=4,"High Performer","Low/Avg Performer") -> Low/Avg Performer | Y84: =IF( AND(V84="Above Avg Pay",W84="High Performer"),"Well Aligned", IF( AND(V84="Below Avg Pay",W84="High Performer"),"Underpaid High Performer", IF( AND(V84="Above Avg Pay",W84="Low/Avg Performer"),"Overpaid Low Performer", "Low Pay & Low Performance" ) ) ) -> Low Pay & Low Performance
A85: E100083 | B85: M | C85: 34 | D85: Graduate | E85: HR | F85: HR Business Partner | G85: 44861 | H85: M255 | I85: Pune | J85: Full-time | K85: =_xlfn.XLOOKUP(A85,attrition_cleaned!$A:$A,attrition_cleaned!$B:$B,"Missing") -> No | M85: =_xlfn.XLOOKUP(A85,compensation_cleaned!$A:$A,compensation_cleaned!$B:$B,"Missing") -> 1013036 | N85: =_xlfn.XLOOKUP(A85,compensation_cleaned!$A:$A,compensation_cleaned!$C:$C,"Missing") -> 120630 | O85: =_xlfn.XLOOKUP(A85,compensation_cleaned!$A:$A,compensation_cleaned!$D:$D,"Missing") -> L3 | P85: =_xlfn.XLOOKUP(A85,engagement_pivot!$A:$A,engagement_pivot!$B:$B,"Missing") -> 1 | Q85: =IF( _xlfn.XLOOKUP(A85, engagement_pivot!A:A, engagement_pivot!C:C, 0) > 0, "Yes", "No" ) -> Yes | R85: =IF(K85="Yes",DATEDIF(G85,L85,"M"),DATEDIF(G85,DATE(2023,12,31),"M")) -> 14 | S85: =IF(R85<=12,"0–12 months", IF(R85<=36,"13–36 months","37+ months")) -> 13–36 months | T85: =_xlfn.XLOOKUP(A85,performance_pivot!$A:$A,performance_pivot!$B:$B,"Missing") -> 2 | U85: =_xlfn.XLOOKUP(A85,compensation_cleaned!$A:$A,compensation_cleaned!$F:$F,"Missing") -> 1044648.5 | V85: =IF(M85>U85,"Above Avg Pay","Below Avg Pay") -> Below Avg Pay | W85: =IF(T85>=4,"High Performer","Low/Avg Performer") -> Low/Avg Performer | Y85: =IF( AND(V85="Above Avg Pay",W85="High Performer"),"Well Aligned", IF( AND(V85="Below Avg Pay",W85="High Performer"),"Underpaid High Performer", IF( AND(V85="Above Avg Pay",W85="Low/Avg Performer"),"Overpaid Low Performer", "Low Pay & Low Performance" ) ) ) -> Low Pay & Low Performance
A86: E100084 | B86: M | C86: 27 | D86: Graduate | E86: Sales | F86: Sales Executive | G86: 44267 | H86: M214 | I86: Bangalore | J86: Full-time | K86: =_xlfn.XLOOKUP(A86,attrition_cleaned!$A:$A,attrition_cleaned!$B:$B,"Missing") -> No | M86: =_xlfn.XLOOKUP(A86,compensation_cleaned!$A:$A,compensation_cleaned!$B:$B,"Missing") -> 460039 | N86: =_xlfn.XLOOKUP(A86,compensation_cleaned!$A:$A,compensation_cleaned!$C:$C,"Missing") -> 55771 | O86: =_xlfn.XLOOKUP(A86,compensation_cleaned!$A:$A,compensation_cleaned!$D:$D,"Missing") -> L1 | P86: =_xlfn.XLOOKUP(A86,engagement_pivot!$A:$A,engagement_pivot!$B:$B,"Missing") -> 5 | Q86: =IF( _xlfn.XLOOKUP(A86, engagement_pivot!A:A, engagement_pivot!C:C, 0) > 0, "Yes", "No" ) -> Yes | R86: =IF(K86="Yes",DATEDIF(G86,L86,"M"),DATEDIF(G86,DATE(2023,12,31),"M")) -> 33 | S86: =IF(R86<=12,"0–12 months", IF(R86<=36,"13–36 months","37+ months")) -> 13–36 months | T86: =_xlfn.XLOOKUP(A86,performance_pivot!$A:$A,performance_pivot!$B:$B,"Missing") -> 4 | U86: =_xlfn.XLOOKUP(A86,compensation_cleaned!$A:$A,compensation_cleaned!$F:$F,"Missing") -> 499723.04 | V86: =IF(M86>U86,"Above Avg Pay","Below Avg Pay") -> Below Avg Pay | W86: =IF(T86>=4,"High Performer","Low/Avg Performer") -> High Performer | Y86: =IF( AND(V86="Above Avg Pay",W86="High Performer"),"Well Aligned", IF( AND(V86="Below Avg Pay",W86="High Performer"),"Underpaid High Performer", IF( AND(V86="Above Avg Pay",W86="Low/Avg Performer"),"Overpaid Low Performer", "Low Pay & Low Performance" ) ) ) -> Underpaid High Performer
A87: E100085 | B87: M | C87: 28 | D87: Graduate | E87: Finance | F87: Accountant | G87: 43798 | H87: M325 | I87: Delhi | J87: Full-time | K87: =_xlfn.XLOOKUP(A87,attrition_cleaned!$A:$A,attrition_cleaned!$B:$B,"Missing") -> No | M87: =_xlfn.XLOOKUP(A87,compensation_cleaned!$A:$A,compensation_cleaned!$B:$B,"Missing") -> 559381 | N87: =_xlfn.XLOOKUP(A87,compensation_cleaned!$A:$A,compensation_cleaned!$C:$C,"Missing") -> 57955 | O87: =_xlfn.XLOOKUP(A87,compensation_cleaned!$A:$A,compensation_cleaned!$D:$D,"Missing") -> L1 | P87: =_xlfn.XLOOKUP(A87,engagement_pivot!$A:$A,engagement_pivot!$B:$B,"Missing") -> 3 | Q87: =IF( _xlfn.XLOOKUP(A87, engagement_pivot!A:A, engagement_pivot!C:C, 0) > 0, "Yes", "No" ) -> Yes | R87: =IF(K87="Yes",DATEDIF(G87,L87,"M"),DATEDIF(G87,DATE(2023,12,31),"M")) -> 49 | S87: =IF(R87<=12,"0–12 months", IF(R87<=36,"13–36 months","37+ months")) -> 37+ months | T87: =_xlfn.XLOOKUP(A87,performance_pivot!$A:$A,performance_pivot!$B:$B,"Missing") -> 3.5 | U87: =_xlfn.XLOOKUP(A87,compensation_cleaned!$A:$A,compensation_cleaned!$F:$F,"Missing") -> 499723.04 | V87: =IF(M87>U87,"Above Avg Pay","Below Avg Pay") -> Above Avg Pay | W87: =IF(T87>=4,"High Performer","Low/Avg Performer") -> Low/Avg Performer | Y87: =IF( AND(V87="Above Avg Pay",W87="High Performer"),"Well Aligned", IF( AND(V87="Below Avg Pay",W87="High Performer"),"Underpaid High Performer", IF( AND(V87="Above Avg Pay",W87="Low/Avg Performer"),"Overpaid Low Performer", "Low Pay & Low Performance" ) ) ) -> Overpaid Low Performer
A88: E100086 | B88: F | C88: 24 | D88: Graduate | E88: Operations | F88: Process Manager | G88: 44808 | H88: M345 | I88: Delhi | J88: Full-time | K88: =_xlfn.XLOOKUP(A88,attrition_cleaned!$A:$A,attrition_cleaned!$B:$B,"Missing") -> No | M88: =_xlfn.XLOOKUP(A88,compensation_cleaned!$A:$A,compensation_cleaned!$B:$B,"Missing") -> 501135 | N88: =_xlfn.XLOOKUP(A88,compensation_cleaned!$A:$A,compensation_cleaned!$C:$C,"Missing") -> 66187 | O88: =_xlfn.XLOOKUP(A88,compensation_cleaned!$A:$A,compensation_cleaned!$D:$D,"Missing") -> L1 | P88: =_xlfn.XLOOKUP(A88,engagement_pivot!$A:$A,engagement_pivot!$B:$B,"Missing") -> 3.5 | Q88: =IF( _xlfn.XLOOKUP(A88, engagement_pivot!A:A, engagement_pivot!C:C, 0) > 0, "Yes", "No" ) -> Yes | R88: =IF(K88="Yes",DATEDIF(G88,L88,"M"),DATEDIF(G88,DATE(2023,12,31),"M")) -> 15 | S88: =IF(R88<=12,"0–12 months", IF(R88<=36,"13–36 months","37+ months")) -> 13–36 months | T88: =_xlfn.XLOOKUP(A88,performance_pivot!$A:$A,performance_pivot!$B:$B,"Missing") -> 3.3333333 | U88: =_xlfn.XLOOKUP(A88,compensation_cleaned!$A:$A,compensation_cleaned!$F:$F,"Missing") -> 499723.04 | V88: =IF(M88>U88,"Above Avg Pay","Below Avg Pay") -> Above Avg Pay | W88: =IF(T88>=4,"High Performer","Low/Avg Performer") -> Low/Avg Performer | Y88: =IF( AND(V88="Above Avg Pay",W88="High Performer"),"Well Aligned", IF( AND(V88="Below Avg Pay",W88="High Performer"),"Underpaid High Performer", IF( AND(V88="Above Avg Pay",W88="Low/Avg Performer"),"Overpaid Low Performer", "Low Pay & Low Performance" ) ) ) -> Overpaid Low Performer
A89: E100087 | B89: M | C89: 41 | D89: Graduate | E89: HR | F89: HR Executive | G89: 45208 | H89: M258 | I89: Mumbai | J89: Full-time | K89: =_xlfn.XLOOKUP(A89,attrition_cleaned!$A:$A,attrition_cleaned!$B:$B,"Missing") -> No | M89: =_xlfn.XLOOKUP(A89,compensation_cleaned!$A:$A,compensation_cleaned!$B:$B,"Missing") -> 687232 | N89: =_xlfn.XLOOKUP(A89,compensation_cleaned!$A:$A,compensation_cleaned!$C:$C,"Missing") -> 45077 | O89: =_xlfn.XLOOKUP(A89,compensation_cleaned!$A:$A,compensation_cleaned!$D:$D,"Missing") -> L2 | P89: =_xlfn.XLOOKUP(A89,engagement_pivot!$A:$A,engagement_pivot!$B:$B,"Missing") -> 4 | Q89: =IF( _xlfn.XLOOKUP(A89, engagement_pivot!A:A, engagement_pivot!C:C, 0) > 0, "Yes", "No" ) -> Yes | R89: =IF(K89="Yes",DATEDIF(G89,L89,"M"),DATEDIF(G89,DATE(2023,12,31),"M")) -> 2 | S89: =IF(R89<=12,"0–12 months", IF(R89<=36,"13–36 months","37+ months")) -> 0–12 months | T89: =_xlfn.XLOOKUP(A89,performance_pivot!$A:$A,performance_pivot!$B:$B,"Missing") -> 3.25 | U89: =_xlfn.XLOOKUP(A89,compensation_cleaned!$A:$A,compensation_cleaned!$F:$F,"Missing") -> 746435.4 | V89: =IF(M89>U89,"Above Avg Pay","Below Avg Pay") -> Below Avg Pay | W89: =IF(T89>=4,"High Performer","Low/Avg Performer") -> Low/Avg Performer | Y89: =IF( AND(V89="Above Avg Pay",W89="High Performer"),"Well Aligned", IF( AND(V89="Below Avg Pay",W89="High Performer"),"Underpaid High Performer", IF( AND(V89="Above Avg Pay",W89="Low/Avg Performer"),"Overpaid Low Performer", "Low Pay & Low Performance" ) ) ) -> Low Pay & Low Performance
A90: E100088 | B90: M | C90: 27 | D90: Graduate | E90: IT | F90: Software Engineer | G90: 44196 | H90: M311 | I90: Delhi | J90: Contract | K90: =_xlfn.XLOOKUP(A90,attrition_cleaned!$A:$A,attrition_cleaned!$B:$B,"Missing") -> No | M90: =_xlfn.XLOOKUP(A90,compensation_cleaned!$A:$A,compensation_cleaned!$B:$B,"Missing") -> 836164 | N90: =_xlfn.XLOOKUP(A90,compensation_cleaned!$A:$A,compensation_cleaned!$C:$C,"Missing") -> 73420 | O90: =_xlfn.XLOOKUP(A90,compensation_cleaned!$A:$A,compensation_cleaned!$D:$D,"Missing") -> L2 | P90: =_xlfn.XLOOKUP(A90,engagement_pivot!$A:$A,engagement_pivot!$B:$B,"Missing") -> 5 | Q90: =IF( _xlfn.XLOOKUP(A90, engagement_pivot!A:A, engagement_pivot!C:C, 0) > 0, "Yes", "No" ) -> Yes | R90: =IF(K90="Yes",DATEDIF(G90,L90,"M"),DATEDIF(G90,DATE(2023,12,31),"M")) -> 36 | S90: =IF(R90<=12,"0–12 months", IF(R90<=36,"13–36 months","37+ months")) -> 13–36 months | T90: =_xlfn.XLOOKUP(A90,performance_pivot!$A:$A,performance_pivot!$B:$B,"Missing") -> 3 | U90: =_xlfn.XLOOKUP(A90,compensation_cleaned!$A:$A,compensation_cleaned!$F:$F,"Missing") -> 746435.4 | V90: =IF(M90>U90,"Above Avg Pay","Below Avg Pay") -> Above Avg Pay | W90: =IF(T90>=4,"High Performer","Low/Avg Performer") -> Low/Avg Performer | Y90: =IF( AND(V90="Above Avg Pay",W90="High Performer"),"Well Aligned", IF( AND(V90="Below Avg Pay",W90="High Performer"),"Underpaid High Performer", IF( AND(V90="Above Avg Pay",W90="Low/Avg Performer"),"Overpaid Low Performer", "Low Pay & Low Performance" ) ) ) -> Overpaid Low Performer
A91: E100089 | B91: M | C91: 26 | D91: Postgraduate | E91: IT | F91: QA Engineer | G91: 42978 | H91: M205 | I91: Hyderabad | J91: Full-time | K91: =_xlfn.XLOOKUP(A91,attrition_cleaned!$A:$A,attrition_cleaned!$B:$B,"Missing") -> No | M91: =_xlfn.XLOOKUP(A91,compensation_cleaned!$A:$A,compensation_cleaned!$B:$B,"Missing") -> 1192007 | N91: =_xlfn.XLOOKUP(A91,compensation_cleaned!$A:$A,compensation_cleaned!$C:$C,"Missing") -> 98331 | O91: =_xlfn.XLOOKUP(A91,compensation_cleaned!$A:$A,compensation_cleaned!$D:$D,"Missing") -> L3 | P91: =_xlfn.XLOOKUP(A91,engagement_pivot!$A:$A,engagement_pivot!$B:$B,"Missing") -> 3 | Q91: =IF( _xlfn.XLOOKUP(A91, engagement_pivot!A:A, engagement_pivot!C:C, 0) > 0, "Yes", "No" ) -> Yes | R91: =IF(K91="Yes",DATEDIF(G91,L91,"M"),DATEDIF(G91,DATE(2023,12,31),"M")) -> 76 | S91: =IF(R91<=12,"0–12 months", IF(R91<=36,"13–36 months","37+ months")) -> 37+ months | T91: =_xlfn.XLOOKUP(A91,performance_pivot!$A:$A,performance_pivot!$B:$B,"Missing") -> 4.3333333 | U91: =_xlfn.XLOOKUP(A91,compensation_cleaned!$A:$A,compensation_cleaned!$F:$F,"Missing") -> 1044648.5 | V91: =IF(M91>U91,"Above Avg Pay","Below Avg Pay") -> Above Avg Pay | W91: =IF(T91>=4,"High Performer","Low/Avg Performer") -> High Performer | Y91: =IF( AND(V91="Above Avg Pay",W91="High Performer"),"Well Aligned", IF( AND(V91="Below Avg Pay",W91="High Performer"),"Underpaid High Performer", IF( AND(V91="Above Avg Pay",W91="Low/Avg Performer"),"Overpaid Low Performer", "Low Pay & Low Performance" ) ) ) -> Well Aligned
A92: E100090 | B92: F | C92: 38 | D92: Graduate | E92: Sales | F92: Account Manager | G92: 44606 | H92: M261 | I92: Bangalore | J92: Full-time | K92: =_xlfn.XLOOKUP(A92,attrition_cleaned!$A:$A,attrition_cleaned!$B:$B,"Missing") -> Yes | L92: 45597 | M92: =_xlfn.XLOOKUP(A92,compensation_cleaned!$A:$A,compensation_cleaned!$B:$B,"Missing") -> 1397305 | N92: =_xlfn.XLOOKUP(A92,compensation_cleaned!$A:$A,compensation_cleaned!$C:$C,"Missing") -> 163417 | O92: =_xlfn.XLOOKUP(A92,compensation_cleaned!$A:$A,compensation_cleaned!$D:$D,"Missing") -> L4 | P92: =_xlfn.XLOOKUP(A92,engagement_pivot!$A:$A,engagement_pivot!$B:$B,"Missing") -> 4 | Q92: =IF( _xlfn.XLOOKUP(A92, engagement_pivot!A:A, engagement_pivot!C:C, 0) > 0, "Yes", "No" ) -> Yes | R92: =IF(K92="Yes",DATEDIF(G92,L92,"M"),DATEDIF(G92,DATE(2023,12,31),"M")) -> 32 | S92: =IF(R92<=12,"0–12 months", IF(R92<=36,"13–36 months","37+ months")) -> 13–36 months | T92: =_xlfn.XLOOKUP(A92,performance_pivot!$A:$A,performance_pivot!$B:$B,"Missing") -> 3 | U92: =_xlfn.XLOOKUP(A92,compensation_cleaned!$A:$A,compensation_cleaned!$F:$F,"Missing") -> 1044648.5 | V92: =IF(M92>U92,"Above Avg Pay","Below Avg Pay") -> Above Avg Pay | W92: =IF(T92>=4,"High Performer","Low/Avg Performer") -> Low/Avg Performer | Y92: =IF( AND(V92="Above Avg Pay",W92="High Performer"),"Well Aligned", IF( AND(V92="Below Avg Pay",W92="High Performer"),"Underpaid High Performer", IF( AND(V92="Above Avg Pay",W92="Low/Avg Performer"),"Overpaid Low Performer", "Low Pay & Low Performance" ) ) ) -> Overpaid Low Performer
A93: E100091 | B93: F | C93: 26 | D93: Graduate | E93: Sales | F93: Account Manager | G93: 44194 | H93: M317 | I93: Delhi | J93: Full-time | K93: =_xlfn.XLOOKUP(A93,attrition_cleaned!$A:$A,attrition_cleaned!$B:$B,"Missing") -> No | M93: =_xlfn.XLOOKUP(A93,compensation_cleaned!$A:$A,compensation_cleaned!$B:$B,"Missing") -> 944577 | N93: =_xlfn.XLOOKUP(A93,compensation_cleaned!$A:$A,compensation_cleaned!$C:$C,"Missing") -> 103611 | O93: =_xlfn.XLOOKUP(A93,compensation_cleaned!$A:$A,compensation_cleaned!$D:$D,"Missing") -> L3 | P93: =_xlfn.XLOOKUP(A93,engagement_pivot!$A:$A,engagement_pivot!$B:$B,"Missing") -> 3.6666667 | Q93: =IF( _xlfn.XLOOKUP(A93, engagement_pivot!A:A, engagement_pivot!C:C, 0) > 0, "Yes", "No" ) -> Yes | R93: =IF(K93="Yes",DATEDIF(G93,L93,"M"),DATEDIF(G93,DATE(2023,12,31),"M")) -> 36 | S93: =IF(R93<=12,"0–12 months", IF(R93<=36,"13–36 months","37+ months")) -> 13–36 months | T93: =_xlfn.XLOOKUP(A93,performance_pivot!$A:$A,performance_pivot!$B:$B,"Missing") -> 4 | U93: =_xlfn.XLOOKUP(A93,compensation_cleaned!$A:$A,compensation_cleaned!$F:$F,"Missing") -> 1044648.5 | V93: =IF(M93>U93,"Above Avg Pay","Below Avg Pay") -> Below Avg Pay | W93: =IF(T93>=4,"High Performer","Low/Avg Performer") -> High Performer | Y93: =IF( AND(V93="Above Avg Pay",W93="High Performer"),"Well Aligned", IF( AND(V93="Below Avg Pay",W93="High Performer"),"Underpaid High Performer", IF( AND(V93="Above Avg Pay",W93="Low/Avg Performer"),"Overpaid Low Performer", "Low Pay & Low Performance" ) ) ) -> Underpaid High Performer
A94: E100092 | B94: M | C94: 35 | D94: Graduate | E94: IT | F94: Software Engineer | G94: 44923 | H94: M236 | I94: Chennai | J94: Full-time | K94: =_xlfn.XLOOKUP(A94,attrition_cleaned!$A:$A,attrition_cleaned!$B:$B,"Missing") -> No | M94: =_xlfn.XLOOKUP(A94,compensation_cleaned!$A:$A,compensation_cleaned!$B:$B,"Missing") -> 406377 | N94: =_xlfn.XLOOKUP(A94,compensation_cleaned!$A:$A,compensation_cleaned!$C:$C,"Missing") -> 20501 | O94: =_xlfn.XLOOKUP(A94,compensation_cleaned!$A:$A,compensation_cleaned!$D:$D,"Missing") -> L1 | P94: =_xlfn.XLOOKUP(A94,engagement_pivot!$A:$A,engagement_pivot!$B:$B,"Missing") -> 2 | Q94: =IF( _xlfn.XLOOKUP(A94, engagement_pivot!A:A, engagement_pivot!C:C, 0) > 0, "Yes", "No" ) -> Yes | R94: =IF(K94="Yes",DATEDIF(G94,L94,"M"),DATEDIF(G94,DATE(2023,12,31),"M")) -> 12 | S94: =IF(R94<=12,"0–12 months", IF(R94<=36,"13–36 months","37+ months")) -> 0–12 months | T94: =_xlfn.XLOOKUP(A94,performance_pivot!$A:$A,performance_pivot!$B:$B,"Missing") -> 3.3333333 | U94: =_xlfn.XLOOKUP(A94,compensation_cleaned!$A:$A,compensation_cleaned!$F:$F,"Missing") -> 499723.04 | V94: =IF(M94>U94,"Above Avg Pay","Below Avg Pay") -> Below Avg Pay | W94: =IF(T94>=4,"High Performer","Low/Avg Performer") -> Low/Avg Performer | Y94: =IF( AND(V94="Above Avg Pay",W94="High Performer"),"Well Aligned", IF( AND(V94="Below Avg Pay",W94="High Performer"),"Underpaid High Performer", IF( AND(V94="Above Avg Pay",W94="Low/Avg Performer"),"Overpaid Low Performer", "Low Pay & Low Performance" ) ) ) -> Low Pay & Low Performance
A95: E100093 | B95: M | C95: 27 | D95: Graduate | E95: Finance | F95: Financial Analyst | G95: 44762 | H95: M209 | I95: Mumbai | J95: Full-time | K95: =_xlfn.XLOOKUP(A95,attrition_cleaned!$A:$A,attrition_cleaned!$B:$B,"Missing") -> No | M95: =_xlfn.XLOOKUP(A95,compensation_cleaned!$A:$A,compensation_cleaned!$B:$B,"Missing") -> 587972 | N95: =_xlfn.XLOOKUP(A95,compensation_cleaned!$A:$A,compensation_cleaned!$C:$C,"Missing") -> 45092 | O95: =_xlfn.XLOOKUP(A95,compensation_cleaned!$A:$A,compensation_cleaned!$D:$D,"Missing") -> L1 | P95: =_xlfn.XLOOKUP(A95,engagement_pivot!$A:$A,engagement_pivot!$B:$B,"Missing") -> 1 | Q95: =IF( _xlfn.XLOOKUP(A95, engagement_pivot!A:A, engagement_pivot!C:C, 0) > 0, "Yes", "No" ) -> Yes | R95: =IF(K95="Yes",DATEDIF(G95,L95,"M"),DATEDIF(G95,DATE(2023,12,31),"M")) -> 17 | S95: =IF(R95<=12,"0–12 months", IF(R95<=36,"13–36 months","37+ months")) -> 13–36 months | T95: =_xlfn.XLOOKUP(A95,performance_pivot!$A:$A,performance_pivot!$B:$B,"Missing") -> 4 | U95: =_xlfn.XLOOKUP(A95,compensation_cleaned!$A:$A,compensation_cleaned!$F:$F,"Missing") -> 499723.04 | V95: =IF(M95>U95,"Above Avg Pay","Below Avg Pay") -> Above Avg Pay | W95: =IF(T95>=4,"High Performer","Low/Avg Performer") -> High Performer | Y95: =IF( AND(V95="Above Avg Pay",W95="High Performer"),"Well Aligned", IF( AND(V95="Below Avg Pay",W95="High Performer"),"Underpaid High Performer", IF( AND(V95="Above Avg Pay",W95="Low/Avg Performer"),"Overpaid Low Performer", "Low Pay & Low Performance" ) ) ) -> Well Aligned
A96: E100094 | B96: F | C96: 41 | D96: Graduate | E96: Finance | F96: Accountant | G96: 44796 | H96: M300 | I96: Bangalore | J96: Full-time | K96: =_xlfn.XLOOKUP(A96,attrition_cleaned!$A:$A,attrition_cleaned!$B:$B,"Missing") -> No | M96: =_xlfn.XLOOKUP(A96,compensation_cleaned!$A:$A,compensation_cleaned!$B:$B,"Missing") -> 1699749 | N96: =_xlfn.XLOOKUP(A96,compensation_cleaned!$A:$A,compensation_cleaned!$C:$C,"Missing") -> 208258 | O96: =_xlfn.XLOOKUP(A96,compensation_cleaned!$A:$A,compensation_cleaned!$D:$D,"Missing") -> L5 | P96: =_xlfn.XLOOKUP(A96,engagement_pivot!$A:$A,engagement_pivot!$B:$B,"Missing") -> 1 | Q96: =IF( _xlfn.XLOOKUP(A96, engagement_pivot!A:A, engagement_pivot!C:C, 0) > 0, "Yes", "No" ) -> Yes | R96: =IF(K96="Yes",DATEDIF(G96,L96,"M"),DATEDIF(G96,DATE(2023,12,31),"M")) -> 16 | S96: =IF(R96<=12,"0–12 months", IF(R96<=36,"13–36 months","37+ months")) -> 13–36 months | T96: =_xlfn.XLOOKUP(A96,performance_pivot!$A:$A,performance_pivot!$B:$B,"Missing") -> 4.3333333 | U96: =_xlfn.XLOOKUP(A96,compensation_cleaned!$A:$A,compensation_cleaned!$F:$F,"Missing") -> 1044648.5 | V96: =IF(M96>U96,"Above Avg Pay","Below Avg Pay") -> Above Avg Pay | W96: =IF(T96>=4,"High Performer","Low/Avg Performer") -> High Performer | Y96: =IF( AND(V96="Above Avg Pay",W96="High Performer"),"Well Aligned", IF( AND(V96="Below Avg Pay",W96="High Performer"),"Underpaid High Performer", IF( AND(V96="Above Avg Pay",W96="Low/Avg Performer"),"Overpaid Low Performer", "Low Pay & Low Performance" ) ) ) -> Well Aligned
A97: E100095 | B97: M | C97: 24 | D97: Graduate | E97: Sales | F97: Sales Executive | G97: 44679 | H97: M248 | I97: Mumbai | J97: Full-time | K97: =_xlfn.XLOOKUP(A97,attrition_cleaned!$A:$A,attrition_cleaned!$B:$B,"Missing") -> Yes | L97: 45639 | M97: =_xlfn.XLOOKUP(A97,compensation_cleaned!$A:$A,compensation_cleaned!$B:$B,"Missing") -> 900605 | N97: =_xlfn.XLOOKUP(A97,compensation_cleaned!$A:$A,compensation_cleaned!$C:$C,"Missing") -> 118359 | O97: =_xlfn.XLOOKUP(A97,compensation_cleaned!$A:$A,compensation_cleaned!$D:$D,"Missing") -> L3 | P97: =_xlfn.XLOOKUP(A97,engagement_pivot!$A:$A,engagement_pivot!$B:$B,"Missing") -> 3.5 | Q97: =IF( _xlfn.XLOOKUP(A97, engagement_pivot!A:A, engagement_pivot!C:C, 0) > 0, "Yes", "No" ) -> Yes | R97: =IF(K97="Yes",DATEDIF(G97,L97,"M"),DATEDIF(G97,DATE(2023,12,31),"M")) -> 31 | S97: =IF(R97<=12,"0–12 months", IF(R97<=36,"13–36 months","37+ months")) -> 13–36 months | T97: =_xlfn.XLOOKUP(A97,performance_pivot!$A:$A,performance_pivot!$B:$B,"Missing") -> 3 | U97: =_xlfn.XLOOKUP(A97,compensation_cleaned!$A:$A,compensation_cleaned!$F:$F,"Missing") -> 1044648.5 | V97: =IF(M97>U97,"Above Avg Pay","Below Avg Pay") -> Below Avg Pay | W97: =IF(T97>=4,"High Performer","Low/Avg Performer") -> Low/Avg Performer | Y97: =IF( AND(V97="Above Avg Pay",W97="High Performer"),"Well Aligned", IF( AND(V97="Below Avg Pay",W97="High Performer"),"Underpaid High Performer", IF( AND(V97="Above Avg Pay",W97="Low/Avg Performer"),"Overpaid Low Performer", "Low Pay & Low Performance" ) ) ) -> Low Pay & Low Performance
A98: E100096 | B98: F | C98: 32 | D98: Postgraduate | E98: Finance | F98: Accountant | G98: 43069 | H98: M275 | I98: Pune | J98: Full-time | K98: =_xlfn.XLOOKUP(A98,attrition_cleaned!$A:$A,attrition_cleaned!$B:$B,"Missing") -> No | M98: =_xlfn.XLOOKUP(A98,compensation_cleaned!$A:$A,compensation_cleaned!$B:$B,"Missing") -> 418441 | N98: =_xlfn.XLOOKUP(A98,compensation_cleaned!$A:$A,compensation_cleaned!$C:$C,"Missing") -> 44064 | O98: =_xlfn.XLOOKUP(A98,compensation_cleaned!$A:$A,compensation_cleaned!$D:$D,"Missing") -> L1 | P98: =_xlfn.XLOOKUP(A98,engagement_pivot!$A:$A,engagement_pivot!$B:$B,"Missing") -> 2 | Q98: =IF( _xlfn.XLOOKUP(A98, engagement_pivot!A:A, engagement_pivot!C:C, 0) > 0, "Yes", "No" ) -> Yes | R98: =IF(K98="Yes",DATEDIF(G98,L98,"M"),DATEDIF(G98,DATE(2023,12,31),"M")) -> 73 | S98: =IF(R98<=12,"0–12 months", IF(R98<=36,"13–36 months","37+ months")) -> 37+ months | T98: =_xlfn.XLOOKUP(A98,performance_pivot!$A:$A,performance_pivot!$B:$B,"Missing") -> 3.5 | U98: =_xlfn.XLOOKUP(A98,compensation_cleaned!$A:$A,compensation_cleaned!$F:$F,"Missing") -> 499723.04 | V98: =IF(M98>U98,"Above Avg Pay","Below Avg Pay") -> Below Avg Pay | W98: =IF(T98>=4,"High Performer","Low/Avg Performer") -> Low/Avg Performer | Y98: =IF( AND(V98="Above Avg Pay",W98="High Performer"),"Well Aligned", IF( AND(V98="Below Avg Pay",W98="High Performer"),"Underpaid High Performer", IF( AND(V98="Above Avg Pay",W98="Low/Avg Performer"),"Overpaid Low Performer", "Low Pay & Low Performance" ) ) ) -> Low Pay & Low Performance
A99: E100097 | B99: M | C99: 30 | D99: Postgraduate | E99: Finance | F99: Accountant | G99: 44108 | H99: M259 | I99: Chennai | J99: Full-time | K99: =_xlfn.XLOOKUP(A99,attrition_cleaned!$A:$A,attrition_cleaned!$B:$B,"Missing") -> No | M99: =_xlfn.XLOOKUP(A99,compensation_cleaned!$A:$A,compensation_cleaned!$B:$B,"Missing") -> 1036378 | N99: =_xlfn.XLOOKUP(A99,compensation_cleaned!$A:$A,compensation_cleaned!$C:$C,"Missing") -> 132509 | O99: =_xlfn.XLOOKUP(A99,compensation_cleaned!$A:$A,compensation_cleaned!$D:$D,"Missing") -> L3 | P99: =_xlfn.XLOOKUP(A99,engagement_pivot!$A:$A,engagement_pivot!$B:$B,"Missing") -> 5 | Q99: =IF( _xlfn.XLOOKUP(A99, engagement_pivot!A:A, engagement_pivot!C:C, 0) > 0, "Yes", "No" ) -> Yes | R99: =IF(K99="Yes",DATEDIF(G99,L99,"M"),DATEDIF(G99,DATE(2023,12,31),"M")) -> 38 | S99: =IF(R99<=12,"0–12 months", IF(R99<=36,"13–36 months","37+ months")) -> 37+ months | T99: =_xlfn.XLOOKUP(A99,performance_pivot!$A:$A,performance_pivot!$B:$B,"Missing") -> 3.75 | U99: =_xlfn.XLOOKUP(A99,compensation_cleaned!$A:$A,compensation_cleaned!$F:$F,"Missing") -> 1044648.5 | V99: =IF(M99>U99,"Above Avg Pay","Below Avg Pay") -> Below Avg Pay | W99: =IF(T99>=4,"High Performer","Low/Avg Performer") -> Low/Avg Performer | Y99: =IF( AND(V99="Above Avg Pay",W99="High Performer"),"Well Aligned", IF( AND(V99="Below Avg Pay",W99="High Performer"),"Underpaid High Performer", IF( AND(V99="Above Avg Pay",W99="Low/Avg Performer"),"Overpaid Low Performer", "Low Pay & Low Performance" ) ) ) -> Low Pay & Low Performance
A100: E100098 | B100: M | C100: 25 | D100: Graduate | E100: Operations | F100: Operations Analyst | G100: 42813 | H100: M241 | I100: Bangalore | J100: Full-time | K100: =_xlfn.XLOOKUP(A100,attrition_cleaned!$A:$A,attrition_cleaned!$B:$B,"Missing") -> No | M100: =_xlfn.XLOOKUP(A100,compensation_cleaned!$A:$A,compensation_cleaned!$B:$B,"Missing") -> 498564 | N100: =_xlfn.XLOOKUP(A100,compensation_cleaned!$A:$A,compensation_cleaned!$C:$C,"Missing") -> 57975 | O100: =_xlfn.XLOOKUP(A100,compensation_cleaned!$A:$A,compensation_cleaned!$D:$D,"Missing") -> L1 | P100: =_xlfn.XLOOKUP(A100,engagement_pivot!$A:$A,engagement_pivot!$B:$B,"Missing") -> 2 | Q100: =IF( _xlfn.XLOOKUP(A100, engagement_pivot!A:A, engagement_pivot!C:C, 0) > 0, "Yes", "No" ) -> Yes | R100: =IF(K100="Yes",DATEDIF(G100,L100,"M"),DATEDIF(G100,DATE(2023,12,31),"M")) -> 81 | S100: =IF(R100<=12,"0–12 months", IF(R100<=36,"13–36 months","37+ months")) -> 37+ months | T100: =_xlfn.XLOOKUP(A100,performance_pivot!$A:$A,performance_pivot!$B:$B,"Missing") -> 2.5 | U100: =_xlfn.XLOOKUP(A100,compensation_cleaned!$A:$A,compensation_cleaned!$F:$F,"Missing") -> 499723.04 | V100: =IF(M100>U100,"Above Avg Pay","Below Avg Pay") -> Below Avg Pay | W100: =IF(T100>=4,"High Performer","Low/Avg Performer") -> Low/Avg Performer | Y100: =IF( AND(V100="Above Avg Pay",W100="High Performer"),"Well Aligned", IF( AND(V100="Below Avg Pay",W100="High Performer"),"Underpaid High Performer", IF( AND(V100="Above Avg Pay",W100="Low/Avg Performer"),"Overpaid Low Performer", "Low Pay & Low Performance" ) ) ) -> Low Pay & Low Performance
...

Sheet attrition_cleaned
A1: employee_id | B1: attrition_flag | C1: exit_date | D1: exit_reason | E1: exit_reason_cleaned
A2: E100000 | B2: No | E2: =IF(B2="No"," ",IF(AND(B2="Yes",D2=" "),"Not Recorded",D2))
A3: E100001 | B3: No | E3: =IF(B3="No"," ",IF(AND(B3="Yes",D3=" "),"Not Recorded",D3))
A4: E100002 | B4: No | E4: =IF(B4="No"," ",IF(AND(B4="Yes",D4=" "),"Not Recorded",D4))
A5: E100003 | B5: No | E5: =IF(B5="No"," ",IF(AND(B5="Yes",D5=" "),"Not Recorded",D5))
A6: E100004 | B6: No | E6: =IF(B6="No"," ",IF(AND(B6="Yes",D6=" "),"Not Recorded",D6))
A7: E100005 | B7: No | E7: =IF(B7="No"," ",IF(AND(B7="Yes",D7=" "),"Not Recorded",D7))
A8: E100006 | B8: No | E8: =IF(B8="No"," ",IF(AND(B8="Yes",D8=" "),"Not Recorded",D8))
A9: E100007 | B9: No | E9: =IF(B9="No"," ",IF(AND(B9="Yes",D9=" "),"Not Recorded",D9))
A10: E100008 | B10: No | E10: =IF(B10="No"," ",IF(AND(B10="Yes",D10=" "),"Not Recorded",D10))
A11: E100009 | B11: No | E11: =IF(B11="No"," ",IF(AND(B11="Yes",D11=" "),"Not Recorded",D11))
A12: E100010 | B12: No | E12: =IF(B12="No"," ",IF(AND(B12="Yes",D12=" "),"Not Recorded",D12))
A13: E100011 | B13: No | E13: =IF(B13="No"," ",IF(AND(B13="Yes",D13=" "),"Not Recorded",D13))
... A23: E100021 | B23: No | E23: =IF(B23="No"," ",IF(AND(B23="Yes",D23=" "),"Not Recorded",D23))
A24: E100022 | B24: Yes | C24: 44899 | D24: Career Stagnation | E24: =IF(B24="No"," ",IF(AND(B24="Yes",D24=" "),"Not Recorded",D24)) -> Career Stagnation
A25: E100023 | B25: No | E25: =IF(B25="No"," ",IF(AND(B25="Yes",D25=" "),"Not Recorded",D25))
A26: E100024 | B26: No | E26: =IF(B26="No"," ",IF(AND(B26="Yes",D26=" "),"Not Recorded",D26))
A27: E100025 | B27: Yes | C27: 44569 | D27: Work-Life Balance | E27: =IF(B27="No"," ",IF(AND(B27="Yes",D27=" "),"Not Recorded",D27)) -> Work-Life Balance
A28: E100026 | B28: No | E28: =IF(B28="No"," ",IF(AND(B28="Yes",D28=" "),"Not Recorded",D28))
A29: E100027 | B29: No | E29: =IF(B29="No"," ",IF(AND(B29="Yes",D29=" "),"Not Recorded",D29))
A30: E100028 | B30: No | E30: =IF(B30="No"," ",IF(AND(B30="Yes",D30=" "),"Not Recorded",D30))
A31: E100029 | B31: No | E31: =IF(B31="No"," ",IF(AND(B31="Yes",D31=" "),"Not Recorded",D31))
A32: E100030 | B32: No | E32: =IF(B32="No"," ",IF(AND(B32="Yes",D32=" "),"Not Recorded",D32))
A33: E100031 | B33: Yes | C33: 44718 | D33: Manager Issues | E33: =IF(B33="No"," ",IF(AND(B33="Yes",D33=" "),"Not Recorded",D33)) -> Manager Issues
A34: E100032 | B34: Yes | C34: 45226 | D34: Manager Issues | E34: =IF(B34="No"," ",IF(AND(B34="Yes",D34=" "),"Not Recorded",D34)) -> Manager Issues
A35: E100033 | B35: Yes | C35: 45626 | D35: Manager Issues | E35: =IF(B35="No"," ",IF(AND(B35="Yes",D35=" "),"Not Recorded",D35)) -> Manager Issues
A36: E100034 | B36: No | E36: =IF(B36="No"," ",IF(AND(B36="Yes",D36=" "),"Not Recorded",D36))
A37: E100035 | B37: No | E37: =IF(B37="No"," ",IF(AND(B37="Yes",D37=" "),"Not Recorded",D37))
A38: E100036 | B38: No | E38: =IF(B38="No"," ",IF(AND(B38="Yes",D38=" "),"Not Recorded",D38))
A39: E100037 | B39: Yes | C39: 43750 | D39: Better Pay | E39: =IF(B39="No"," ",IF(AND(B39="Yes",D39=" "),"Not Recorded",D39)) -> Better Pay
A40: E100038 | B40: No | E40: =IF(B40="No"," ",IF(AND(B40="Yes",D40=" "),"Not Recorded",D40))
A41: E100039 | B41: No | E41: =IF(B41="No"," ",IF(AND(B41="Yes",D41=" "),"Not Recorded",D41))
A42: E100040 | B42: Yes | C42: 44017 | D42: Better Pay | E42: =IF(B42="No"," ",IF(AND(B42="Yes",D42=" "),"Not Recorded",D42)) -> Better Pay
A43: E100041 | B43: No | E43: =IF(B43="No"," ",IF(AND(B43="Yes",D43=" "),"Not Recorded",D43))
A44: E100042 | B44: No | E44: =IF(B44="No"," ",IF(AND(B44="Yes",D44=" "),"Not Recorded",D44))
A45: E100043 | B45: Yes | C45: 44154 | D45: Career Stagnation | E45: =IF(B45="No"," ",IF(AND(B45="Yes",D45=" "),"Not Recorded",D45)) -> Career Stagnation
A46: E100044 | B46: No | E46: =IF(B46="No"," ",IF(AND(B46="Yes",D46=" "),"Not Recorded",D46))
A47: E100045 | B47: Yes | C47: 46131 | D47: Manager Issues | E47: =IF(B47="No"," ",IF(AND(B47="Yes",D47=" "),"Not Recorded",D47)) -> Manager Issues
A48: E100046 | B48: No | E48: =IF(B48="No"," ",IF(AND(B48="Yes",D48=" "),"Not Recorded",D48))
A49: E100047 | B49: No | E49: =IF(B49="No"," ",IF(AND(B49="Yes",D49=" "),"Not Recorded",D49))
A50: E100048 | B50: No | E50: =IF(B50="No"," ",IF(AND(B50="Yes",D50=" "),"Not Recorded",D50))
A51: E100049 | B51: No | E51: =IF(B51="No"," ",IF(AND(B51="Yes",D51=" "),"Not Recorded",D51))
A52: E100050 | B52: Yes | C52: 44765 | D52: Career Stagnation | E52: =IF(B52="No"," ",IF(AND(B52="Yes",D52=" "),"Not Recorded",D52)) -> Career Stagnation
A53: E100051 | B53: No | E53: =IF(B53="No"," ",IF(AND(B53="Yes",D53=" "),"Not Recorded",D53))
A54: E100052 | B54: No | E54: =IF(B54="No"," ",IF(AND(B54="Yes",D54=" "),"Not Recorded",D54))
A55: E100053 | B55: No | E55: =IF(B55="No"," ",IF(AND(B55="Yes",D55=" "),"Not Recorded",D55))
A56: E100054 | B56: No | E56: =IF(B56="No"," ",IF(AND(B56="Yes",D56=" "),"Not Recorded",D56))
A57: E100055 | B57: No | E57: =IF(B57="No"," ",IF(AND(B57="Yes",D57=" "),"Not Recorded",D57))
A58: E100056 | B58: Yes | C58: 45042 | D58: Work-Life Balance | E58: =IF(B58="No"," ",IF(AND(B58="Yes",D58=" "),"Not Recorded",D58)) -> Work-Life Balance
A59: E100057 | B59: No | E59: =IF(B59="No"," ",IF(AND(B59="Yes",D59=" "),"Not Recorded",D59))
A60: E100058 | B60: Yes | C60: 45044 | D60: Career Stagnation | E60: =IF(B60="No"," ",IF(AND(B60="Yes",D60=" "),"Not Recorded",D60)) -> Career Stagnation
A61: E100059 | B61: No | E61: =IF(B61="No"," ",IF(AND(B61="Yes",D61=" "),"Not Recorded",D61))
A62: E100060 | B62: No | E62: =IF(B62="No"," ",IF(AND(B62="Yes",D62=" "),"Not Recorded",D62))
A63: E100061 | B63: No | E63: =IF(B63="No"," ",IF(AND(B63="Yes",D63=" "),"Not Recorded",D63))
A64: E100062 | B64: No | E64: =IF(B64="No"," ",IF(AND(B64="Yes",D64=" "),"Not Recorded",D64))
A65: E100063 | B65: No | E65: =IF(B65="No"," ",IF(AND(B65="Yes",D65=" "),"Not Recorded",D65))
A66: E100064 | B66: No | E66: =IF(B66="No"," ",IF(AND(B66="Yes",D66=" "),"Not Recorded",D66))
A67: E100065 | B67: No | E67: =IF(B67="No"," ",IF(AND(B67="Yes",D67=" "),"Not Recorded",D67))
A68: E100066 | B68: Yes | C68: 44527 | D68: Career Stagnation | E68: =IF(B68="No"," ",IF(AND(B68="Yes",D68=" "),"Not Recorded",D68)) -> Career Stagnation
A69: E100067 | B69: Yes | C69: 43774 | D69: Career Stagnation | E69: =IF(B69="No"," ",IF(AND(B69="Yes",D69=" "),"Not Recorded",D69)) -> Career Stagnation
A70: E100068 | B70: No | E70: =IF(B70="No"," ",IF(AND(B70="Yes",D70=" "),"Not Recorded",D70))
A71: E100069 | B71: No | E71: =IF(B71="No"," ",IF(AND(B71="Yes",D71=" "),"Not Recorded",D71))
A72: E100070 | B72: No | E72: =IF(B72="No"," ",IF(AND(B72="Yes",D72=" "),"Not Recorded",D72))
A73: E100071 | B73: No | E73: =IF(B73="No"," ",IF(AND(B73="Yes",D73=" "),"Not Recorded",D73))
A74: E100072 | B74: No | E74: =IF(B74="No"," ",IF(AND(B74="Yes",D74=" "),"Not Recorded",D74))
A75: E100073 | B75: No | E75: =IF(B75="No"," ",IF(AND(B75="Yes",D75=" "),"Not Recorded",D75))
A76: E100074 | B76: Yes | C76: 43886 | D76: Better Pay | E76: =IF(B76="No"," ",IF(AND(B76="Yes",D76=" "),"Not Recorded",D76)) -> Better Pay
A77: E100075 | B77: No | E77: =IF(B77="No"," ",IF(AND(B77="Yes",D77=" "),"Not Recorded",D77))
A78: E100076 | B78: No | E78: =IF(B78="No"," ",IF(AND(B78="Yes",D78=" "),"Not Recorded",D78))
A79: E100077 | B79: No | E79: =IF(B79="No"," ",IF(AND(B79="Yes",D79=" "),"Not Recorded",D79))
A80: E100078 | B80: Yes | C80: 46589 | D80: Work-Life Balance | E80: =IF(B80="No"," ",IF(AND(B80="Yes",D80=" "),"Not Recorded",D80)) -> Work-Life Balance
A81: E100079 | B81: No | E81: =IF(B81="No"," ",IF(AND(B81="Yes",D81=" "),"Not Recorded",D81))
A82: E100080 | B82: Yes | C82: 44279 | D82: Manager Issues | E82: =IF(B82="No"," ",IF(AND(B82="Yes",D82=" "),"Not Recorded",D82)) -> Manager Issues
A83: E100081 | B83: No | E83: =IF(B83="No"," ",IF(AND(B83="Yes",D83=" "),"Not Recorded",D83))
A84: E100082 | B84: Yes | C84: 43933 | D84: Work-Life Balance | E84: =IF(B84="No"," ",IF(AND(B84="Yes",D84=" "),"Not Recorded",D84)) -> Work-Life Balance
A85: E100083 | B85: No | E85: =IF(B85="No"," ",IF(AND(B85="Yes",D85=" "),"Not Recorded",D85))
A86: E100084 | B86: No | E86: =IF(B86="No"," ",IF(AND(B86="Yes",D86=" "),"Not Recorded",D86))
A87: E100085 | B87: No | E87: =IF(B87="No"," ",IF(AND(B87="Yes",D87=" "),"Not Recorded",D87))
A88: E100086 | B88: No | E88: =IF(B88="No"," ",IF(AND(B88="Yes",D88=" "),"Not Recorded",D88))
A89: E100087 | B89: No | E89: =IF(B89="No"," ",IF(AND(B89="Yes",D89=" "),"Not Recorded",D89))
A90: E100088 | B90: No | E90: =IF(B90="No"," ",IF(AND(B90="Yes",D90=" "),"Not Recorded",D90))
A91: E100089 | B91: No | E91: =IF(B91="No"," ",IF(AND(B91="Yes",D91=" "),"Not Recorded",D91))
A92: E100090 | B92: Yes | C92: 45597 | D92: Better Pay | E92: =IF(B92="No"," ",IF(AND(B92="Yes",D92=" "),"Not Recorded",D92)) -> Better Pay
A93: E100091 | B93: No | E93: =IF(B93="No"," ",IF(AND(B93="Yes",D93=" "),"Not Recorded",D93))
A94: E100092 | B94: No | E94: =IF(B94="No"," ",IF(AND(B94="Yes",D94=" "),"Not Recorded",D94))
A95: E100093 | B95: No | E95: =IF(B95="No"," ",IF(AND(B95="Yes",D95=" "),"Not Recorded",D95))
A96: E100094 | B96: No | E96: =IF(B96="No"," ",IF(AND(B96="Yes",D96=" "),"Not Recorded",D96))
A97: E100095 | B97: Yes | C97: 45639 | D97: Career Stagnation | E97: =IF(B97="No"," ",IF(AND(B97="Yes",D97=" "),"Not Recorded",D97)) -> Career Stagnation
A98: E100096 | B98: No | E98: =IF(B98="No"," ",IF(AND(B98="Yes",D98=" "),"Not Recorded",D98))
A99: E100097 | B99: No | E99: =IF(B99="No"," ",IF(AND(B99="Yes",D99=" "),"Not Recorded",D99))
A100: E100098 | B100: No | E100: =IF(B100="No"," ",IF(AND(B100="Yes",D100=" "),"Not Recorded",D100))
A101: E100099 | B101: No | E101: =IF(B101="No"," ",IF(AND(B101="Yes",D101=" "),"Not Recorded",D101))
A102: E100100 | B102: No | E102: =IF(B102="No"," ",IF(AND(B102="Yes",D102=" "),"Not Recorded",D102))
A103: E100101 | B103: No | E103: =IF(B103="No"," ",IF(AND(B103="Yes",D103=" "),"Not Recorded",D103))
A104: E100102 | B104: No | E104: =IF(B104="No"," ",IF(AND(B104="Yes",D104=" "),"Not Recorded",D104))
A105: E100103 | B105: No | E105: =IF(B105="No"," ",IF(AND(B105="Yes",D105=" "),"Not Recorded",D105))
A106: E100104 | B106: Yes | C106: 46086 | D106: Better Pay | E106: =IF(B106="No"," ",IF(AND(B106="Yes",D106=" "),"Not Recorded",D106)) -> Better Pay
A107: E100105 | B107: No | E107: =IF(B107="No"," ",IF(AND(B107="Yes",D107=" "),"Not Recorded",D107))
A108: E100106 | B108: No | E108: =IF(B108="No"," ",IF(AND(B108="Yes",D108=" "),"Not Recorded",D108))
A109: E100107 | B109: Yes | C109: 44832 | D109: Better Pay | E109: =IF(B109="No"," ",IF(AND(B109="Yes",D109=" "),"Not Recorded",D109)) -> Better Pay
...

Sheet performance_pivot
A3: Employee ID | B3: Average of performance_rating
A4: E100000 | B4: 4
A5: E100001 | B5: 3.25
A6: E100002 | B6: 3
A7: E100003 | B7: 4.25
A8: E100004 | B8: 4
A9: E100005 | B9: 4.5
A10: E100006 | B10: 4
A11: E100007 | B11: 4
A12: E100008 | B12: 3.5
A13: E100009 | B13: 4.25
A14: E100010 | B14: 3
A15: E100011 | B15: 3
... A3204: Grand Total | B3204: 3.4957009

Sheet compensation_cleaned
A1: employee_id | B1: salary | C1: bonus | D1: salary_band | E1: last_hike_date | F1: avg_salary_per_band
A2: E100000 | B2: 417763 | C2: 45322 | D2: L1 | E2: 44646 | F2: =IF(D2="L1",$L$3,IF(D2="L2",$L$4,$L$5)) -> 499723.04
A3: E100001 | B3: 1114335 | C3: 92842 | D3: L3 | E3: 43606 | F3: =IF(D3="L1",$L$3,IF(D3="L2",$L$4,$L$5)) -> 1044648.5 | K3: Avg salary in L1 | L3: =AVERAGEIF(D:D,"L1",B:B) -> 499723.04
A4: E100002 | B4: 819575 | C4: 70960 | D4: L2 | E4: 44311 | F4: =IF(D4="L1",$L$3,IF(D4="L2",$L$4,$L$5)) -> 746435.4 | K4: Avg salary in L2 | L4: =AVERAGEIF(D:D,"L2",B:B) -> 746435.4
A5: E100003 | B5: 485874 | C5: 29469 | D5: L1 | E5: 45542 | F5: =IF(D5="L1",$L$3,IF(D5="L2",$L$4,$L$5)) -> 499723.04 | K5: Avg salary in L3 | L5: =AVERAGEIF(D:D,"L3",B:B) -> 1044648.5
A6: E100004 | B6: 825704 | C6: 45542 | D6: L2 | E6: 44532 | F6: =IF(D6="L1",$L$3,IF(D6="L2",$L$4,$L$5)) -> 746435.4
A7: E100005 | B7: 851431 | C7: 110027 | D7: L2 | E7: 45109 | F7: =IF(D7="L1",$L$3,IF(D7="L2",$L$4,$L$5)) -> 746435.4
A8: E100006 | B8: 660855 | C8: 53466 | D8: L2 | E8: 44578 | F8: =IF(D8="L1",$L$3,IF(D8="L2",$L$4,$L$5)) -> 746435.4
A9: E100007 | B9: 1541591 | C9: 167329 | D9: L4 | E9: 44566 | F9: =IF(D9="L1",$L$3,IF(D9="L2",$L$4,$L$5)) -> 1044648.5
A10: E100008 | B10: 418481 | C10: 38859 | D10: L1 | E10: 44971 | F10: =IF(D10="L1",$L$3,IF(D10="L2",$L$4,$L$5)) -> 499723.04
A11: E100009 | B11: 757662 | C11: 97007 | D11: L2 | E11: 45429 | F11: =IF(D11="L1",$L$3,IF(D11="L2",$L$4,$L$5)) -> 746435.4
A12: E100010 | B12: 1192590 | C12: 110531 | D12: L3 | E12: 45427 | F12: =IF(D12="L1",$L$3,IF(D12="L2",$L$4,$L$5)) -> 1044648.5
A13: E100011 | B13: 1160686 | C13: 70987 | D13: L3 | E13: 45144 | F13: =IF(D13="L1",$L$3,IF(D13="L2",$L$4,$L$5)) -> 1044648.5
A14: E100012 | B14: 1060040 | C14: 94821 | D14: L3 | E14: 44306 | F14: =IF(D14="L1",$L$3,IF(D14="L2",$L$4,$L$5)) -> 1044648.5
A15: E100013 | B15: 1163414 | C15: 116603 | D15: L3 | E15: 44732 | F15: =IF(D15="L1",$L$3,IF(D15="L2",$L$4,$L$5)) -> 1044648.5
A16: E100014 | B16: 532901 | C16: 57968 | D16: L1 | E16: 44308 | F16: =IF(D16="L1",$L$3,IF(D16="L2",$L$4,$L$5)) -> 499723.04
A17: E100015 | B17: 422000 | C17: 29980 | D17: L1 | E17: 44491 | F17: =IF(D17="L1",$L$3,IF(D17="L2",$L$4,$L$5)) -> 499723.04
... A3201: E103199 | B3201: 1096637 | C3201: 87480 | D3201: L3 | E3201: 45281 | F3201: =IF(D3201="L1",$L$3,IF(D3201="L2",$L$4,$L$5)) -> 1044648.5

Sheet engagement_pivot
A3: Employee_ID | B3: Average of engagement_score | C3: Sum of engagement_score | D3: Average of manager_support | E3: Average of work_life_balance
A4: E100000 | B4: 2.3333333 | C4: 7 | D4: 2.6666667 | E4: 3
A5: E100001 | B5: 2.6666667 | C5: 8 | D5: 3.3333333 | E5: 3.6666667
A6: E100002 | B6: 2 | C6: 6 | D6: 2.6666667 | E6: 3.3333333
A7: E100003 | B7: 2 | C7: 6 | D7: 2.6666667 | E7: 3.6666667
A8: E100004 | B8: 1.6666667 | C8: 5 | D8: 3.3333333 | E8: 4.3333333
A9: E100005 | B9: 4 | C9: 8 | D9: 3 | E9: 1.5
A10: E100006 | B10: 5 | C10: 5 | D10: 4 | E10: 5
A11: E100007 | B11: 2 | C11: 4 | D11: 2.5 | E11: 1
A12: E100008 | B12: 2 | C12: 2 | D12: 1 | E12: 2
A13: E100009 | B13: 3 | C13: 9 | D13: 4 | E13: 1.6666667
A14: E100010 | B14: 5 | C14: 15 | D14: 3 | E14: 3.3333333
A15: E100011 | B15: 2.5 | C15: 5 | D15: 1.5 | E15: 2.5
... A3204: Grand Total | B3204: 2.9976145 | C3204: 18849 | D3204: 2.9750318 | E3204: 3.0071565

Sheet data_notes
A1: Step | B1: Check Performed | C1: Observation | D1: Action | E1: Impact on Analysis
A2: Phase 1 – Step 1 | B2: Table grain validation | C2: Employees, attrition, and compensation are 1 row per employee; performance and engagement are multi-row | D2: Aggregate performance and engagement before joining | E2: Prevents double counting and biased metrics
A3: Phase 1 – Step 2 | B3: Join completeness check | C3: 100% of employees have matching attrition and compensation records | D3: Proceed without imputation or exclusion | E3: Ensures attrition and compensation analysis is reliable
A4: Phase 1 – Step 3 | B4: Exit reason missing value check | C4: Exit reasons are populated for all attrited employees; no missing exit reasons observed | D4: No imputation or recoding required; original exit reasons retained | E4: Enables reliable analysis of attrition drivers without data quality caveats
A5: Phase 1 – Step 4 | B5: Engagement survey response coverage | C5: All employees responded to at least one engagement survey; no missing engagement responses observed | D5: No imputation or response flag differentiation required | E5: Engagement metrics can be analyzed without non-response bias
A6: Phase 1 – Step 5 | B6: Analysis date selection | C6: Dataset covers records up to 2023 | D6: Fixed analysis date set to 31-Dec-2023 for tenure calculation | E6: Ensures consistent and reproducible tenure metrics
A7: Phase 1 – Step 6 | B7: Tenure calculation | C7: Tenure computed using hire and exit dates with fixed analysis date | D7: Created tenure_months in months and tenure buckets | E7: Enables early, mid, and late attrition analysis
A8: Phase 1 – Step 7 | B8: Pay vs performance alignment | C8: Salary and performance compared within salary bands | D8: Created categorical pay–performance index | E8: Enables identification of underpaid high performers and misaligned compensation
A9: Phase 1 – Step 8 | B9: Bias assessment | C9: Potential survivorship, attrition, and reporting biases identified | D9: Biases acknowledged and documented without adjustment | E9: Prevents overinterpretation of engagement, performance, and exit insights
A10: Phase 2 – Step 1 | B10: Employee base validation | C10: Row count equals distinct employee count; no unexpected NULLs | D10: Proceeded with employee_base as single source of truth | E10: Ensures all downstream attrition metrics are accurate and unbiased
A11: Phase 2 – Step 2 | B11: Attrition Rate | C11: Overall attrition rate ≈ 22.8%, within realistic industry range | D11: Attrition definition validated; joins and grain confirmed | E11: Increases confidence in downstream tenure, department, and pay–performance attrition insights
A12: Phase 2 – Step 3 | B12: Tenure-Based Risk Pattern | C12: Early-tenure attrition lower than expected; late-tenure attrition relatively stable | D12: Rejected hypothesis that attrition is driven mainly by onboarding failure | E12: Enables deeper investigation into pay-performance alignment and engagement during mid-tenure
... A19: Phase 2 – Step 8 | B19: Attrition by Engagement | C19: Lower engagement associated with higher attrition, though high engagement does not eliminate exits | D19: Treated engagement as a leading indicator rather than a causal guarantee | E19: Encourages proactive engagement monitoring over reactive retention actions
